Workbook

Sheet Summary
A1: GEARBOX LEADS - MASTER FILE, ALL 7 MARKETS
A2: 1,400 contacts | 1017 companies | 7 markets | zero duplicate people across markets
A3: Source: Apollo.io, batches pulled Aug 2026 | Filter the Leads tab by Market (column H) to work one market at a time
A5: BY MARKET
A6: Market | B6: Batch | C6: Contacts | D6: Companies | E6: Language / note
A7: Southern Africa | B7: 1 | C7: =COUNTIF(Leads!$H$2:$H$1401,A7) | D7: 134 | E7: English; ZA/Zambia/Botswana etc - mining & sugar heavy
A8: Lithuania | B8: 2 | C8: =COUNTIF(Leads!$H$2:$H$1401,A8) | D8: 145 | E8: English; EU, truck 10-15 days
A9: Cote d'Ivoire | B9: 3 | C9: =COUNTIF(Leads!$H$2:$H$1401,A9) | D9: 144 | E9: FRENCH mails; cocoa, mining, ports
A10: Turkey | B10: 4 | C10: =COUNTIF(Leads!$H$2:$H$1401,A10) | D10: 182 | E10: Turkish; home market
A11: Latvia | B11: 5 | C11: =COUNTIF(Leads!$H$2:$H$1401,A11) | D11: 137 | E11: English; EU, wood & machine builders
A12: Estonia | B12: 6 | C12: =COUNTIF(Leads!$H$2:$H$1401,A12) | D12: 144 | E12: English; EU, wood & machine builders
A13: Nigeria | B13: 7 | C13: =COUNTIF(Leads!$H$2:$H$1401,A13) | D13: 131 | E13: English; phone-first market, 80 direct numbers in file
A14: TOTAL | C14: =SUM(C7:C13) | D14: 1017
A16: BY SEGMENT
A17: Segment | B17: Contacts | C17: Companies
A18: Distributor | B18: =COUNTIF(Leads!$I$2:$I$1401,A18) | C18: 180
A19: Machine Builder | B19: =COUNTIF(Leads!$I$2:$I$1401,A19) | C19: 153
A20: Food & Agro | B20: =COUNTIF(Leads!$I$2:$I$1401,A20) | C20: 111
A21: Materials/Construction | B21: =COUNTIF(Leads!$I$2:$I$1401,A21) | C21: 73
A22: Materials/Packaging | B22: =COUNTIF(Leads!$I$2:$I$1401,A22) | C22: 78
A23: Wood/Timber | B23: =COUNTIF(Leads!$I$2:$I$1401,A23) | C23: 62
A24: Port/Energy | B24: =COUNTIF(Leads!$I$2:$I$1401,A24) | C24: 63
A25: Mining | B25: =COUNTIF(Leads!$I$2:$I$1401,A25) | C25: 14
A26: Agro-Processing | B26: =COUNTIF(Leads!$I$2:$I$1401,A26) | C26: 20
A27: Agro/Cement | B27: =COUNTIF(Leads!$I$2:$I$1401,A27) | C27: 28
A28: Wood/Packaging | B28: =COUNTIF(Leads!$I$2:$I$1401,A28) | C28: 27
A29: Steel & Metals | B29: =COUNTIF(Leads!$I$2:$I$1401,A29) | C29: 25
... A40: Agro/Food | B40: =COUNTIF(Leads!$I$2:$I$1401,A40) | C40: 6
A42: TRACKING (whole file)
A43: Status | B43: Count
A44: Emailed | B44: =COUNTIF(Leads!$U$2:$U$1401,A44)
A45: Replied | B45: =COUNTIF(Leads!$U$2:$U$1401,A45)
A46: Meeting | B46: =COUNTIF(Leads!$U$2:$U$1401,A46)
A47: Quoted | B47: =COUNTIF(Leads!$U$2:$U$1401,A47)
A48: Won | B48: =COUNTIF(Leads!$U$2:$U$1401,A48)
A49: Not interested | B49: =COUNTIF(Leads!$U$2:$U$1401,A49)
A51: HOW TO WORK THE MASTER FILE
A52: 1. This file merges your 7 market lists into one place. The single-market files still exist - pick ONE home for tracking (this file or the country files), do not tick both.
A53: 2. Work market by market: filter Leads by Market (column H). Language differs - Cote d'Ivoire is FRENCH, Turkey is TURKISH, the rest English. The Language column is per person.
A54: 3. Sending pace still applies PER DAY overall, not per market: max 20-30 emails/day from your Outlook, colleagues in BCC not CC. This file is roughly 3 months of steady sending.
A55: 4. Tier A = distributors, machine builders and (in Africa) cement/mining - recurring volume. Start each market with its Tier A rows.
A56: 5. Groups appear in several markets (Graanul, Stora Enso, Orkla, Intrac, Hansa-Flex, KG Knutsson, Dotnuva/Techvitas across the Baltics; global groups elsewhere): different people per country - fine to contact all, but not the same week.
A57: 6. A few emails are flagged 'extrapolated' in Notes - not Apollo-verified, use with care. Everyone else is verified.

Sheet Leads
A1: First name | B1: Last name | C1: Email address | D1: Company | E1: Title | F1: Country | G1: City | H1: Market | I1: Segment | J1: Tier | K1: Language | L1: LinkedIn | M1: Company domain | N1: Company phone | O1: Direct/Mobile phone | P1: Employees | Q1: Industry | R1: Suggested angle | S1: Salutation | T1: Name check | U1: Status | V1: Date sent | W1: Replied | X1: Notes
A2: Ivo | B2: Araujo | C2: ivo.araujo@centrocar.com | D2: CENTROCAR - Centro de Equipamentos Mecânicos S.A. | E2: General Manager Angola | F2: Angola | G2: Luanda | H2: Southern Africa | I2: Distributor | J2: A | K2: Portuguese | L2: http://www.linkedin.com/in/ivo-araujo-9470b849 | M2: centrocar.com | N2: +351 22 002 9150 | P2: 150 | Q2: machinery | R2: Stocking terms and margin - lead with the commercial offer to the MD/GM, not the spec sheet | S2: Sr.
A3: Luca | B3: Sassella | C3: luca.sassella@eats.ao | D3: E.A.T.S Metering Systems | E3: Managing Director | F3: Angola | H3: Southern Africa | I3: Distributor | J3: A | K3: Portuguese | L3: http://www.linkedin.com/in/luca-sassella-6b69765 | M3: eats.ao | N3: +244 931 878 469 | P3: 9 | Q3: oil & energy | R3: Stocking terms and margin - lead with the commercial offer to the MD/GM, not the spec sheet | S3: Sr.
A4: Eduardo | B4: Fernandez | C4: eduardo.fernandez@encom.it.ao | D4: ENCOM Lda. | E4: Managing Director | F4: Angola | G4: Luanda | H4: Southern Africa | I4: Distributor | J4: A | K4: Portuguese | L4: http://www.linkedin.com/in/edufernandez | M4: encom.it.ao | N4: +1 713-429-5084 | P4: 24 | Q4: oil & energy | R4: Stocking terms and margin - lead with the commercial offer to the MD/GM, not the spec sheet | S4: Sr.
A5: Jose | B5: Santos | C5: josesantos@enerline.ao | D5: ENERLINE, SA | E5: General Manager | F5: Angola | G5: Luanda | H5: Southern Africa | I5: Distributor | J5: A | K5: Portuguese | L5: http://www.linkedin.com/in/jose-santos-9193b9253 | M5: enerline.ao | P5: 250 | Q5: oil & energy | R5: Stocking terms and margin - lead with the commercial offer to the MD/GM, not the spec sheet | S5: Sr.
A6: Jose | B6: Garrido | C6: jlgarrido@elecnor.com | D6: Elecnor Group | E6: Director Geral Adjunto de Sucursal Angola | F6: Angola | G6: Luanda | H6: Southern Africa | I6: Distributor | J6: A | K6: Portuguese | L6: http://www.linkedin.com/in/jose-luis-garrido-34110623 | M6: grupoelecnor.com | P6: 29000 | Q6: construction | R6: Stocking terms and margin - lead with the commercial offer to the MD/GM, not the spec sheet | S6: Sr.
A7: Januario | B7: Cuela | C7: januario.cuela@gea.com | D7: GEA Group | E7: Branch Manager Angola | F7: Angola | H7: Southern Africa | I7: Distributor | J7: A | K7: Portuguese | L7: http://www.linkedin.com/in/januario-cuela-985a1538 | M7: gea.com | N7: +49 211 91360 | P7: 20000 | Q7: machinery | R7: Stocking terms and margin - lead with the commercial offer to the MD/GM, not the spec sheet | S7: Sr.
A8: Rayan | B8: Farhat | C8: rayan.farhat@industryhubangola.com | D8: Industryhub | E8: Managing Director and Founder | F8: Angola | G8: Luanda | H8: Southern Africa | I8: Distributor | J8: A | K8: Portuguese | L8: http://www.linkedin.com/in/rayan-farhat | M8: industryhubangola.com | P8: 11 | Q8: automotive | R8: Stocking terms and margin - lead with the commercial offer to the MD/GM, not the spec sheet | S8: Sr.
A9: Nasim | B9: Kayali | C9: n.kayali@mecanixsal.com | D9: Mega Mecanix | E9: General Manager | F9: Angola | H9: Southern Africa | I9: Distributor | J9: A | K9: Portuguese | L9: http://www.linkedin.com/in/nasim-kayali-0bbb2937 | M9: mecanixsal.com | N9: +961 5 950 866 | P9: 19 | Q9: machinery | R9: Stocking terms and margin - lead with the commercial offer to the MD/GM, not the spec sheet | S9: Sr.
A10: Paulo | B10: Rodrigues | C10: paulo.rodrigues@movicortes.pt | D10: Movicortes Angola | E10: General Manager | F10: Angola | G10: Luanda | H10: Southern Africa | I10: Distributor | J10: A | K10: Portuguese | L10: http://www.linkedin.com/in/paulo-rodrigues-a35823164 | M10: movicortesangola.com | P10: 7 | Q10: machinery | R10: Stocking terms and margin - lead with the commercial offer to the MD/GM, not the spec sheet | S10: Sr.
A11: Peter | B11: Mashangu | C11: peter.mashangu@nampak.com | D11: Nampak | E11: Managing Director | F11: Angola | G11: Luanda | H11: Southern Africa | I11: Distributor | J11: A | K11: Portuguese | L11: http://www.linkedin.com/in/peter-mashangu-394611159 | M11: nampak.com | N11: +27 11 719 6300 | P11: 2500 | Q11: packaging & containers | R11: Stocking terms and margin - lead with the commercial offer to the MD/GM, not the spec sheet | S11: Sr.
A12: Kitana | B12: Barbosa | C12: kbarbosa@nors.com | D12: Nors Group | E12: After Sales Director | F12: Angola | G12: Luanda | H12: Southern Africa | I12: Distributor | J12: A | K12: Portuguese | L12: http://www.linkedin.com/in/kitana-barbosa-b3b58486 | M12: nors.com | N12: +351 22 615 0320 | P12: 3200 | Q12: automotive | R12: Stocking terms and margin - lead with the commercial offer to the MD/GM, not the spec sheet | S12: Sr.ª | T12: Set to Ms. - confirm
A13: Jean | B13: Rodrigues | C13: jean-philippe.rodrigues@og3s-mecanica.com | D13: OG3S Mecanica Lda | E13: Executive Managing Director | F13: Angola | H13: Southern Africa | I13: Distributor | J13: A | K13: Portuguese | L13: http://www.linkedin.com/in/jean-philippe-rodrigues-a727b82b | M13: og3s-mecanica.com | P13: 35 | Q13: oil & energy | R13: Stocking terms and margin - lead with the commercial offer to the MD/GM, not the spec sheet | S13: Sr.
A14: Luis | B14: Almeida | C14: l.almeida@spie.com | D14: SPIE Global Services Energy | E14: Managing Director Angola & Mozambique | F14: Angola | G14: Luanda | H14: Southern Africa | I14: Distributor | J14: A | K14: Portuguese | L14: http://www.linkedin.com/in/luis-ferreira-de-almeida-34495338 | M14: spie.com | N14: +33 1 34 41 81 81 | P14: 5000 | Q14: oil & energy | R14: Stocking terms and margin - lead with the commercial offer to the MD/GM, not the spec sheet | S14: Sr.
A15: Nicolas | B15: Monville | C15: nicolas.monville@grouptfe.com | D15: TFE GROUP INC | E15: Managing Director | F15: Angola | H15: Southern Africa | I15: Distributor | J15: A | K15: Portuguese | L15: http://www.linkedin.com/in/nicolas-monville-411a6358 | M15: grouptfe.com | N15: +33 4 66 70 64 10 | P15: 45 | Q15: oil & energy | R15: Stocking terms and margin - lead with the commercial offer to the MD/GM, not the spec sheet | S15: Sr.
A16: Mathieu | B16: Wallach | C16: mwallach@welltec.com | D16: Welltec | E16: Sales Director and General Manager, Southern Africa | F16: Angola | H16: Southern Africa | I16: Distributor | J16: A | K16: Portuguese | L16: http://www.linkedin.com/in/mathieu-wallach-a9203a59 | M16: welltec.com | N16: +45 48 14 35 14 | P16: 740 | Q16: oil & energy | R16: Stocking terms and margin - lead with the commercial offer to the MD/GM, not the spec sheet | S16: Sr.
A17: Favor | B17: Marebole | C17: favor@appliedmetrology.co.za | D17: Applied Metrology Services (Pty) Ltd. | E17: Managing Director | F17: Botswana | H17: Southern Africa | I17: Distributor | J17: A | K17: English | L17: http://www.linkedin.com/in/favor-marebole-a060559 | M17: appliedmetrology.co.za | N17: +27 11 568 0386 | P17: 12 | Q17: machinery | R17: Stocking terms and margin - lead with the commercial offer to the MD/GM, not the spec sheet | S17: Mr. | T17: Unisex name - confirm Mr./Ms.
A18: Bofedile | B18: Moeti | C18: bmoeti@bts-bw.com | D18: Bofedile Tech Services (Pty) Ltd | E18: Managing Director | F18: Botswana | G18: Gaborone | H18: Southern Africa | I18: Distributor | J18: A | K18: English | L18: http://www.linkedin.com/in/bofedile-moeti-6b1b0447 | M18: bts-bw.com | P18: 6 | Q18: industrial automation | R18: Stocking terms and margin - lead with the commercial offer to the MD/GM, not the spec sheet | S18: Mr. | T18: Unisex name - confirm Mr./Ms.
A19: Wessel | B19: Wessels | C19: wessel@coastalhire.co.za | D19: Coastal Hire | E19: Managing Director | F19: Botswana | H19: Southern Africa | I19: Distributor | J19: A | K19: English | L19: http://www.linkedin.com/in/wessel-wessels-086569146 | M19: coastalhire.co.za | N19: +27 10 158 0525 | P19: 260 | Q19: construction / equipment hire | R19: Stocking terms and margin - lead with the commercial offer to the MD/GM, not the spec sheet | S19: Mr.
A20: Tichaona | B20: Ndhlovu | C20: tndhlovu@delswizgroup.com | D20: Delswiz Manufacturing (Pty) Limited | E20: Managing Director | F20: Botswana | G20: Gaborone | H20: Southern Africa | I20: Distributor | J20: A | K20: English | L20: http://www.linkedin.com/in/tichaona-ndhlovu-93212b141 | M20: delswizgroup.com | N20: +971 55 157 9261 | P20: 26 | Q20: mining & metals | R20: Stocking terms and margin - lead with the commercial offer to the MD/GM, not the spec sheet | S20: Mr.
A21: Clayton | B21: Davis | C21: clayton.davis@hansa-flex.com | D21: HANSA-FLEX AG | E21: General Manager | F21: Botswana | H21: Southern Africa | I21: Distributor | J21: A | K21: English | L21: http://www.linkedin.com/in/clayton-davis-a18a377b | M21: hansa-flex.de | N21: +49 42 1489070 | P21: 5200 | Q21: machinery / hydraulics | R21: Stocking terms and margin - lead with the commercial offer to the MD/GM, not the spec sheet | S21: Mr.
A22: Zayd | B22: Bhoyroo | C22: zayd@impex.co.bw | D22: Impex Group | E22: Assistant General Manager | F22: Botswana | H22: Southern Africa | I22: Distributor | J22: A | K22: English | L22: http://www.linkedin.com/in/zayd-bhoyroo-41419b161 | M22: impex.co.bw | P22: 26 | Q22: automotive / wholesale | R22: Stocking terms and margin - lead with the commercial offer to the MD/GM, not the spec sheet | S22: Mr.
A23: Sonny | B23: Morekisi | C23: sonnym@komatsu.co.za | D23: Komatsu Africa Holdings (Pty) Ltd | E23: Branch Manager | F23: Botswana | H23: Southern Africa | I23: Distributor | J23: A | K23: English | L23: http://www.linkedin.com/in/sonny-morekisi-9b921043 | M23: komatsu.co.za | P23: 360 | Q23: machinery | R23: Stocking terms and margin - lead with the commercial offer to the MD/GM, not the spec sheet | S23: Mr.
A24: Donovan | B24: Lendrum | C24: donovan@rotatingsolutions.co.bw | D24: Rotating Solutions Botswana | E24: Sales Director | F24: Botswana | G24: Gaborone | H24: Southern Africa | I24: Distributor | J24: A | K24: English | L24: http://www.linkedin.com/in/donovan-lendrum-906a6352 | M24: rotatingsolutions.co.bw | P24: 2 | Q24: industrial supply / bearings and lubricants | R24: Stocking terms and margin - lead with the commercial offer to the MD/GM, not the spec sheet | S24: Mr.
A25: Tshegofatso | B25: Mosweu | C25: tshegofatso@sptc.com.sa | D25: SPTC | E25: Assistant Manager Procurement | F25: Botswana | H25: Southern Africa | I25: Distributor | J25: A | K25: English | L25: http://www.linkedin.com/in/tshegofatso-mosweu-783017a1 | M25: sptc.com.sa | N25: +966 13 814 4624 | P25: 320 | Q25: electrical/electronic manufacturing | R25: Stocking terms and margin - lead with the commercial offer to the MD/GM, not the spec sheet | S25: Mr. | T25: Unisex name - confirm Mr./Ms.
A26: Justice | B26: Moilwa | C26: jmoilwa@zismoengineering.com | D26: ZISMO Engineering (Pty) Ltd. | E26: Managing Director | F26: Botswana | G26: Gaborone | H26: Southern Africa | I26: Distributor | J26: A | K26: English | L26: http://www.linkedin.com/in/justice-moilwa-859595ba | M26: zismoengineeing.com | N26: +267 393 2711 | P26: 58 | Q26: electrical/electronic manufacturing | R26: Stocking terms and margin - lead with the commercial offer to the MD/GM, not the spec sheet | S26: Mr.
A27: Michael | B27: Bentley | C27: m.bentley@actionautozambia.com | D27: ACTION AUTO ZAMBIA | E27: Managing Director | F27: Zambia | H27: Southern Africa | I27: Distributor | J27: A | K27: English | L27: http://www.linkedin.com/in/michael-bentley-69240073 | M27: actionautozambia.com | P27: 54 | Q27: automotive | R27: Stocking terms and margin - lead with the commercial offer to the MD/GM, not the spec sheet | S27: Mr. | X27: Sent 29-Jul-2026 07:53 from Outlook, cc Haffar, Kayacan, Nesren. Delivered, no bounce.
A28: Sajad | B28: Ahmed | C28: sajad@accessenergys.com | D28: Access Energy Solutions Pty Ltd | E28: MD | F28: Zambia | H28: Southern Africa | I28: Distributor | J28: A | K28: English | L28: http://www.linkedin.com/in/sajad-ahmed-2ba5b5112 | M28: accessenergys.com | P28: 4 | Q28: environmental services | R28: Stocking terms and margin - lead with the commercial offer to the MD/GM, not the spec sheet | S28: Mr. | X28: Sent 29-Jul-2026 07:56 from Outlook, cc Haffar, Kayacan, Nesren, Tahir. Delivered, no bounce.
A29: Dirk | B29: Wet | C29: dirk.dewet@biagroup.com | D29: BIA GROUP | E29: Project Operation Manager | F29: Zambia | G29: Lusaka | H29: Southern Africa | I29: Distributor | J29: A | K29: English | L29: http://www.linkedin.com/in/dirk-de-wet-8969b189 | M29: biagroup.com | N29: +32 2 689 28 11 | P29: 1300 | Q29: machinery | R29: Stocking terms and margin - lead with the commercial offer to the MD/GM, not the spec sheet | S29: Mr.
A30: Cobus | B30: Potgieter | C30: cobus@bldequipment.com | D30: BL&D Plant Hire & Sales | E30: Branch Manager | F30: Zambia | H30: Southern Africa | I30: Distributor | J30: A | K30: English | L30: http://www.linkedin.com/in/cobus-potgieter-68204494 | M30: bldequipment.com | P30: 76 | Q30: machinery | R30: Stocking terms and margin - lead with the commercial offer to the MD/GM, not the spec sheet | S30: Mr.
A31: Samson | B31: Chingozho | C31: samson.chingozho@bellequipment.com | D31: Bell Equipment Mining & Construction | E31: Managing Director | F31: Zambia | H31: Southern Africa | I31: Distributor | J31: A | K31: English | L31: http://www.linkedin.com/in/samson-chingozho-b584a212 | M31: bellequipment.com | N31: +27 35 907 9111 | P31: 3500 | Q31: machinery | R31: Stocking terms and margin - lead with the commercial offer to the MD/GM, not the spec sheet | S31: Mr.
A32: Bevin | B32: Samwata | C32: bevin.samwata@blumaq.com | D32: Blumaq, S.A. | E32: Branch Manager | F32: Zambia | G32: Kitwe | H32: Southern Africa | I32: Distributor | J32: A | K32: English | L32: http://www.linkedin.com/in/bevin-samwata-76765a64 | M32: blumaq.com | N32: +34 964 69 70 30 | P32: 250 | Q32: machinery | R32: Stocking terms and margin - lead with the commercial offer to the MD/GM, not the spec sheet | S32: Mr.
A33: Henry | B33: Kapesa | C33: henry@bordertecltd.com | D33: Bordertec Limited | E33: Managing Director | F33: Zambia | H33: Southern Africa | I33: Distributor | J33: A | K33: English | L33: http://www.linkedin.com/in/henry-kapesa-044b16aa | M33: bordertec.co.zm | P33: 5 | Q33: management consulting | R33: Stocking terms and margin - lead with the commercial offer to the MD/GM, not the spec sheet | S33: Mr.
A34: Jinu | B34: Raj | C34: jinu@dgc-africa.com | D34: DGC AFRICA | E34: General Manager | F34: Zambia | H34: Southern Africa | I34: Distributor | J34: A | K34: English | L34: http://www.linkedin.com/in/jinu-raj-b51a2b15a | M34: dgc-africa.com | N34: +27 16 421 3720 | P34: 200 | Q34: mining & metals | R34: Stocking terms and margin - lead with the commercial offer to the MD/GM, not the spec sheet | S34: Mr.
A35: Gregory | B35: Gavazzi | C35: greg@doppioequipment.com | D35: Doppio Mining Equipment | E35: Managing Director | F35: Zambia | H35: Southern Africa | I35: Distributor | J35: A | K35: English | L35: http://www.linkedin.com/in/gregory-gavazzi-97ba9713a | M35: doppioequipment.com | P35: 4 | Q35: mining & metals | R35: Stocking terms and margin - lead with the commercial offer to the MD/GM, not the spec sheet | S35: Mr.
A36: Chongo | B36: Mumba | C36: chongom@aoj-pump.com | D36: Hebei Aojin Machinery Co.,Ltd. | E36: Technical Sales Manager | F36: Zambia | H36: Southern Africa | I36: Distributor | J36: A | K36: English | L36: http://www.linkedin.com/in/chongo-mumba-13295520 | M36: aoj-pump.com | N36: +86 311 8880 2472 | P36: 150 | Q36: machinery | R36: Stocking terms and margin - lead with the commercial offer to the MD/GM, not the spec sheet | S36: Mr.
A37: Arne | B37: Thorkildsen | C37: arne.thorkildsen@hcmaf.com | D37: Hitachi Construction Machinery | E37: Branch Operations Manager | F37: Zambia | H37: Southern Africa | I37: Distributor | J37: A | K37: English | L37: http://www.linkedin.com/in/arne-thorkildsen-336b2b82 | M37: hitachicm.com | N37: +81 358-26-8100 | P37: 26000 | Q37: machinery | R37: Stocking terms and margin - lead with the commercial offer to the MD/GM, not the spec sheet | S37: Mr.
A38: Henri | B38: Wassink | C38: hendrik.wassink@liebherr.com | D38: Liebherr Group | E38: Managing Director - Administration | F38: Zambia | H38: Southern Africa | I38: Distributor | J38: A | K38: English | L38: http://www.linkedin.com/in/henri-wassink-60322140 | M38: liebherr.com | N38: +49 735 1410 | P38: 54000 | Q38: machinery | R38: Stocking terms and margin - lead with the commercial offer to the MD/GM, not the spec sheet | S38: Mr.
A39: Yoginder | B39: Singh | C39: yoginder@racsafrica.com | D39: R A Consulting Services (RACS) | E39: Workshop Manager | F39: Zambia | H39: Southern Africa | I39: Distributor | J39: A | K39: English | L39: http://www.linkedin.com/in/yoginder-singh-944003180 | M39: racsafrica.com | N39: +267 393 9773 | P39: 87 | Q39: information technology & services | R39: Stocking terms and margin - lead with the commercial offer to the MD/GM, not the spec sheet | S39: Mr.
A40: Simon | B40: Kazunda | C40: simon.kazunda@safekahya.com | D40: SAFE KAHYA Limited | E40: Managing Director | F40: Zambia | H40: Southern Africa | I40: Distributor | J40: A | K40: English | L40: http://www.linkedin.com/in/simon-kazunda-46655b21 | M40: safekahya.com | P40: 1 | Q40: electrical/electronic manufacturing | R40: Stocking terms and margin - lead with the commercial offer to the MD/GM, not the spec sheet | S40: Mr.
A41: Ashok | B41: Oza | C41: ashok@saroagri.co.zm | D41: Saro Agro Industrial Ltd | E41: Managing Director | F41: Zambia | H41: Southern Africa | I41: Distributor | J41: A | K41: English | L41: http://www.linkedin.com/in/ashok-oza-286ab513 | M41: sarozambia.com | N41: +1 260-241-4779 | P41: 300 | Q41: consumer goods | R41: Stocking terms and margin - lead with the commercial offer to the MD/GM, not the spec sheet | S41: Mr.
A42: Tim | B42: Mumba | C42: timmy.mumba@skmsltd.com | D42: Scamont and Karlsons Mining Solutions (SKMS) | E42: General Manager Sales & Technical | F42: Zambia | H42: Southern Africa | I42: Distributor | J42: A | K42: English | L42: http://www.linkedin.com/in/tim-mumba-49963488 | M42: skmsltd.com | P42: 16 | Q42: mining & metals | R42: Stocking terms and margin - lead with the commercial offer to the MD/GM, not the spec sheet | S42: Mr.
A43: Justin | B43: Ricquebourg | C43: justin.r@sszam.com | D43: Selected Supplies | E43: Group Managing Director | F43: Zambia | H43: Southern Africa | I43: Distributor | J43: A | K43: English | L43: http://www.linkedin.com/in/justin-de-ricquebourg-172539106 | M43: selectedsupplies.com | N43: +258 87 011 0660 | P43: 92 | Q43: retail | R43: Stocking terms and margin - lead with the commercial offer to the MD/GM, not the spec sheet | S43: Mr.
A44: Sean | B44: Bester | C44: sean.bester@selectedsupplies.com | D44: Selected Supplies | E44: Regional Commercial and Operations Manager | F44: Zambia | H44: Southern Africa | I44: Distributor | J44: A | K44: English | L44: http://www.linkedin.com/in/sean-bester-14570911a | M44: selectedsupplies.com | N44: +258 87 011 0660 | P44: 92 | Q44: retail | R44: Stocking terms and margin - lead with the commercial offer to the MD/GM, not the spec sheet | S44: Mr.
A45: Robert | B45: Chisenga | C45: robert.chisenga@sulzer.com | D45: Sulzer | E45: Managing Director | F45: Zambia | G45: Chingola | H45: Southern Africa | I45: Distributor | J45: A | K45: English | L45: http://www.linkedin.com/in/robert-chisenga-960b0887 | M45: sulzer.com | N45: +41 52 262 30 00 | P45: 14000 | Q45: machinery | R45: Stocking terms and margin - lead with the commercial offer to the MD/GM, not the spec sheet | S45: Mr.
A46: Madalitso | B46: Banda | C46: madalitso@unirate.co.zm | D46: Unirate Investments Limited | E46: Managing Director | F46: Zambia | H46: Southern Africa | I46: Distributor | J46: A | K46: English | L46: http://www.linkedin.com/in/madalitso-banda-bab64215 | M46: unirate.co.zm | P46: 21 | Q46: logistics & supply chain | R46: Stocking terms and margin - lead with the commercial offer to the MD/GM, not the spec sheet | S46: Mr. | T46: Unisex name - confirm Mr./Ms.
A47: Mlayana | B47: Jasmin | C47: mlayana@younique-engineering.com | D47: Younique Engineering Limited | E47: Co-Founder & Managing Director | F47: Zambia | G47: Lusaka | H47: Southern Africa | I47: Distributor | J47: A | K47: English | L47: http://www.linkedin.com/in/mlayanachisi | M47: younique-engineering.com | P47: 3 | Q47: machinery | R47: Stocking terms and margin - lead with the commercial offer to the MD/GM, not the spec sheet | S47: Mr. | T47: Unisex name - confirm Mr./Ms.
A48: Badr | B48: Zein | C48: badr.zein@dar.com | D48: Dar | E48: Mechanical Engineer | F48: Angola | G48: Luanda | H48: Southern Africa | I48: Mining/Construction | J48: B | K48: Portuguese | L48: http://www.linkedin.com/in/badr-zein-78a891109 | M48: dar.com | N48: +961 1 790 002 | P48: 14000 | Q48: design / civil engineering | R48: Downtime on plant and fleet drives - lead with lead time and availability | S48: Sr.
A49: Georges | B49: Stelly | C49: georges.stelly@dar.com | D49: Dar | E49: Mechanical Engineer | F49: Angola | G49: Luanda | H49: Southern Africa | I49: Mining/Construction | J49: B | K49: Portuguese | L49: http://www.linkedin.com/in/georges-stelly-980898196 | M49: dar.com | N49: +961 1 790 002 | P49: 14000 | Q49: design / civil engineering | R49: Downtime on plant and fleet drives - lead with lead time and availability | S49: Sr.
A50: Vitor | B50: Mendes | C50: vitor.mendes@esa-angola.com | D50: ESA - Engineering Services Angola | E50: Mechanical Engineer | F50: Angola | H50: Southern Africa | I50: Mining/Construction | J50: B | K50: Portuguese | L50: http://www.linkedin.com/in/vitor-mendes-586921b9 | P50: 61 | Q50: construction | R50: Downtime on plant and fleet drives - lead with lead time and availability | S50: Sr.
A51: Rosmely | B51: Diaz | C51: rosmely.diaz@elecnor.com | D51: Elecnor Group | E51: Mechanical Engineer | F51: Angola | H51: Southern Africa | I51: Mining/Construction | J51: B | K51: Portuguese | L51: http://www.linkedin.com/in/rosmely-diaz-b26a15171 | M51: grupoelecnor.com | P51: 29000 | Q51: construction | R51: Downtime on plant and fleet drives - lead with lead time and availability | S51: Sr.ª | T51: Set to Ms. - confirm
A52: Ernesto | B52: Manuel | C52: ernesto.manuel@endiama.co.ao | D52: Endiama | E52: Senior Procurement Manager | F52: Angola | G52: Luanda | H52: Southern Africa | I52: Mining/Construction | J52: B | K52: Portuguese | L52: http://www.linkedin.com/in/ernesto-manuel-9287b186 | M52: endiama.co.ao | N52: +244 222 334 585 | P52: 310 | Q52: mining & metals | R52: Downtime on plant and fleet drives - lead with lead time and availability | S52: Sr.
A53: Theuns | B53: Oosthuizen | C53: theuns.oosthuizen@ec-africa.com | D53: Equipment & Controls Africa | E53: Workshop Manager | F53: Angola | G53: Soyo | H53: Southern Africa | I53: Mining/Construction | J53: B | K53: Portuguese | L53: http://www.linkedin.com/in/theuns-oosthuizen-1292091a7 | M53: ec-africa.com | N53: +1 412-489-3000 | P53: 71 | Q53: oil & energy | R53: Downtime on plant and fleet drives - lead with lead time and availability | S53: Sr.
A54: Aguinaldo | B54: Antunes | C54: aguinaldoantunes@omatapalo.com | D54: Grupo Omatapalo | E54: Mechanical Engineer | F54: Angola | G54: Luanda | H54: Southern Africa | I54: Mining/Construction | J54: B | K54: Portuguese | L54: http://www.linkedin.com/in/agui-antunes | M54: omatapalo.com | P54: 12000 | Q54: construction | R54: Downtime on plant and fleet drives - lead with lead time and availability | S54: Sr.
A55: Pradeep | B55: Kukna | C55: pradeep.kukna@marlin.co.ao | D55: Marlin Natural Stones | E55: Workshop Manager | F55: Angola | G55: Lubango | H55: Southern Africa | I55: Mining/Construction | J55: B | K55: Portuguese | L55: http://www.linkedin.com/in/pradeep-kukna-210997173 | M55: marlin.co.ao | P55: 22 | Q55: mechanical or industrial engineering | R55: Downtime on plant and fleet drives - lead with lead time and availability | S55: Sr.
A56: Aurelio | B56: Numa | C56: aurelio.numa@metalosul.com | D56: Metalosul | E56: Mechanical Engineer | F56: Angola | G56: Luanda | H56: Southern Africa | I56: Mining/Construction | J56: B | K56: Portuguese | L56: http://www.linkedin.com/in/aur%c3%a9lio-livongue-numa-b620922bb | M56: metalosul.com | N56: +244 931 599 625 | P56: 170 | Q56: mining & metals | R56: Downtime on plant and fleet drives - lead with lead time and availability | S56: Sr.
A57: William | B57: Sebastian | C57: williams@odebrecht.com | D57: Odebrecht Engenharia & Construção | E57: Mechanical Engineer | F57: Angola | G57: Cabinda | H57: Southern Africa | I57: Mining/Construction | J57: B | K57: Portuguese | L57: http://www.linkedin.com/in/william-sebastian-3002852a8 | P57: 6800 | Q57: civil engineering | R57: Downtime on plant and fleet drives - lead with lead time and availability | S57: Sr.
A58: Antonio | B58: Zacarias | C58: antonio.zacarias@prometim.net | D58: PROMETIM | E58: Workshop Manager | F58: Angola | G58: Cacuaco | H58: Southern Africa | I58: Mining/Construction | J58: B | K58: Portuguese | L58: http://www.linkedin.com/in/ant%c3%b3nio-zacarias-b2131656 | M58: prometim.net | N58: +244 923 637 414 | P58: 350 | Q58: oil & energy | R58: Downtime on plant and fleet drives - lead with lead time and availability | S58: Sr.
A59: Dario | B59: Dantas | C59: dario.dantas@catoca.com | D59: Sociedade Mineira de Catoca | E59: Mechanical Engineer | F59: Angola | G59: Luanda | H59: Southern Africa | I59: Mining/Construction | J59: B | K59: Portuguese | L59: http://www.linkedin.com/in/dario-dantas-4755b1237 | M59: catoca.com | N59: +1 226-624-7001 | P59: 3000 | Q59: mining & metals | R59: Downtime on plant and fleet drives - lead with lead time and availability | S59: Sr.
A60: James | B60: Biggar | C60: james.biggar@technipfmc.com | D60: TechnipFMC | E60: Workshop Manager | F60: Angola | H60: Southern Africa | I60: Mining/Construction | J60: B | K60: Portuguese | L60: http://www.linkedin.com/in/james-biggar-0491a251 | M60: technipfmc.com | N60: +44 28 1591 4000 | P60: 21000 | Q60: oil & energy | R60: Downtime on plant and fleet drives - lead with lead time and availability | S60: Sr.
A61: Eugenia | B61: Domingos | C61: eugenia.domingos@technipfmc.com | D61: TechnipFMC | E61: Mechanical Engineer | F61: Angola | G61: Luanda | H61: Southern Africa | I61: Mining/Construction | J61: B | K61: Portuguese | L61: http://www.linkedin.com/in/eddomingos | M61: technipfmc.com | N61: +44 28 1591 4000 | P61: 21000 | Q61: oil & energy | R61: Downtime on plant and fleet drives - lead with lead time and availability | S61: Sr.ª | T61: Set to Ms. - confirm
A62: Seabi | B62: Sekhobe | C62: seabi.sekhobe@aeciworld.com | D62: AECI Mining | E62: Maintenance Manager | F62: Botswana | H62: Southern Africa | I62: Mining | J62: B | K62: English | L62: http://www.linkedin.com/in/seabi-sekhobe-68671840 | M62: aecimining.com | N62: +27 11 806 8700 | P62: 2500 | Q62: mining & metals | R62: Downtime cost per hour on mill and conveyor drives - lead with lead time and availability | S62: Mr. | T62: Unisex name - confirm Mr./Ms. | X62: Sent 29-Jul-2026 07:54 from Outlook, cc Haffar, Tahir, Kayacan, Nesren. Delivered, no bounce.
A63: Tlamelo | B63: Rapata | C63: trapata@amsgh.com | D63: African Mining Services | E63: Maintenance Manager | F63: Botswana | G63: Gaborone | H63: Southern Africa | I63: Mining | J63: B | K63: English | L63: http://www.linkedin.com/in/tlamelo-rapata-7a33a596 | M63: amsgh.com | N63: +233 30 261 1333 | P63: 670 | Q63: mining & metals | R63: Downtime cost per hour on mill and conveyor drives - lead with lead time and availability | S63: Mr. | T63: Unisex name - confirm Mr./Ms.
A64: Andries | B64: Garnett | C64: andries.garnett@bme.co.za | D64: BME, a Member of the Omnia Group | E64: Workshop Manager | F64: Botswana | H64: Southern Africa | I64: Mining | J64: B | K64: English | L64: http://www.linkedin.com/in/andries-garnett-056a401a0 | M64: bme.co.za | P64: 2000 | Q64: mining & metals | R64: Downtime cost per hour on mill and conveyor drives - lead with lead time and availability | S64: Mr.
A65: Sidney | B65: Kubuitsile | C65: sidney.kubuitsile@barminco.com.au | D65: Barminco | E65: Site Reliability Engineer | F65: Botswana | H65: Southern Africa | I65: Mining | J65: B | K65: English | L65: http://www.linkedin.com/in/sidney777 | M65: barminco.com.au | N65: +61 8 9416 1000 | P65: 4300 | Q65: mining & metals | R65: Downtime cost per hour on mill and conveyor drives - lead with lead time and availability | S65: Mr.
A66: Modise | B66: Moora | C66: mm1@botash.bw | D66: Botswana Ash | E66: Maintenance Manager | F66: Botswana | G66: Francistown | H66: Southern Africa | I66: Mining | J66: B | K66: English | L66: http://www.linkedin.com/in/modise-moora-7700b421 | M66: botash.bw | N66: +267 621 3210 | P66: 190 | Q66: chemicals | R66: Downtime cost per hour on mill and conveyor drives - lead with lead time and availability | S66: Mr. | T66: Unisex name - confirm Mr./Ms.
A67: Obakeng | B67: Matonyane | C67: omatonyane@debswana.bw | D67: Debswana Diamond Company | E67: Mechanical Engineer | F67: Botswana | H67: Southern Africa | I67: Mining | J67: B | K67: English | L67: http://www.linkedin.com/in/obakeng-matonyane-64081883 | M67: debswana.com | N67: +267 361 4200 | P67: 6200 | Q67: mining & metals | R67: Downtime cost per hour on mill and conveyor drives - lead with lead time and availability | S67: Mr. | T67: Unisex name - confirm Mr./Ms.
A68: Tebogo | B68: Tshane | C68: ttshane@debswana.bw | D68: Debswana Diamond Company | E68: Plant Manager | F68: Botswana | H68: Southern Africa | I68: Mining | J68: B | K68: English | L68: http://www.linkedin.com/in/tebogo-tshane-p-eng-b7284020 | M68: debswana.com | N68: +267 361 4200 | P68: 6200 | Q68: mining & metals | R68: Downtime cost per hour on mill and conveyor drives - lead with lead time and availability | S68: Mr. | T68: Unisex name - confirm Mr./Ms.
A69: Adam | B69: Masebola | C69: amasebola@debswana.bw | D69: Debswana Diamond Company | E69: Plant Manager | F69: Botswana | G69: Gaborone | H69: Southern Africa | I69: Mining | J69: B | K69: English | L69: http://www.linkedin.com/in/adam-masebola-b546b8121 | M69: debswana.com | N69: +267 361 4200 | P69: 6200 | Q69: mining & metals | R69: Downtime cost per hour on mill and conveyor drives - lead with lead time and availability | S69: Mr.
A70: Phemelo | B70: Tshenolo | C70: ptshenolo@debswana.bw | D70: Debswana Diamond Company | E70: Project Mechanical Engineer | F70: Botswana | H70: Southern Africa | I70: Mining | J70: B | K70: English | L70: http://www.linkedin.com/in/phemelo-tshenolo-84881666 | M70: debswana.com | N70: +267 361 4200 | P70: 6200 | Q70: mining & metals | R70: Downtime cost per hour on mill and conveyor drives - lead with lead time and availability | S70: Mr. | T70: Unisex name - confirm Mr./Ms.
A71: Badiri | B71: Keitumetse | C71: bkeitumetse@debswana.bw | D71: Debswana Diamond Company | E71: Project Procurement Manager | F71: Botswana | H71: Southern Africa | I71: Mining | J71: B | K71: English | L71: http://www.linkedin.com/in/badirikeitumetse | M71: debswana.com | N71: +267 361 4200 | P71: 6200 | Q71: mining & metals | R71: Downtime cost per hour on mill and conveyor drives - lead with lead time and availability | S71: Mr. | T71: Unisex name - confirm Mr./Ms.
A72: Kago | B72: Morale | C72: kmorale@debswana.bw | D72: Debswana Diamond Company | E72: Engineering Manager Electrical | F72: Botswana | H72: Southern Africa | I72: Mining | J72: B | K72: English | L72: http://www.linkedin.com/in/kago-morale-pr-eng-pmp-70383a110 | M72: debswana.com | N72: +267 361 4200 | P72: 6200 | Q72: mining & metals | R72: Downtime cost per hour on mill and conveyor drives - lead with lead time and availability | S72: Mr. | T72: Unisex name - confirm Mr./Ms.
A73: Gwere | B73: Albert | C73: agwere@debswana.bw | D73: Debswana Diamond Company | E73: Senior Engineering Manager | F73: Botswana | H73: Southern Africa | I73: Mining | J73: B | K73: English | L73: http://www.linkedin.com/in/gwere-albert-7473968a | M73: debswana.com | N73: +267 361 4200 | P73: 6200 | Q73: mining & metals | R73: Downtime cost per hour on mill and conveyor drives - lead with lead time and availability | S73: Mr. | T73: Unisex name - confirm Mr./Ms.
A74: Keene | B74: Nkoane | C74: knkoane@debswana.bw | D74: Debswana Diamond Company | E74: Senior Engineering Manager at Debswana Diamond Company | F74: Botswana | H74: Southern Africa | I74: Mining | J74: B | K74: English | L74: http://www.linkedin.com/in/keene-nkoane-a4ba2893 | M74: debswana.com | N74: +267 361 4200 | P74: 6200 | Q74: mining & metals | R74: Downtime cost per hour on mill and conveyor drives - lead with lead time and availability | S74: Mr. | T74: Unisex name - confirm Mr./Ms.
A75: Omphile | B75: Mafunye | C75: omafunye@debswana.bw | D75: Debswana Diamond Company | E75: Principal Engineer-Mechanical | F75: Botswana | G75: Gaborone | H75: Southern Africa | I75: Mining | J75: B | K75: English | L75: http://www.linkedin.com/in/omphile-mafunye-58364238 | M75: debswana.com | N75: +267 361 4200 | P75: 6200 | Q75: mining & metals | R75: Downtime cost per hour on mill and conveyor drives - lead with lead time and availability | S75: Mr. | T75: Unisex name - confirm Mr./Ms.
A76: Kevin | B76: Tladiyamoroba | C76: ktladiyamoroba@debswana.bw | D76: Debswana Diamond Company | E76: Mining Manager - Technical Services | F76: Botswana | H76: Southern Africa | I76: Mining | J76: B | K76: English | L76: http://www.linkedin.com/in/kevin-tladiyamoroba | M76: debswana.com | N76: +267 361 4200 | P76: 6200 | Q76: mining & metals | R76: Downtime cost per hour on mill and conveyor drives - lead with lead time and availability | S76: Mr.
A77: Edwin | B77: Sesinyi | C77: edwin@minergycoal.com | D77: Minergy Ltd | E77: Mechanical Engineer | F77: Botswana | H77: Southern Africa | I77: Mining | J77: B | K77: English | L77: http://www.linkedin.com/in/edwin-sesinyi-92187736 | M77: minergycoal.com | N77: +267 397 2891 | P77: 19 | Q77: mining & metals | R77: Downtime cost per hour on mill and conveyor drives - lead with lead time and availability | S77: Mr.
A78: Mothusi | B78: Makwape | C78: mmakwape@mcm.co.bw | D78: Morupule Coal Mine | E78: Mine Reliability Engineer | F78: Botswana | H78: Southern Africa | I78: Mining | J78: B | K78: English | L78: http://www.linkedin.com/in/mothusi-makwape-bb323447 | M78: mcm.co.bw | N78: +267 492 0251 | P78: 900 | Q78: mining & metals | R78: Downtime cost per hour on mill and conveyor drives - lead with lead time and availability | S78: Mr. | T78: Unisex name - confirm Mr./Ms.
A79: Oaitse | B79: Medupe | C79: omedupe@mcm.co.bw | D79: Morupule Coal Mine | E79: Plant Manager | F79: Botswana | H79: Southern Africa | I79: Mining | J79: B | K79: English | L79: http://www.linkedin.com/in/oaitse-medupe-b140098a | M79: mcm.co.bw | N79: +267 492 0251 | P79: 900 | Q79: mining & metals | R79: Downtime cost per hour on mill and conveyor drives - lead with lead time and availability | S79: Mr. | T79: Unisex name - confirm Mr./Ms.
A80: Kabo | B80: Malebang | C80: kmalebang@mcm.co.bw | D80: Morupule Coal Mine | E80: Technical Services Manager | F80: Botswana | H80: Southern Africa | I80: Mining | J80: B | K80: English | L80: http://www.linkedin.com/in/kabo-malebang-79513645 | M80: mcm.co.bw | N80: +267 492 0251 | P80: 900 | Q80: mining & metals | R80: Downtime cost per hour on mill and conveyor drives - lead with lead time and availability | S80: Mr. | T80: Unisex name - confirm Mr./Ms.
A81: Onnete | B81: Raditsi | C81: onnete.raditsi@sandfire.com.au | D81: Sandfire | E81: Reliability Engineer | F81: Botswana | G81: Maun | H81: Southern Africa | I81: Mining | J81: B | K81: English | L81: http://www.linkedin.com/in/onnete-raditsi-270a7ba3 | M81: sandfire.com.au | N81: +61 8 6430 3800 | P81: 1300 | Q81: mining & metals | R81: Downtime cost per hour on mill and conveyor drives - lead with lead time and availability | S81: Mr. | T81: Unisex name - confirm Mr./Ms.
A82: Teto | B82: Ntswaneng | C82: teto.ntswaneng@sandfire.com.au | D82: Sandfire | E82: Reliability Engineer | F82: Botswana | G82: Ghanzi | H82: Southern Africa | I82: Mining | J82: B | K82: English | L82: http://www.linkedin.com/in/teto-ntswaneng-403391b1 | M82: sandfire.com.au | N82: +61 8 6430 3800 | P82: 1300 | Q82: mining & metals | R82: Downtime cost per hour on mill and conveyor drives - lead with lead time and availability | S82: Mr. | T82: Unisex name - confirm Mr./Ms.
A83: Airborne | B83: Clark | C83: airbornec@umsint.com | D83: UMS Group (United Mining Services) | E83: Mechanical Engineer | F83: Botswana | G83: Gaborone | H83: Southern Africa | I83: Mining | J83: B | K83: English | L83: http://www.linkedin.com/in/airborne-clark-505158223 | M83: umsint.com | N83: +27 11 445 4300 | P83: 450 | Q83: mining & metals | R83: Downtime cost per hour on mill and conveyor drives - lead with lead time and availability | S83: Mr.
A84: Chimuka | B84: Christopher | C84: cchimuka@barrick.com | D84: Barrick Mining Corporation | E84: Assistant Maintenance Manager | F84: Zambia | G84: Solwezi | H84: Southern Africa | I84: Mining | J84: B | K84: English | L84: http://www.linkedin.com/in/christopher-chimuka-8661ba63 | M84: barrick.com | N84: +1 416-861-9911 | P84: 6500 | Q84: mining & metals | R84: Downtime cost per hour on mill and conveyor drives - lead with lead time and availability | S84: Mr. | T84: Unisex name - confirm Mr./Ms.
A85: Anton | B85: Khoroshev | C85: anton.khoroshev@fqml.com | D85: First Quantum Minerals | E85: Plant Maintenance Manager | F85: Zambia | G85: Solwezi | H85: Southern Africa | I85: Mining | J85: B | K85: English | L85: http://www.linkedin.com/in/anton-khoroshev-460264b6 | M85: first-quantum.com | N85: +1 416-361-6400 | P85: 20000 | Q85: mining & metals | R85: Downtime cost per hour on mill and conveyor drives - lead with lead time and availability | S85: Mr.
A86: Theuns | B86: Hamman | C86: theuns.hamman@fqml.com | D86: First Quantum Minerals | E86: Engineering Manager Process Plant | F86: Zambia | G86: Solwezi | H86: Southern Africa | I86: Mining | J86: B | K86: English | L86: http://www.linkedin.com/in/theuns-hamman-45781484 | M86: first-quantum.com | N86: +1 416-361-6400 | P86: 20000 | Q86: mining & metals | R86: Downtime cost per hour on mill and conveyor drives - lead with lead time and availability | S86: Mr.
A87: Sylvester | B87: Mulanshoka | C87: sylvester.mulanshoka@fqml.com | D87: First Quantum Minerals | E87: Senior Reliability Engineer | F87: Zambia | H87: Southern Africa | I87: Mining | J87: B | K87: English | L87: http://www.linkedin.com/in/sylvester-mulanshoka-822229a6 | M87: first-quantum.com | N87: +1 416-361-6400 | P87: 20000 | Q87: mining & metals | R87: Downtime cost per hour on mill and conveyor drives - lead with lead time and availability | S87: Mr.
A88: Lutoba | B88: Kayamba | C88: lutoba.kayamba@fqml.com | D88: First Quantum Minerals | E88: Senior Reliability Engineer | F88: Zambia | G88: Solwezi | H88: Southern Africa | I88: Mining | J88: B | K88: English | L88: http://www.linkedin.com/in/lutoba-kayamba-b04539128 | M88: first-quantum.com | N88: +1 416-361-6400 | P88: 20000 | Q88: mining & metals | R88: Downtime cost per hour on mill and conveyor drives - lead with lead time and availability | S88: Mr. | T88: Unisex name - confirm Mr./Ms.
A89: Ernest | B89: Tembo | C89: ernest.tembo@fqml.com | D89: First Quantum Minerals | E89: Senior Reliability Engineer | F89: Zambia | G89: Lusaka | H89: Southern Africa | I89: Mining | J89: B | K89: English | L89: http://www.linkedin.com/in/ernest-tembo-9321ba1b3 | M89: first-quantum.com | N89: +1 416-361-6400 | P89: 20000 | Q89: mining & metals | R89: Downtime cost per hour on mill and conveyor drives - lead with lead time and availability | S89: Mr.
A90: Wesley | B90: Yowela | C90: wesley.yowela@fqml.com | D90: First Quantum Minerals | E90: Reliability Engineer | F90: Zambia | G90: Lusaka | H90: Southern Africa | I90: Mining | J90: B | K90: English | L90: http://www.linkedin.com/in/wesley-yowela-8b4072242 | M90: first-quantum.com | N90: +1 416-361-6400 | P90: 20000 | Q90: mining & metals | R90: Downtime cost per hour on mill and conveyor drives - lead with lead time and availability | S90: Mr.
A91: Mildred | B91: Kapika | C91: mildred.kapika@fqml.com | D91: First Quantum Minerals | E91: Reliability Engineer | F91: Zambia | G91: Mufulira | H91: Southern Africa | I91: Mining | J91: B | K91: English | L91: http://www.linkedin.com/in/mildred-kapika-8073a4216 | M91: first-quantum.com | N91: +1 416-361-6400 | P91: 20000 | Q91: mining & metals | R91: Downtime cost per hour on mill and conveyor drives - lead with lead time and availability | S91: Ms. | T91: Set to Ms. - confirm
A92: Jane | B92: George | C92: jane.george@fqml.com | D92: First Quantum Minerals | E92: Reliability Engineer | F92: Zambia | H92: Southern Africa | I92: Mining | J92: B | K92: English | L92: http://www.linkedin.com/in/jane-george-40b42315b | M92: first-quantum.com | N92: +1 416-361-6400 | P92: 20000 | Q92: mining & metals | R92: Downtime cost per hour on mill and conveyor drives - lead with lead time and availability | S92: Ms. | T92: Set to Ms. - confirm
A93: Michael | B93: Mumamba | C93: michael.mumamba@fqml.com | D93: First Quantum Minerals | E93: Reliability Engineer | F93: Zambia | H93: Southern Africa | I93: Mining | J93: B | K93: English | L93: http://www.linkedin.com/in/michael-mumamba-3562a6212 | M93: first-quantum.com | N93: +1 416-361-6400 | P93: 20000 | Q93: mining & metals | R93: Downtime cost per hour on mill and conveyor drives - lead with lead time and availability | S93: Mr.
A94: Dalitso | B94: Ngoma | C94: dalitso.ngoma@fqml.com | D94: First Quantum Minerals | E94: Reliability Engineer | F94: Zambia | H94: Southern Africa | I94: Mining | J94: B | K94: English | L94: http://www.linkedin.com/in/dalitso-ngoma-37a43692 | M94: first-quantum.com | N94: +1 416-361-6400 | P94: 20000 | Q94: mining & metals | R94: Downtime cost per hour on mill and conveyor drives - lead with lead time and availability | S94: Mr. | T94: Unisex name - confirm Mr./Ms.
A95: Isaac | B95: Kabula | C95: isaac.kabula@fqml.com | D95: First Quantum Minerals | E95: Maintenance Reliability Engineer | F95: Zambia | H95: Southern Africa | I95: Mining | J95: B | K95: English | L95: http://www.linkedin.com/in/isaac-kabula-23b3b31ab | M95: first-quantum.com | N95: +1 416-361-6400 | P95: 20000 | Q95: mining & metals | R95: Downtime cost per hour on mill and conveyor drives - lead with lead time and availability | S95: Mr.
A96: Bright | B96: Kamawu | C96: bright.kamawu@fqml.com | D96: First Quantum Minerals | E96: Reliability Engineer, Electrical | F96: Zambia | H96: Southern Africa | I96: Mining | J96: B | K96: English | L96: http://www.linkedin.com/in/brightkamawu | M96: first-quantum.com | N96: +1 416-361-6400 | P96: 20000 | Q96: mining & metals | R96: Downtime cost per hour on mill and conveyor drives - lead with lead time and availability | S96: Mr.
A97: Vinod | B97: Purohit | C97: vinod.purohit@kcm.co.zm | D97: Konkola Copper Mines plc | E97: Maintenance Manager | F97: Zambia | G97: Chingola | H97: Southern Africa | I97: Mining | J97: B | K97: English | L97: http://www.linkedin.com/in/vinod-kumar-purohit-328a546b | M97: kcm.co.zm | N97: +260 21 2350604 | P97: 14000 | Q97: mining & metals | R97: Downtime cost per hour on mill and conveyor drives - lead with lead time and availability | S97: Mr.
A98: Laison | B98: Malindi | C98: laison.malindi@kcm.co.zm | D98: Konkola Copper Mines plc | E98: Plant Manager | F98: Zambia | H98: Southern Africa | I98: Mining | J98: B | K98: English | L98: http://www.linkedin.com/in/laison-malindi-528a0947 | M98: kcm.co.zm | N98: +260 21 2350604 | P98: 14000 | Q98: mining & metals | R98: Downtime cost per hour on mill and conveyor drives - lead with lead time and availability | S98: Mr. | T98: Unisex name - confirm Mr./Ms.
A99: Yoram | B99: Kapai | C99: yoram.kapai@kcm.co.zm | D99: Konkola Copper Mines plc | E99: Plant Manager | F99: Zambia | H99: Southern Africa | I99: Mining | J99: B | K99: English | L99: http://www.linkedin.com/in/yoram-kapai-75760522 | M99: kcm.co.zm | N99: +260 21 2350604 | P99: 14000 | Q99: mining & metals | R99: Downtime cost per hour on mill and conveyor drives - lead with lead time and availability | S99: Mr.
A100: Franklin | B100: Ngandu | C100: franklin.ngandu@kcm.co.zm | D100: Konkola Copper Mines plc | E100: Plant Manager | F100: Zambia | H100: Southern Africa | I100: Mining | J100: B | K100: English | L100: http://www.linkedin.com/in/franklin-bwalya-ngandu-4a0a0678 | M100: kcm.co.zm | N100: +260 21 2350604 | P100: 14000 | Q100: mining & metals | R100: Downtime cost per hour on mill and conveyor drives - lead with lead time and availability | S100: Mr.
...

Sheet Read me
A1: HOW TO USE THIS FILE
A3: MASTER FILE - all 7 of your market lists in one workbook: Southern Africa, Lithuania, Cote d'Ivoire, Turkey, Latvia, Estonia, Nigeria. 1,400 people, no duplicates across markets.
A5: The single-market files still exist in the repo. IMPORTANT: pick one place to track progress - either this master file or the per-country files - and stick to it, otherwise your Status columns will disagree.
A7: LEADS tab - filter by Market (column H) to work one market at a time. Every row keeps its original Tier, Suggested angle, Salutation and Notes from the country file.
A8: LANGUAGE: Cote d'Ivoire rows are FRENCH, Turkey rows TURKISH, everything else English. Check the Language column before writing.
A9: DIRECT/MOBILE PHONE: filled for 80 Nigeria contacts (Apollo phone reveals). Other markets show only the company switchboard - say the word if you want phone reveals for them too.
A10: NAME CHECK (orange): unisex names (mainly Cote d'Ivoire and Nigeria) - glance at the LinkedIn photo before writing Mr./Ms.
A12: TIER A = distributors, machine builders, cement/mining. TIER B = plants (spares business).
A14: Track in the yellow columns (Status / Date sent / Replied / Notes). Summary counts recalculate when Excel opens the file.
A16: Reminders that apply everywhere:
A17: - Max 20-30 emails per day total from your Outlook, colleagues in BCC not CC.
A18: - A handful of emails are marked 'extrapolated' in Notes - not verified, use with care.
... A20: - Payment risk in Nigeria and West Africa: confirmed LC or advance for first orders, never open account.
