Workbook

Sheet Summary
A1: Gearbox Leads - Batch 1
A2: Botswana | Zambia | Angola - every contact has an Apollo-verified work email
A4: By country
A5: Country | B5: Contacts
A6: Botswana | B6: =COUNTIF(Leads!$E$2:$E$201,A6)
A7: Zambia | B7: =COUNTIF(Leads!$E$2:$E$201,A7)
A8: Angola | B8: =COUNTIF(Leads!$E$2:$E$201,A8)
A9: Total | B9: =SUM(B6:B8)
A11: By segment
A12: Segment | B12: Contacts
A13: Distributor | B13: =COUNTIF(Leads!$G$2:$G$201,A13)
A14: Mining | B14: =COUNTIF(Leads!$G$2:$G$201,A14)
A15: Mining/Construction | B15: =COUNTIF(Leads!$G$2:$G$201,A15)
A16: Agro/Cement | B16: =COUNTIF(Leads!$G$2:$G$201,A16)
A17: Agro/Food | B17: =COUNTIF(Leads!$G$2:$G$201,A17)
A18: Energy/Oil&Gas | B18: =COUNTIF(Leads!$G$2:$G$201,A18)
A19: Energy/Logistics | B19: =COUNTIF(Leads!$G$2:$G$201,A19)
A20: Total | B20: =SUM(B13:B19)
A22: By priority tier - work A first
A23: Tier | B23: What it is | C23: Contacts
A24: A | B24: Distributors and dealers - resell, stock, buy repeatedly | C24: =COUNTIF(Leads!$H$2:$H$201,A24)
A25: B | B25: Mining - highest spend, downtime costs them per hour | C25: =COUNTIF(Leads!$H$2:$H$201,A25)
A26: C | B26: Other end users - agro, cement, energy, logistics | C26: =COUNTIF(Leads!$H$2:$H$201,A26)
A27: Total | C27: =SUM(C24:C26)
A29: Send language
A30: Language | B30: Contacts
A31: English | B31: =COUNTIF(Leads!$K$2:$K$201,A31)
A32: Portuguese | B32: =COUNTIF(Leads!$K$2:$K$201,A32)
A33: Angola is Portuguese. Send those in English and they are wasted.
A35: Outreach progress - fills in as you update the Status column
A36: Status | B36: Contacts
A37: Not contacted | B37: =COUNTIF(Leads!$S$2:$S$201,A37)
A38: Emailed | B38: =COUNTIF(Leads!$S$2:$S$201,A38)
A39: Follow-up sent | B39: =COUNTIF(Leads!$S$2:$S$201,A39)
A40: Replied | B40: =COUNTIF(Leads!$S$2:$S$201,A40)
A41: Meeting booked | B41: =COUNTIF(Leads!$S$2:$S$201,A41)
A42: Quoted | B42: =COUNTIF(Leads!$S$2:$S$201,A42)
A43: Not interested | B43: =COUNTIF(Leads!$S$2:$S$201,A43)
A44: Bounced | B44: =COUNTIF(Leads!$S$2:$S$201,A44)
A45: Reply rate | B45: =IFERROR(COUNTIF(Leads!$S$2:$S$201,"Replied")/MAX(1,COUNTIF(Leads!$S$2:$S$201,"Emailed")+COUNTIF(Leads!$S$2:$S$201,"Follow-up sent")+COUNTIF(Leads!$S$2:$S$201,"Replied")),0)

Sheet Mails
A1: Emails by target group
A2: One email per group of similar companies. Filter the Mail column on the Leads tab to send one group at a time.
A3: Replace every [BRACKET] with your own details before sending. {First}, {Company} and {Country} are merge fields - your mail tool fills them from the Leads tab.
A5: Mail | B5: Target group | C5: Language | D5: Contacts | E5: Typical companies | F5: Subject line | G5: Email body | H5: Follow-up, day 4
A6: M1 | B6: Equipment & parts dealers | C6: English | D6: =COUNTIF(Leads!$I$2:$I$201,A6) | E6: Komatsu, Bell Equipment, Hitachi, Liebherr, Barloworld, Blumaq, BIA Group, Coastal Hire, Saro Agro, Action Auto, Impex | F6: Gearbox spares for the machines you support | G6: Hi {First}, {Company} keeps your customers' machines running - and a gearbox on backorder is what stops one for six weeks. We supply industrial and mobile gearboxes: [helical, bevel-helical, planetary, travel and swing drives]. Stock on the shelf, [X] days into {Country}. Most dealers we work with hold a small consignment of the units they replace most often, so a breakdown becomes a same-week fix instead of a six-week import. Can I send our range and dealer pricing? [YOUR NAME] [YOUR COMPANY] | [PHONE] | H6: Did the range list reach you? Happy to quote the three units you replace most often - no obligation.
A7: M2 | B7: Industrial & engineering suppliers | C7: English | D7: =COUNTIF(Leads!$I$2:$I$201,A7) | E7: ZISMO Engineering, Rotating Solutions, Sulzer, HANSA-FLEX, Selected Supplies, SKMS, Younique Engineering, Delswiz, DGC Africa, Bordertec, Access Energy | F7: Gearbox supply partner for {Company} | G7: Hi {First}, When your client's drive fails, the job is won or lost on how fast you can put a gearbox on site. We supply [helical, bevel-helical, worm and planetary] units, plus made-to-drawing replacements for [SEW, Flender, Bonfiglioli, Nord] - [X] days into {Country}, at trade pricing for resellers. We supply through local partners, not around them. The client stays yours. Worth a short call? I can send the range and trade terms first. [YOUR NAME] [YOUR COMPANY] | [PHONE] | H7: Any drive enquiries open right now? Send me the nameplate and I'll come back with price and lead time the same day.
A8: M3 | B8: Distribuidores e fornecedores industriais | C8: Portuguese | D8: =COUNTIF(Leads!$I$2:$I$201,A8) | E8: Centrocar, Nors Group, OG3S Mecanica, Movicortes, Mega Mecanix, GEA Group, Industryhub, ENCOM, ENERLINE, Elecnor, SPIE | F8: Redutores para as maquinas que a {Company} assiste | G8: Ola {First}, A {Company} mantem as maquinas dos vossos clientes a trabalhar - e um redutor em falta e o que para uma maquina durante seis semanas. Fornecemos redutores industriais e moveis: [helicoidais, conicos, planetarios, comandos de translacao e rotacao]. Stock disponivel, [X] dias ate Angola. A maioria dos distribuidores com quem trabalhamos mantem um pequeno stock das unidades que mais substituem - assim uma avaria resolve-se na mesma semana. Posso enviar a nossa gama e precos de revenda? [SEU NOME] [SUA EMPRESA] | [TELEFONE] | H8: Recebeu a nossa gama? Posso orcamentar as tres unidades que mais substituem, sem compromisso.
A9: M4 | B9: Mining - maintenance & reliability | C9: English | D9: =COUNTIF(Leads!$I$2:$I$201,A9) | E9: First Quantum, Konkola Copper, Mopani, Debswana, Morupule Coal, Sandfire, Barrick, Minergy, Barminco, African Mining Services | F9: Gearbox lead times for {Company} | G9: Hi {First}, A failed mill or conveyor drive is measured in dollars an hour, and the usual answer from suppliers is "twelve weeks". We hold [helical, bevel-helical and planetary] gearboxes and supply drop-in replacements for [SEW, Flender, David Brown] - [X] days into {Country}, with rebuild-on-exchange. No pitch needed: send me the units on your critical spares list and I'll come back with price and lead time, so you have a second source on file before you need one. [YOUR NAME] [YOUR COMPANY] | [PHONE] | H9: Even one nameplate photo is enough - I'll quote it so you know where we sit on price and lead time.
A10: M5 | B10: Procurement & supply chain | C10: English | D10: =COUNTIF(Leads!$I$2:$I$201,A10) | E10: Procurement, purchasing, contracts and supply-chain contacts across the mining, agro, cement and energy accounts | F10: Second source for gearbox spares | G10: Hi {First}, Most gearbox spend in {Country} sits with one supplier on long lead times. That works until the unit is on backorder. We supply [helical, bevel-helical and planetary] gearboxes and drop-in replacements for [SEW, Flender, David Brown] - [X] days into {Country}, with rebuild-on-exchange. Happy to simply be quoted against as a second source. No switching required. Send me your gearbox line items and I'll return prices and lead times. What do you need from us to get on the vendor list? [YOUR NAME] [YOUR COMPANY] | [PHONE] | H10: Shall I send our company profile and compliance documents for vendor registration?
A11: M6 | B11: Mineracao e construcao - tecnico | C11: Portuguese | D11: =COUNTIF(Leads!$I$2:$I$201,A11) | E11: Sociedade Mineira de Catoca, Endiama, Grupo Omatapalo, Marlin Natural Stones, PROMETIM, Equipment & Controls, ESA, Metalosul, TechnipFMC | F11: Prazos de entrega de redutores para a {Company} | G11: Ola {First}, Uma avaria num redutor de moinho ou transportador conta-se em horas de paragem, e a resposta habitual dos fornecedores e "doze semanas". Temos em stock redutores [helicoidais, conicos e planetarios] e substituicoes compativeis com [SEW, Flender, David Brown] - [X] dias ate Angola, com recondicionamento por troca. Se me enviar as unidades da vossa lista de pecas criticas, respondo com preco e prazo, para terem uma segunda fonte registada antes de precisarem. [SEU NOME] [SUA EMPRESA] | [TELEFONE] | H11: Basta uma foto da chapa de caracteristicas - devolvo orcamento e prazo no mesmo dia.
A12: M7 | B12: Agro, food & cement plants | C12: English | D12: =COUNTIF(Leads!$I$2:$I$201,A12) | E12: National Milling, Olam, Cargill, Dangote, Chilanga Cement, Trade Kings, Varun Beverages, Botswana Meat Commission, Lactalis, PepsiCo, Coca-Cola, Irvine's | F12: Gearbox spares before your next shutdown | G12: Hi {First}, Plants like {Company} buy drive spares before the season, not during it - a gearbox failing mid-run costs far more than the part. We supply [helical, bevel-helical, planetary and shaft-mounted] gearboxes for mills, mixers, conveyors and elevators - [X] days into {Country}. If you tell me roughly when your next shutdown falls, I'll quote the units worth having on the shelf before it. [YOUR NAME] [YOUR COMPANY] | [PHONE] | H12: When is the next shutdown window? I'll work backwards from it so the parts land in time.
A13: M8 | B13: Agro-industria, bebidas e cimento | C13: Portuguese | D13: =COUNTIF(Leads!$I$2:$I$201,A13) | E13: Carrinho Group, Castel Africa, Refriango, Webcor Group, Unique Beverages, BEFCO, FOZKUDIA, Nampak, MAXAM | F13: Redutores antes da proxima paragem programada | G13: Ola {First}, Fabricas como a {Company} compram pecas de transmissao antes da campanha, nao durante - porque um redutor a falhar em producao custa muito mais do que a peca. Fornecemos redutores [helicoidais, conicos, planetarios e de eixo oco] para moinhos, misturadoras, transportadores e elevadores - [X] dias ate Angola. Se me indicar a data da proxima paragem, orcamento as unidades que deveriam estar em stock antes disso. [SEU NOME] [SUA EMPRESA] | [TELEFONE] | H13: Quando esta prevista a proxima paragem? Trabalho a partir dessa data para as pecas chegarem a tempo.
A14: M9 | B14: Energy, utilities & logistics | C14: English | D14: =COUNTIF(Leads!$I$2:$I$201,A14) | E14: ZESCO, Copperbelt Energy, Botswana Power, Vivo Energy, Puma Energy, Juba Transport, SABOT, Simba Group, Africa Global Logistics, Lake Oil | F14: Drive and gearbox spares for {Company} | G14: Hi {First}, Fleet, materials-handling and plant drives fail the same way everywhere: the machine is available, the gearbox is not. We supply [industrial, shaft-mounted and mobile] gearboxes plus travel and swing drives - [X] days into {Country}, with rebuild-on-exchange. Send me the drives that give you the most trouble and I'll come back with price and lead time. If we're not better than your current source, nothing lost. [YOUR NAME] [YOUR COMPANY] | [PHONE] | H14: Do you keep a critical spares list? I'll price the gearbox lines on it so you have a benchmark.
A15: M10 | B15: Petroleo, gas e maritimo | C15: Portuguese | D15: =COUNTIF(Leads!$I$2:$I$201,A15) | E15: Azule Energy, TotalEnergies, ExxonMobil, Chevron, PETROBEL, Siemens Energy, Petromar, SONILS, CONSUL-MARINE, Pumangol, Core Laboratories, DOF | F15: Redutores e acionamentos para a {Company} | G15: Ola {First}, Em operacoes offshore e portuarias o equipamento costuma estar disponivel - o redutor e que nao esta. Fornecemos redutores [industriais, de eixo oco e maritimos], guinchos e acionamentos, com [X] dias ate Angola e recondicionamento por troca. Envie-me os acionamentos que mais problemas dao e respondo com preco e prazo. Se nao formos melhores que a vossa fonte actual, nao perdeu nada. Posso enviar o nosso perfil de empresa para registo de fornecedor? [SEU NOME] [SUA EMPRESA] | [TELEFONE] | H15: Precisa da documentacao de qualificacao de fornecedor? Envio hoje.
A16: M11 | B16: Compras e aprovisionamento | C16: Portuguese | D16: =COUNTIF(Leads!$I$2:$I$201,A16) | E16: Compradores e responsaveis de aprovisionamento na Azule Energy, TotalEnergies, ExxonMobil, Endiama, Petromar, TechnipFMC, Refriango, Webcor Group, Castel Africa | F16: Segunda fonte para redutores e pecas de transmissao | G16: Ola {First}, Grande parte da despesa em redutores em Angola concentra-se num unico fornecedor com prazos longos. Funciona ate a unidade estar em rutura. Fornecemos redutores [helicoidais, conicos e planetarios] e substituicoes compativeis com [SEW, Flender, David Brown] - [X] dias ate Angola, com recondicionamento por troca. Nao e preciso mudar de fornecedor: basta consultarem-nos como segunda fonte. Envie-me as vossas linhas de redutores e devolvo precos e prazos. O que precisam da nossa parte para o registo de fornecedor? [SEU NOME] [SUA EMPRESA] | [TELEFONE] | H16: Envio o perfil da empresa e a documentacao de conformidade para o registo de fornecedor?
A17: Total | D17: =SUM(D6:D16)

Sheet Leads
A1: First name | B1: Last name | C1: Title | D1: Company | E1: Country | F1: City | G1: Segment | H1: Tier | I1: Mail | J1: Email | K1: Language | L1: LinkedIn | M1: Company domain | N1: Company phone | O1: Employees | P1: Industry | Q1: Suggested angle | R1: Check | S1: Status | T1: Date sent | U1: Replied | V1: Notes
A2: Ivo | B2: Araujo | C2: General Manager Angola | D2: CENTROCAR - Centro de Equipamentos Mecânicos S.A. | E2: Angola | F2: Luanda | G2: Distributor | H2: A | I2: M3 | J2: ivo.araujo@centrocar.com | K2: Portuguese | L2: http://www.linkedin.com/in/ivo-araujo-9470b849 | M2: centrocar.com | N2: +351 22 002 9150 | O2: 150 | P2: machinery | Q2: Stocking terms and margin - lead with the commercial offer to the MD/GM, not the spec sheet | R2: HQ abroad (Portugal) - verify local buying authority | S2: Not contacted
A3: Luca | B3: Sassella | C3: Managing Director | D3: E.A.T.S Metering Systems | E3: Angola | G3: Distributor | H3: A | I3: M3 | J3: luca.sassella@eats.ao | K3: Portuguese | L3: http://www.linkedin.com/in/luca-sassella-6b69765 | M3: eats.ao | N3: +244 931 878 469 | O3: 9 | P3: oil & energy | Q3: Stocking terms and margin - lead with the commercial offer to the MD/GM, not the spec sheet | S3: Not contacted
A4: Eduardo | B4: Fernandez | C4: Managing Director | D4: ENCOM Lda. | E4: Angola | F4: Luanda | G4: Distributor | H4: A | I4: M3 | J4: eduardo.fernandez@encom.it.ao | K4: Portuguese | L4: http://www.linkedin.com/in/edufernandez | M4: encom.it.ao | N4: +1 713-429-5084 | O4: 24 | P4: oil & energy | Q4: Stocking terms and margin - lead with the commercial offer to the MD/GM, not the spec sheet | S4: Not contacted
A5: Jose | B5: Santos | C5: General Manager | D5: ENERLINE, SA | E5: Angola | F5: Luanda | G5: Distributor | H5: A | I5: M3 | J5: josesantos@enerline.ao | K5: Portuguese | L5: http://www.linkedin.com/in/jose-santos-9193b9253 | M5: enerline.ao | O5: 250 | P5: oil & energy | Q5: Stocking terms and margin - lead with the commercial offer to the MD/GM, not the spec sheet | S5: Not contacted
A6: Jose | B6: Garrido | C6: Director Geral Adjunto de Sucursal Angola | D6: Elecnor Group | E6: Angola | F6: Luanda | G6: Distributor | H6: A | I6: M3 | J6: jlgarrido@elecnor.com | K6: Portuguese | L6: http://www.linkedin.com/in/jose-luis-garrido-34110623 | M6: grupoelecnor.com | O6: 29000 | P6: construction | Q6: Stocking terms and margin - lead with the commercial offer to the MD/GM, not the spec sheet | R6: HQ abroad (Spain) - verify local buying authority | S6: Not contacted
A7: Januario | B7: Cuela | C7: Branch Manager Angola | D7: GEA Group | E7: Angola | G7: Distributor | H7: A | I7: M3 | J7: januario.cuela@gea.com | K7: Portuguese | L7: http://www.linkedin.com/in/januario-cuela-985a1538 | M7: gea.com | N7: +49 211 91360 | O7: 20000 | P7: machinery | Q7: Stocking terms and margin - lead with the commercial offer to the MD/GM, not the spec sheet | R7: HQ abroad (Germany) - verify local buying authority | S7: Not contacted
A8: Rayan | B8: Farhat | C8: Managing Director and Founder | D8: Industryhub | E8: Angola | F8: Luanda | G8: Distributor | H8: A | I8: M3 | J8: rayan.farhat@industryhubangola.com | K8: Portuguese | L8: http://www.linkedin.com/in/rayan-farhat | M8: industryhubangola.com | O8: 11 | P8: automotive | Q8: Stocking terms and margin - lead with the commercial offer to the MD/GM, not the spec sheet | S8: Not contacted
A9: Nasim | B9: Kayali | C9: General Manager | D9: Mega Mecanix | E9: Angola | G9: Distributor | H9: A | I9: M3 | J9: n.kayali@mecanixsal.com | K9: Portuguese | L9: http://www.linkedin.com/in/nasim-kayali-0bbb2937 | M9: mecanixsal.com | N9: +961 5 950 866 | O9: 19 | P9: machinery | Q9: Stocking terms and margin - lead with the commercial offer to the MD/GM, not the spec sheet | S9: Not contacted
A10: Paulo | B10: Rodrigues | C10: General Manager | D10: Movicortes Angola | E10: Angola | F10: Luanda | G10: Distributor | H10: A | I10: M3 | J10: paulo.rodrigues@movicortes.pt | K10: Portuguese | L10: http://www.linkedin.com/in/paulo-rodrigues-a35823164 | M10: movicortesangola.com | O10: 7 | P10: machinery | Q10: Stocking terms and margin - lead with the commercial offer to the MD/GM, not the spec sheet | S10: Not contacted
A11: Peter | B11: Mashangu | C11: Managing Director | D11: Nampak | E11: Angola | F11: Luanda | G11: Distributor | H11: A | I11: M3 | J11: peter.mashangu@nampak.com | K11: Portuguese | L11: http://www.linkedin.com/in/peter-mashangu-394611159 | M11: nampak.com | N11: +27 11 719 6300 | O11: 2500 | P11: packaging & containers | Q11: Stocking terms and margin - lead with the commercial offer to the MD/GM, not the spec sheet | R11: HQ abroad (South Africa) - verify local buying authority | S11: Not contacted
A12: Kitana | B12: Barbosa | C12: After Sales Director | D12: Nors Group | E12: Angola | F12: Luanda | G12: Distributor | H12: A | I12: M3 | J12: kbarbosa@nors.com | K12: Portuguese | L12: http://www.linkedin.com/in/kitana-barbosa-b3b58486 | M12: nors.com | N12: +351 22 615 0320 | O12: 3200 | P12: automotive | Q12: Stocking terms and margin - lead with the commercial offer to the MD/GM, not the spec sheet | R12: HQ abroad (Portugal) - verify local buying authority | S12: Not contacted
A13: Jean | B13: Rodrigues | C13: Executive Managing Director | D13: OG3S Mecanica Lda | E13: Angola | G13: Distributor | H13: A | I13: M3 | J13: jean-philippe.rodrigues@og3s-mecanica.com | K13: Portuguese | L13: http://www.linkedin.com/in/jean-philippe-rodrigues-a727b82b | M13: og3s-mecanica.com | O13: 35 | P13: oil & energy | Q13: Stocking terms and margin - lead with the commercial offer to the MD/GM, not the spec sheet | S13: Not contacted
A14: Luis | B14: Almeida | C14: Managing Director Angola & Mozambique | D14: SPIE Global Services Energy | E14: Angola | F14: Luanda | G14: Distributor | H14: A | I14: M3 | J14: l.almeida@spie.com | K14: Portuguese | L14: http://www.linkedin.com/in/luis-ferreira-de-almeida-34495338 | M14: spie.com | N14: +33 1 34 41 81 81 | O14: 5000 | P14: oil & energy | Q14: Stocking terms and margin - lead with the commercial offer to the MD/GM, not the spec sheet | R14: HQ abroad (France) - verify local buying authority | S14: Not contacted
A15: Nicolas | B15: Monville | C15: Managing Director | D15: TFE GROUP INC | E15: Angola | G15: Distributor | H15: A | I15: M3 | J15: nicolas.monville@grouptfe.com | K15: Portuguese | L15: http://www.linkedin.com/in/nicolas-monville-411a6358 | M15: grouptfe.com | N15: +33 4 66 70 64 10 | O15: 45 | P15: oil & energy | Q15: Stocking terms and margin - lead with the commercial offer to the MD/GM, not the spec sheet | R15: HQ abroad (France) - verify local buying authority | S15: Not contacted
A16: Mathieu | B16: Wallach | C16: Sales Director and General Manager, Southern Africa | D16: Welltec | E16: Angola | G16: Distributor | H16: A | I16: M3 | J16: mwallach@welltec.com | K16: Portuguese | L16: http://www.linkedin.com/in/mathieu-wallach-a9203a59 | M16: welltec.com | N16: +45 48 14 35 14 | O16: 740 | P16: oil & energy | Q16: Stocking terms and margin - lead with the commercial offer to the MD/GM, not the spec sheet | R16: HQ abroad (Denmark) - verify local buying authority | S16: Not contacted
A17: Favor | B17: Marebole | C17: Managing Director | D17: Applied Metrology Services (Pty) Ltd. | E17: Botswana | G17: Distributor | H17: A | I17: M2 | J17: favor@appliedmetrology.co.za | K17: English | L17: http://www.linkedin.com/in/favor-marebole-a060559 | M17: appliedmetrology.co.za | N17: +27 11 568 0386 | O17: 12 | P17: machinery | Q17: Stocking terms and margin - lead with the commercial offer to the MD/GM, not the spec sheet | R17: HQ abroad (South Africa) - verify local buying authority | S17: Not contacted
A18: Bofedile | B18: Moeti | C18: Managing Director | D18: Bofedile Tech Services (Pty) Ltd | E18: Botswana | F18: Gaborone | G18: Distributor | H18: A | I18: M2 | J18: bmoeti@bts-bw.com | K18: English | L18: http://www.linkedin.com/in/bofedile-moeti-6b1b0447 | M18: bts-bw.com | O18: 6 | P18: industrial automation | Q18: Stocking terms and margin - lead with the commercial offer to the MD/GM, not the spec sheet | S18: Not contacted
A19: Wessel | B19: Wessels | C19: Managing Director | D19: Coastal Hire | E19: Botswana | G19: Distributor | H19: A | I19: M1 | J19: wessel@coastalhire.co.za | K19: English | L19: http://www.linkedin.com/in/wessel-wessels-086569146 | M19: coastalhire.co.za | N19: +27 10 158 0525 | O19: 260 | P19: construction / equipment hire | Q19: Stocking terms and margin - lead with the commercial offer to the MD/GM, not the spec sheet | R19: HQ abroad (South Africa) - verify local buying authority | S19: Not contacted
A20: Tichaona | B20: Ndhlovu | C20: Managing Director | D20: Delswiz Manufacturing (Pty) Limited | E20: Botswana | F20: Gaborone | G20: Distributor | H20: A | I20: M2 | J20: tndhlovu@delswizgroup.com | K20: English | L20: http://www.linkedin.com/in/tichaona-ndhlovu-93212b141 | M20: delswizgroup.com | N20: +971 55 157 9261 | O20: 26 | P20: mining & metals | Q20: Stocking terms and margin - lead with the commercial offer to the MD/GM, not the spec sheet | S20: Not contacted
A21: Clayton | B21: Davis | C21: General Manager | D21: HANSA-FLEX AG | E21: Botswana | G21: Distributor | H21: A | I21: M2 | J21: clayton.davis@hansa-flex.com | K21: English | L21: http://www.linkedin.com/in/clayton-davis-a18a377b | M21: hansa-flex.de | N21: +49 42 1489070 | O21: 5200 | P21: machinery / hydraulics | Q21: Stocking terms and margin - lead with the commercial offer to the MD/GM, not the spec sheet | R21: HQ abroad (Germany) - verify local buying authority | S21: Not contacted
A22: Zayd | B22: Bhoyroo | C22: Assistant General Manager | D22: Impex Group | E22: Botswana | G22: Distributor | H22: A | I22: M1 | J22: zayd@impex.co.bw | K22: English | L22: http://www.linkedin.com/in/zayd-bhoyroo-41419b161 | M22: impex.co.bw | O22: 26 | P22: automotive / wholesale | Q22: Stocking terms and margin - lead with the commercial offer to the MD/GM, not the spec sheet | S22: Not contacted
A23: Sonny | B23: Morekisi | C23: Branch Manager | D23: Komatsu Africa Holdings (Pty) Ltd | E23: Botswana | G23: Distributor | H23: A | I23: M1 | J23: sonnym@komatsu.co.za | K23: English | L23: http://www.linkedin.com/in/sonny-morekisi-9b921043 | M23: komatsu.co.za | O23: 360 | P23: machinery | Q23: Stocking terms and margin - lead with the commercial offer to the MD/GM, not the spec sheet | R23: HQ abroad (South Africa) - verify local buying authority | S23: Not contacted
A24: Donovan | B24: Lendrum | C24: Sales Director | D24: Rotating Solutions Botswana | E24: Botswana | F24: Gaborone | G24: Distributor | H24: A | I24: M2 | J24: donovan@rotatingsolutions.co.bw | K24: English | L24: http://www.linkedin.com/in/donovan-lendrum-906a6352 | M24: rotatingsolutions.co.bw | O24: 2 | P24: industrial supply / bearings and lubricants | Q24: Stocking terms and margin - lead with the commercial offer to the MD/GM, not the spec sheet | S24: Not contacted
A25: Tshegofatso | B25: Mosweu | C25: Assistant Manager Procurement | D25: SPTC | E25: Botswana | G25: Distributor | H25: A | I25: M2 | J25: tshegofatso@sptc.com.sa | K25: English | L25: http://www.linkedin.com/in/tshegofatso-mosweu-783017a1 | M25: sptc.com.sa | N25: +966 13 814 4624 | O25: 320 | P25: electrical/electronic manufacturing | Q25: Stocking terms and margin - lead with the commercial offer to the MD/GM, not the spec sheet | R25: HQ abroad (Saudi Arabia) - verify local buying authority | S25: Not contacted
A26: Justice | B26: Moilwa | C26: Managing Director | D26: ZISMO Engineering (Pty) Ltd. | E26: Botswana | F26: Gaborone | G26: Distributor | H26: A | I26: M2 | J26: jmoilwa@zismoengineering.com | K26: English | L26: http://www.linkedin.com/in/justice-moilwa-859595ba | M26: zismoengineeing.com | N26: +267 393 2711 | O26: 58 | P26: electrical/electronic manufacturing | Q26: Stocking terms and margin - lead with the commercial offer to the MD/GM, not the spec sheet | S26: Not contacted
A27: Michael | B27: Bentley | C27: Managing Director | D27: ACTION AUTO ZAMBIA | E27: Zambia | G27: Distributor | H27: A | I27: M1 | J27: m.bentley@actionautozambia.com | K27: English | L27: http://www.linkedin.com/in/michael-bentley-69240073 | M27: actionautozambia.com | O27: 54 | P27: automotive | Q27: Stocking terms and margin - lead with the commercial offer to the MD/GM, not the spec sheet | S27: Not contacted
A28: Sajad | B28: Ahmed | C28: MD | D28: Access Energy Solutions Pty Ltd | E28: Zambia | G28: Distributor | H28: A | I28: M2 | J28: sajad@accessenergys.com | K28: English | L28: http://www.linkedin.com/in/sajad-ahmed-2ba5b5112 | M28: accessenergys.com | O28: 4 | P28: environmental services | Q28: Stocking terms and margin - lead with the commercial offer to the MD/GM, not the spec sheet | S28: Not contacted
A29: Dirk | B29: Wet | C29: Project Operation Manager | D29: BIA GROUP | E29: Zambia | F29: Lusaka | G29: Distributor | H29: A | I29: M1 | J29: dirk.dewet@biagroup.com | K29: English | L29: http://www.linkedin.com/in/dirk-de-wet-8969b189 | M29: biagroup.com | N29: +32 2 689 28 11 | O29: 1300 | P29: machinery | Q29: Stocking terms and margin - lead with the commercial offer to the MD/GM, not the spec sheet | R29: HQ abroad (Mauritius) - verify local buying authority | S29: Not contacted
A30: Cobus | B30: Potgieter | C30: Branch Manager | D30: BL&D Plant Hire & Sales | E30: Zambia | G30: Distributor | H30: A | I30: M1 | J30: cobus@bldequipment.com | K30: English | L30: http://www.linkedin.com/in/cobus-potgieter-68204494 | M30: bldequipment.com | O30: 76 | P30: machinery | Q30: Stocking terms and margin - lead with the commercial offer to the MD/GM, not the spec sheet | S30: Not contacted
A31: Samson | B31: Chingozho | C31: Managing Director | D31: Bell Equipment Mining & Construction | E31: Zambia | G31: Distributor | H31: A | I31: M1 | J31: samson.chingozho@bellequipment.com | K31: English | L31: http://www.linkedin.com/in/samson-chingozho-b584a212 | M31: bellequipment.com | N31: +27 35 907 9111 | O31: 3500 | P31: machinery | Q31: Stocking terms and margin - lead with the commercial offer to the MD/GM, not the spec sheet | R31: HQ abroad (South Africa) - verify local buying authority | S31: Not contacted
A32: Bevin | B32: Samwata | C32: Branch Manager | D32: Blumaq, S.A. | E32: Zambia | F32: Kitwe | G32: Distributor | H32: A | I32: M1 | J32: bevin.samwata@blumaq.com | K32: English | L32: http://www.linkedin.com/in/bevin-samwata-76765a64 | M32: blumaq.com | N32: +34 964 69 70 30 | O32: 250 | P32: machinery | Q32: Stocking terms and margin - lead with the commercial offer to the MD/GM, not the spec sheet | R32: HQ abroad (Spain) - verify local buying authority | S32: Not contacted
A33: Henry | B33: Kapesa | C33: Managing Director | D33: Bordertec Limited | E33: Zambia | G33: Distributor | H33: A | I33: M2 | J33: henry@bordertecltd.com | K33: English | L33: http://www.linkedin.com/in/henry-kapesa-044b16aa | M33: bordertec.co.zm | O33: 5 | P33: management consulting | Q33: Stocking terms and margin - lead with the commercial offer to the MD/GM, not the spec sheet | S33: Not contacted
A34: Jinu | B34: Raj | C34: General Manager | D34: DGC AFRICA | E34: Zambia | G34: Distributor | H34: A | I34: M2 | J34: jinu@dgc-africa.com | K34: English | L34: http://www.linkedin.com/in/jinu-raj-b51a2b15a | M34: dgc-africa.com | N34: +27 16 421 3720 | O34: 200 | P34: mining & metals | Q34: Stocking terms and margin - lead with the commercial offer to the MD/GM, not the spec sheet | R34: HQ abroad (South Africa) - verify local buying authority | S34: Not contacted
A35: Gregory | B35: Gavazzi | C35: Managing Director | D35: Doppio Mining Equipment | E35: Zambia | G35: Distributor | H35: A | I35: M1 | J35: greg@doppioequipment.com | K35: English | L35: http://www.linkedin.com/in/gregory-gavazzi-97ba9713a | M35: doppioequipment.com | O35: 4 | P35: mining & metals | Q35: Stocking terms and margin - lead with the commercial offer to the MD/GM, not the spec sheet | S35: Not contacted
A36: Chongo | B36: Mumba | C36: Technical Sales Manager | D36: Hebei Aojin Machinery Co.,Ltd. | E36: Zambia | G36: Distributor | H36: A | I36: M1 | J36: chongom@aoj-pump.com | K36: English | L36: http://www.linkedin.com/in/chongo-mumba-13295520 | M36: aoj-pump.com | N36: +86 311 8880 2472 | O36: 150 | P36: machinery | Q36: Stocking terms and margin - lead with the commercial offer to the MD/GM, not the spec sheet | R36: HQ abroad (China) - verify local buying authority | S36: Not contacted
A37: Arne | B37: Thorkildsen | C37: Branch Operations Manager | D37: Hitachi Construction Machinery | E37: Zambia | G37: Distributor | H37: A | I37: M1 | J37: arne.thorkildsen@hcmaf.com | K37: English | L37: http://www.linkedin.com/in/arne-thorkildsen-336b2b82 | M37: hitachicm.com | N37: +81 358-26-8100 | O37: 26000 | P37: machinery | Q37: Stocking terms and margin - lead with the commercial offer to the MD/GM, not the spec sheet | R37: HQ abroad (Japan) - verify local buying authority | S37: Not contacted
A38: Henri | B38: Wassink | C38: Managing Director - Administration | D38: Liebherr Group | E38: Zambia | G38: Distributor | H38: A | I38: M1 | J38: hendrik.wassink@liebherr.com | K38: English | L38: http://www.linkedin.com/in/henri-wassink-60322140 | M38: liebherr.com | N38: +49 735 1410 | O38: 54000 | P38: machinery | Q38: Stocking terms and margin - lead with the commercial offer to the MD/GM, not the spec sheet | R38: HQ abroad (Germany) - verify local buying authority | S38: Not contacted
A39: Yoginder | B39: Singh | C39: Workshop Manager | D39: R A Consulting Services (RACS) | E39: Zambia | G39: Distributor | H39: A | I39: M2 | J39: yoginder@racsafrica.com | K39: English | L39: http://www.linkedin.com/in/yoginder-singh-944003180 | M39: racsafrica.com | N39: +267 393 9773 | O39: 87 | P39: information technology & services | Q39: Stocking terms and margin - lead with the commercial offer to the MD/GM, not the spec sheet | S39: Not contacted
A40: Simon | B40: Kazunda | C40: Managing Director | D40: SAFE KAHYA Limited | E40: Zambia | G40: Distributor | H40: A | I40: M2 | J40: simon.kazunda@safekahya.com | K40: English | L40: http://www.linkedin.com/in/simon-kazunda-46655b21 | M40: safekahya.com | O40: 1 | P40: electrical/electronic manufacturing | Q40: Stocking terms and margin - lead with the commercial offer to the MD/GM, not the spec sheet | S40: Not contacted
A41: Ashok | B41: Oza | C41: Managing Director | D41: Saro Agro Industrial Ltd | E41: Zambia | G41: Distributor | H41: A | I41: M1 | J41: ashok@saroagri.co.zm | K41: English | L41: http://www.linkedin.com/in/ashok-oza-286ab513 | M41: sarozambia.com | N41: +1 260-241-4779 | O41: 300 | P41: consumer goods | Q41: Stocking terms and margin - lead with the commercial offer to the MD/GM, not the spec sheet | S41: Not contacted
A42: Tim | B42: Mumba | C42: General Manager Sales & Technical | D42: Scamont and Karlsons Mining Solutions (SKMS) | E42: Zambia | G42: Distributor | H42: A | I42: M2 | J42: timmy.mumba@skmsltd.com | K42: English | L42: http://www.linkedin.com/in/tim-mumba-49963488 | M42: skmsltd.com | O42: 16 | P42: mining & metals | Q42: Stocking terms and margin - lead with the commercial offer to the MD/GM, not the spec sheet | S42: Not contacted
A43: Justin | B43: Ricquebourg | C43: Group Managing Director | D43: Selected Supplies | E43: Zambia | G43: Distributor | H43: A | I43: M2 | J43: justin.r@sszam.com | K43: English | L43: http://www.linkedin.com/in/justin-de-ricquebourg-172539106 | M43: selectedsupplies.com | N43: +258 87 011 0660 | O43: 92 | P43: retail | Q43: Stocking terms and margin - lead with the commercial offer to the MD/GM, not the spec sheet | R43: HQ abroad (Mozambique) - verify local buying authority | S43: Not contacted
A44: Sean | B44: Bester | C44: Regional Commercial and Operations Manager | D44: Selected Supplies | E44: Zambia | G44: Distributor | H44: A | I44: M2 | J44: sean.bester@selectedsupplies.com | K44: English | L44: http://www.linkedin.com/in/sean-bester-14570911a | M44: selectedsupplies.com | N44: +258 87 011 0660 | O44: 92 | P44: retail | Q44: Stocking terms and margin - lead with the commercial offer to the MD/GM, not the spec sheet | R44: HQ abroad (Mozambique) - verify local buying authority | S44: Not contacted
A45: Robert | B45: Chisenga | C45: Managing Director | D45: Sulzer | E45: Zambia | F45: Chingola | G45: Distributor | H45: A | I45: M2 | J45: robert.chisenga@sulzer.com | K45: English | L45: http://www.linkedin.com/in/robert-chisenga-960b0887 | M45: sulzer.com | N45: +41 52 262 30 00 | O45: 14000 | P45: machinery | Q45: Stocking terms and margin - lead with the commercial offer to the MD/GM, not the spec sheet | R45: HQ abroad (Switzerland) - verify local buying authority | S45: Not contacted
A46: Madalitso | B46: Banda | C46: Managing Director | D46: Unirate Investments Limited | E46: Zambia | G46: Distributor | H46: A | I46: M2 | J46: madalitso@unirate.co.zm | K46: English | L46: http://www.linkedin.com/in/madalitso-banda-bab64215 | M46: unirate.co.zm | O46: 21 | P46: logistics & supply chain | Q46: Stocking terms and margin - lead with the commercial offer to the MD/GM, not the spec sheet | S46: Not contacted
A47: Mlayana | B47: Jasmin | C47: Co-Founder & Managing Director | D47: Younique Engineering Limited | E47: Zambia | F47: Lusaka | G47: Distributor | H47: A | I47: M2 | J47: mlayana@younique-engineering.com | K47: English | L47: http://www.linkedin.com/in/mlayanachisi | M47: younique-engineering.com | O47: 3 | P47: machinery | Q47: Stocking terms and margin - lead with the commercial offer to the MD/GM, not the spec sheet | S47: Not contacted
A48: Badr | B48: Zein | C48: Mechanical Engineer | D48: Dar | E48: Angola | F48: Luanda | G48: Mining/Construction | H48: B | I48: M6 | J48: badr.zein@dar.com | K48: Portuguese | L48: http://www.linkedin.com/in/badr-zein-78a891109 | M48: dar.com | N48: +961 1 790 002 | O48: 14000 | P48: design / civil engineering | Q48: Downtime on plant and fleet drives - lead with lead time and availability | R48: HQ abroad (Lebanon) - verify local buying authority | S48: Not contacted
A49: Georges | B49: Stelly | C49: Mechanical Engineer | D49: Dar | E49: Angola | F49: Luanda | G49: Mining/Construction | H49: B | I49: M6 | J49: georges.stelly@dar.com | K49: Portuguese | L49: http://www.linkedin.com/in/georges-stelly-980898196 | M49: dar.com | N49: +961 1 790 002 | O49: 14000 | P49: design / civil engineering | Q49: Downtime on plant and fleet drives - lead with lead time and availability | R49: HQ abroad (Lebanon) - verify local buying authority | S49: Not contacted
A50: Vitor | B50: Mendes | C50: Mechanical Engineer | D50: ESA - Engineering Services Angola | E50: Angola | G50: Mining/Construction | H50: B | I50: M6 | J50: vitor.mendes@esa-angola.com | K50: Portuguese | L50: http://www.linkedin.com/in/vitor-mendes-586921b9 | O50: 61 | P50: construction | Q50: Downtime on plant and fleet drives - lead with lead time and availability | S50: Not contacted
A51: Rosmely | B51: Diaz | C51: Mechanical Engineer | D51: Elecnor Group | E51: Angola | G51: Mining/Construction | H51: B | I51: M6 | J51: rosmely.diaz@elecnor.com | K51: Portuguese | L51: http://www.linkedin.com/in/rosmely-diaz-b26a15171 | M51: grupoelecnor.com | O51: 29000 | P51: construction | Q51: Downtime on plant and fleet drives - lead with lead time and availability | R51: HQ abroad (Spain) - verify local buying authority | S51: Not contacted
A52: Ernesto | B52: Manuel | C52: Senior Procurement Manager | D52: Endiama | E52: Angola | F52: Luanda | G52: Mining/Construction | H52: B | I52: M11 | J52: ernesto.manuel@endiama.co.ao | K52: Portuguese | L52: http://www.linkedin.com/in/ernesto-manuel-9287b186 | M52: endiama.co.ao | N52: +244 222 334 585 | O52: 310 | P52: mining & metals | Q52: Downtime on plant and fleet drives - lead with lead time and availability | S52: Not contacted
A53: Theuns | B53: Oosthuizen | C53: Workshop Manager | D53: Equipment & Controls Africa | E53: Angola | F53: Soyo | G53: Mining/Construction | H53: B | I53: M6 | J53: theuns.oosthuizen@ec-africa.com | K53: Portuguese | L53: http://www.linkedin.com/in/theuns-oosthuizen-1292091a7 | M53: ec-africa.com | N53: +1 412-489-3000 | O53: 71 | P53: oil & energy | Q53: Downtime on plant and fleet drives - lead with lead time and availability | R53: HQ abroad (United States) - verify local buying authority | S53: Not contacted
A54: Aguinaldo | B54: Antunes | C54: Mechanical Engineer | D54: Grupo Omatapalo | E54: Angola | F54: Luanda | G54: Mining/Construction | H54: B | I54: M6 | J54: aguinaldoantunes@omatapalo.com | K54: Portuguese | L54: http://www.linkedin.com/in/agui-antunes | M54: omatapalo.com | O54: 12000 | P54: construction | Q54: Downtime on plant and fleet drives - lead with lead time and availability | R54: HQ abroad (Austria) - verify local buying authority | S54: Not contacted
A55: Pradeep | B55: Kukna | C55: Workshop Manager | D55: Marlin Natural Stones | E55: Angola | F55: Lubango | G55: Mining/Construction | H55: B | I55: M6 | J55: pradeep.kukna@marlin.co.ao | K55: Portuguese | L55: http://www.linkedin.com/in/pradeep-kukna-210997173 | M55: marlin.co.ao | O55: 22 | P55: mechanical or industrial engineering | Q55: Downtime on plant and fleet drives - lead with lead time and availability | S55: Not contacted
A56: Aurelio | B56: Numa | C56: Mechanical Engineer | D56: Metalosul | E56: Angola | F56: Luanda | G56: Mining/Construction | H56: B | I56: M6 | J56: aurelio.numa@metalosul.com | K56: Portuguese | L56: http://www.linkedin.com/in/aur%c3%a9lio-livongue-numa-b620922bb | M56: metalosul.com | N56: +244 931 599 625 | O56: 170 | P56: mining & metals | Q56: Downtime on plant and fleet drives - lead with lead time and availability | S56: Not contacted
A57: William | B57: Sebastian | C57: Mechanical Engineer | D57: Odebrecht Engenharia & Construção | E57: Angola | F57: Cabinda | G57: Mining/Construction | H57: B | I57: M6 | J57: williams@odebrecht.com | K57: Portuguese | L57: http://www.linkedin.com/in/william-sebastian-3002852a8 | O57: 6800 | P57: civil engineering | Q57: Downtime on plant and fleet drives - lead with lead time and availability | R57: HQ abroad (Brazil) - verify local buying authority | S57: Not contacted
A58: Antonio | B58: Zacarias | C58: Workshop Manager | D58: PROMETIM | E58: Angola | F58: Cacuaco | G58: Mining/Construction | H58: B | I58: M6 | J58: antonio.zacarias@prometim.net | K58: Portuguese | L58: http://www.linkedin.com/in/ant%c3%b3nio-zacarias-b2131656 | M58: prometim.net | N58: +244 923 637 414 | O58: 350 | P58: oil & energy | Q58: Downtime on plant and fleet drives - lead with lead time and availability | S58: Not contacted
A59: Dario | B59: Dantas | C59: Mechanical Engineer | D59: Sociedade Mineira de Catoca | E59: Angola | F59: Luanda | G59: Mining/Construction | H59: B | I59: M6 | J59: dario.dantas@catoca.com | K59: Portuguese | L59: http://www.linkedin.com/in/dario-dantas-4755b1237 | M59: catoca.com | N59: +1 226-624-7001 | O59: 3000 | P59: mining & metals | Q59: Downtime on plant and fleet drives - lead with lead time and availability | S59: Not contacted
A60: James | B60: Biggar | C60: Workshop Manager | D60: TechnipFMC | E60: Angola | G60: Mining/Construction | H60: B | I60: M6 | J60: james.biggar@technipfmc.com | K60: Portuguese | L60: http://www.linkedin.com/in/james-biggar-0491a251 | M60: technipfmc.com | N60: +44 28 1591 4000 | O60: 21000 | P60: oil & energy | Q60: Downtime on plant and fleet drives - lead with lead time and availability | R60: HQ abroad (United Kingdom) - verify local buying authority | S60: Not contacted
A61: Eugenia | B61: Domingos | C61: Mechanical Engineer | D61: TechnipFMC | E61: Angola | F61: Luanda | G61: Mining/Construction | H61: B | I61: M6 | J61: eugenia.domingos@technipfmc.com | K61: Portuguese | L61: http://www.linkedin.com/in/eddomingos | M61: technipfmc.com | N61: +44 28 1591 4000 | O61: 21000 | P61: oil & energy | Q61: Downtime on plant and fleet drives - lead with lead time and availability | R61: HQ abroad (United Kingdom) - verify local buying authority | S61: Not contacted
A62: Seabi | B62: Sekhobe | C62: Maintenance Manager | D62: AECI Mining | E62: Botswana | G62: Mining | H62: B | I62: M4 | J62: seabi.sekhobe@aeciworld.com | K62: English | L62: http://www.linkedin.com/in/seabi-sekhobe-68671840 | M62: aecimining.com | N62: +27 11 806 8700 | O62: 2500 | P62: mining & metals | Q62: Downtime cost per hour on mill and conveyor drives - lead with lead time and availability | R62: HQ abroad (South Africa) - verify local buying authority | S62: Not contacted
A63: Tlamelo | B63: Rapata | C63: Maintenance Manager | D63: African Mining Services | E63: Botswana | F63: Gaborone | G63: Mining | H63: B | I63: M4 | J63: trapata@amsgh.com | K63: English | L63: http://www.linkedin.com/in/tlamelo-rapata-7a33a596 | M63: amsgh.com | N63: +233 30 261 1333 | O63: 670 | P63: mining & metals | Q63: Downtime cost per hour on mill and conveyor drives - lead with lead time and availability | R63: HQ abroad (Ghana) - verify local buying authority | S63: Not contacted
A64: Andries | B64: Garnett | C64: Workshop Manager | D64: BME, a Member of the Omnia Group | E64: Botswana | G64: Mining | H64: B | I64: M4 | J64: andries.garnett@bme.co.za | K64: English | L64: http://www.linkedin.com/in/andries-garnett-056a401a0 | M64: bme.co.za | O64: 2000 | P64: mining & metals | Q64: Downtime cost per hour on mill and conveyor drives - lead with lead time and availability | R64: HQ abroad (South Africa) - verify local buying authority | S64: Not contacted
A65: Sidney | B65: Kubuitsile | C65: Site Reliability Engineer | D65: Barminco | E65: Botswana | G65: Mining | H65: B | I65: M4 | J65: sidney.kubuitsile@barminco.com.au | K65: English | L65: http://www.linkedin.com/in/sidney777 | M65: barminco.com.au | N65: +61 8 9416 1000 | O65: 4300 | P65: mining & metals | Q65: Downtime cost per hour on mill and conveyor drives - lead with lead time and availability | R65: HQ abroad (Australia) - verify local buying authority | S65: Not contacted
A66: Modise | B66: Moora | C66: Maintenance Manager | D66: Botswana Ash | E66: Botswana | F66: Francistown | G66: Mining | H66: B | I66: M4 | J66: mm1@botash.bw | K66: English | L66: http://www.linkedin.com/in/modise-moora-7700b421 | M66: botash.bw | N66: +267 621 3210 | O66: 190 | P66: chemicals | Q66: Downtime cost per hour on mill and conveyor drives - lead with lead time and availability | S66: Not contacted
A67: Obakeng | B67: Matonyane | C67: Mechanical Engineer | D67: Debswana Diamond Company | E67: Botswana | G67: Mining | H67: B | I67: M4 | J67: omatonyane@debswana.bw | K67: English | L67: http://www.linkedin.com/in/obakeng-matonyane-64081883 | M67: debswana.com | N67: +267 361 4200 | O67: 6200 | P67: mining & metals | Q67: Downtime cost per hour on mill and conveyor drives - lead with lead time and availability | S67: Not contacted
A68: Tebogo | B68: Tshane | C68: Plant Manager | D68: Debswana Diamond Company | E68: Botswana | G68: Mining | H68: B | I68: M4 | J68: ttshane@debswana.bw | K68: English | L68: http://www.linkedin.com/in/tebogo-tshane-p-eng-b7284020 | M68: debswana.com | N68: +267 361 4200 | O68: 6200 | P68: mining & metals | Q68: Downtime cost per hour on mill and conveyor drives - lead with lead time and availability | S68: Not contacted
A69: Adam | B69: Masebola | C69: Plant Manager | D69: Debswana Diamond Company | E69: Botswana | F69: Gaborone | G69: Mining | H69: B | I69: M4 | J69: amasebola@debswana.bw | K69: English | L69: http://www.linkedin.com/in/adam-masebola-b546b8121 | M69: debswana.com | N69: +267 361 4200 | O69: 6200 | P69: mining & metals | Q69: Downtime cost per hour on mill and conveyor drives - lead with lead time and availability | S69: Not contacted
A70: Phemelo | B70: Tshenolo | C70: Project Mechanical Engineer | D70: Debswana Diamond Company | E70: Botswana | G70: Mining | H70: B | I70: M4 | J70: ptshenolo@debswana.bw | K70: English | L70: http://www.linkedin.com/in/phemelo-tshenolo-84881666 | M70: debswana.com | N70: +267 361 4200 | O70: 6200 | P70: mining & metals | Q70: Downtime cost per hour on mill and conveyor drives - lead with lead time and availability | S70: Not contacted
A71: Badiri | B71: Keitumetse | C71: Project Procurement Manager | D71: Debswana Diamond Company | E71: Botswana | G71: Mining | H71: B | I71: M5 | J71: bkeitumetse@debswana.bw | K71: English | L71: http://www.linkedin.com/in/badirikeitumetse | M71: debswana.com | N71: +267 361 4200 | O71: 6200 | P71: mining & metals | Q71: Downtime cost per hour on mill and conveyor drives - lead with lead time and availability | S71: Not contacted
A72: Kago | B72: Morale | C72: Engineering Manager Electrical | D72: Debswana Diamond Company | E72: Botswana | G72: Mining | H72: B | I72: M4 | J72: kmorale@debswana.bw | K72: English | L72: http://www.linkedin.com/in/kago-morale-pr-eng-pmp-70383a110 | M72: debswana.com | N72: +267 361 4200 | O72: 6200 | P72: mining & metals | Q72: Downtime cost per hour on mill and conveyor drives - lead with lead time and availability | S72: Not contacted
A73: Gwere | B73: Albert | C73: Senior Engineering Manager | D73: Debswana Diamond Company | E73: Botswana | G73: Mining | H73: B | I73: M4 | J73: agwere@debswana.bw | K73: English | L73: http://www.linkedin.com/in/gwere-albert-7473968a | M73: debswana.com | N73: +267 361 4200 | O73: 6200 | P73: mining & metals | Q73: Downtime cost per hour on mill and conveyor drives - lead with lead time and availability | S73: Not contacted
A74: Keene | B74: Nkoane | C74: Senior Engineering Manager at Debswana Diamond Company | D74: Debswana Diamond Company | E74: Botswana | G74: Mining | H74: B | I74: M4 | J74: knkoane@debswana.bw | K74: English | L74: http://www.linkedin.com/in/keene-nkoane-a4ba2893 | M74: debswana.com | N74: +267 361 4200 | O74: 6200 | P74: mining & metals | Q74: Downtime cost per hour on mill and conveyor drives - lead with lead time and availability | S74: Not contacted
A75: Omphile | B75: Mafunye | C75: Principal Engineer-Mechanical | D75: Debswana Diamond Company | E75: Botswana | F75: Gaborone | G75: Mining | H75: B | I75: M4 | J75: omafunye@debswana.bw | K75: English | L75: http://www.linkedin.com/in/omphile-mafunye-58364238 | M75: debswana.com | N75: +267 361 4200 | O75: 6200 | P75: mining & metals | Q75: Downtime cost per hour on mill and conveyor drives - lead with lead time and availability | S75: Not contacted
A76: Kevin | B76: Tladiyamoroba | C76: Mining Manager - Technical Services | D76: Debswana Diamond Company | E76: Botswana | G76: Mining | H76: B | I76: M4 | J76: ktladiyamoroba@debswana.bw | K76: English | L76: http://www.linkedin.com/in/kevin-tladiyamoroba | M76: debswana.com | N76: +267 361 4200 | O76: 6200 | P76: mining & metals | Q76: Downtime cost per hour on mill and conveyor drives - lead with lead time and availability | S76: Not contacted
A77: Edwin | B77: Sesinyi | C77: Mechanical Engineer | D77: Minergy Ltd | E77: Botswana | G77: Mining | H77: B | I77: M4 | J77: edwin@minergycoal.com | K77: English | L77: http://www.linkedin.com/in/edwin-sesinyi-92187736 | M77: minergycoal.com | N77: +267 397 2891 | O77: 19 | P77: mining & metals | Q77: Downtime cost per hour on mill and conveyor drives - lead with lead time and availability | S77: Not contacted
A78: Mothusi | B78: Makwape | C78: Mine Reliability Engineer | D78: Morupule Coal Mine | E78: Botswana | G78: Mining | H78: B | I78: M4 | J78: mmakwape@mcm.co.bw | K78: English | L78: http://www.linkedin.com/in/mothusi-makwape-bb323447 | M78: mcm.co.bw | N78: +267 492 0251 | O78: 900 | P78: mining & metals | Q78: Downtime cost per hour on mill and conveyor drives - lead with lead time and availability | S78: Not contacted
A79: Oaitse | B79: Medupe | C79: Plant Manager | D79: Morupule Coal Mine | E79: Botswana | G79: Mining | H79: B | I79: M4 | J79: omedupe@mcm.co.bw | K79: English | L79: http://www.linkedin.com/in/oaitse-medupe-b140098a | M79: mcm.co.bw | N79: +267 492 0251 | O79: 900 | P79: mining & metals | Q79: Downtime cost per hour on mill and conveyor drives - lead with lead time and availability | S79: Not contacted
A80: Kabo | B80: Malebang | C80: Technical Services Manager | D80: Morupule Coal Mine | E80: Botswana | G80: Mining | H80: B | I80: M4 | J80: kmalebang@mcm.co.bw | K80: English | L80: http://www.linkedin.com/in/kabo-malebang-79513645 | M80: mcm.co.bw | N80: +267 492 0251 | O80: 900 | P80: mining & metals | Q80: Downtime cost per hour on mill and conveyor drives - lead with lead time and availability | S80: Not contacted
A81: Onnete | B81: Raditsi | C81: Reliability Engineer | D81: Sandfire | E81: Botswana | F81: Maun | G81: Mining | H81: B | I81: M4 | J81: onnete.raditsi@sandfire.com.au | K81: English | L81: http://www.linkedin.com/in/onnete-raditsi-270a7ba3 | M81: sandfire.com.au | N81: +61 8 6430 3800 | O81: 1300 | P81: mining & metals | Q81: Downtime cost per hour on mill and conveyor drives - lead with lead time and availability | R81: HQ abroad (Australia) - verify local buying authority | S81: Not contacted
A82: Teto | B82: Ntswaneng | C82: Reliability Engineer | D82: Sandfire | E82: Botswana | F82: Ghanzi | G82: Mining | H82: B | I82: M4 | J82: teto.ntswaneng@sandfire.com.au | K82: English | L82: http://www.linkedin.com/in/teto-ntswaneng-403391b1 | M82: sandfire.com.au | N82: +61 8 6430 3800 | O82: 1300 | P82: mining & metals | Q82: Downtime cost per hour on mill and conveyor drives - lead with lead time and availability | R82: HQ abroad (Australia) - verify local buying authority | S82: Not contacted
A83: Airborne | B83: Clark | C83: Mechanical Engineer | D83: UMS Group (United Mining Services) | E83: Botswana | F83: Gaborone | G83: Mining | H83: B | I83: M4 | J83: airbornec@umsint.com | K83: English | L83: http://www.linkedin.com/in/airborne-clark-505158223 | M83: umsint.com | N83: +27 11 445 4300 | O83: 450 | P83: mining & metals | Q83: Downtime cost per hour on mill and conveyor drives - lead with lead time and availability | R83: HQ abroad (South Africa) - verify local buying authority | S83: Not contacted
A84: Chimuka | B84: Christopher | C84: Assistant Maintenance Manager | D84: Barrick Mining Corporation | E84: Zambia | F84: Solwezi | G84: Mining | H84: B | I84: M4 | J84: cchimuka@barrick.com | K84: English | L84: http://www.linkedin.com/in/christopher-chimuka-8661ba63 | M84: barrick.com | N84: +1 416-861-9911 | O84: 6500 | P84: mining & metals | Q84: Downtime cost per hour on mill and conveyor drives - lead with lead time and availability | R84: HQ abroad (Canada) - verify local buying authority | S84: Not contacted
A85: Anton | B85: Khoroshev | C85: Plant Maintenance Manager | D85: First Quantum Minerals | E85: Zambia | F85: Solwezi | G85: Mining | H85: B | I85: M4 | J85: anton.khoroshev@fqml.com | K85: English | L85: http://www.linkedin.com/in/anton-khoroshev-460264b6 | M85: first-quantum.com | N85: +1 416-361-6400 | O85: 20000 | P85: mining & metals | Q85: Downtime cost per hour on mill and conveyor drives - lead with lead time and availability | R85: HQ abroad (Canada) - verify local buying authority | S85: Not contacted
A86: Theuns | B86: Hamman | C86: Engineering Manager Process Plant | D86: First Quantum Minerals | E86: Zambia | F86: Solwezi | G86: Mining | H86: B | I86: M4 | J86: theuns.hamman@fqml.com | K86: English | L86: http://www.linkedin.com/in/theuns-hamman-45781484 | M86: first-quantum.com | N86: +1 416-361-6400 | O86: 20000 | P86: mining & metals | Q86: Downtime cost per hour on mill and conveyor drives - lead with lead time and availability | R86: HQ abroad (Canada) - verify local buying authority | S86: Not contacted
A87: Sylvester | B87: Mulanshoka | C87: Senior Reliability Engineer | D87: First Quantum Minerals | E87: Zambia | G87: Mining | H87: B | I87: M4 | J87: sylvester.mulanshoka@fqml.com | K87: English | L87: http://www.linkedin.com/in/sylvester-mulanshoka-822229a6 | M87: first-quantum.com | N87: +1 416-361-6400 | O87: 20000 | P87: mining & metals | Q87: Downtime cost per hour on mill and conveyor drives - lead with lead time and availability | R87: HQ abroad (Canada) - verify local buying authority | S87: Not contacted
A88: Lutoba | B88: Kayamba | C88: Senior Reliability Engineer | D88: First Quantum Minerals | E88: Zambia | F88: Solwezi | G88: Mining | H88: B | I88: M4 | J88: lutoba.kayamba@fqml.com | K88: English | L88: http://www.linkedin.com/in/lutoba-kayamba-b04539128 | M88: first-quantum.com | N88: +1 416-361-6400 | O88: 20000 | P88: mining & metals | Q88: Downtime cost per hour on mill and conveyor drives - lead with lead time and availability | R88: HQ abroad (Canada) - verify local buying authority | S88: Not contacted
A89: Ernest | B89: Tembo | C89: Senior Reliability Engineer | D89: First Quantum Minerals | E89: Zambia | F89: Lusaka | G89: Mining | H89: B | I89: M4 | J89: ernest.tembo@fqml.com | K89: English | L89: http://www.linkedin.com/in/ernest-tembo-9321ba1b3 | M89: first-quantum.com | N89: +1 416-361-6400 | O89: 20000 | P89: mining & metals | Q89: Downtime cost per hour on mill and conveyor drives - lead with lead time and availability | R89: HQ abroad (Canada) - verify local buying authority | S89: Not contacted
A90: Wesley | B90: Yowela | C90: Reliability Engineer | D90: First Quantum Minerals | E90: Zambia | F90: Lusaka | G90: Mining | H90: B | I90: M4 | J90: wesley.yowela@fqml.com | K90: English | L90: http://www.linkedin.com/in/wesley-yowela-8b4072242 | M90: first-quantum.com | N90: +1 416-361-6400 | O90: 20000 | P90: mining & metals | Q90: Downtime cost per hour on mill and conveyor drives - lead with lead time and availability | R90: HQ abroad (Canada) - verify local buying authority | S90: Not contacted
A91: Mildred | B91: Kapika | C91: Reliability Engineer | D91: First Quantum Minerals | E91: Zambia | F91: Mufulira | G91: Mining | H91: B | I91: M4 | J91: mildred.kapika@fqml.com | K91: English | L91: http://www.linkedin.com/in/mildred-kapika-8073a4216 | M91: first-quantum.com | N91: +1 416-361-6400 | O91: 20000 | P91: mining & metals | Q91: Downtime cost per hour on mill and conveyor drives - lead with lead time and availability | R91: HQ abroad (Canada) - verify local buying authority | S91: Not contacted
A92: Jane | B92: George | C92: Reliability Engineer | D92: First Quantum Minerals | E92: Zambia | G92: Mining | H92: B | I92: M4 | J92: jane.george@fqml.com | K92: English | L92: http://www.linkedin.com/in/jane-george-40b42315b | M92: first-quantum.com | N92: +1 416-361-6400 | O92: 20000 | P92: mining & metals | Q92: Downtime cost per hour on mill and conveyor drives - lead with lead time and availability | R92: HQ abroad (Canada) - verify local buying authority | S92: Not contacted
A93: Michael | B93: Mumamba | C93: Reliability Engineer | D93: First Quantum Minerals | E93: Zambia | G93: Mining | H93: B | I93: M4 | J93: michael.mumamba@fqml.com | K93: English | L93: http://www.linkedin.com/in/michael-mumamba-3562a6212 | M93: first-quantum.com | N93: +1 416-361-6400 | O93: 20000 | P93: mining & metals | Q93: Downtime cost per hour on mill and conveyor drives - lead with lead time and availability | R93: HQ abroad (Canada) - verify local buying authority | S93: Not contacted
A94: Dalitso | B94: Ngoma | C94: Reliability Engineer | D94: First Quantum Minerals | E94: Zambia | G94: Mining | H94: B | I94: M4 | J94: dalitso.ngoma@fqml.com | K94: English | L94: http://www.linkedin.com/in/dalitso-ngoma-37a43692 | M94: first-quantum.com | N94: +1 416-361-6400 | O94: 20000 | P94: mining & metals | Q94: Downtime cost per hour on mill and conveyor drives - lead with lead time and availability | R94: HQ abroad (Canada) - verify local buying authority | S94: Not contacted
A95: Isaac | B95: Kabula | C95: Maintenance Reliability Engineer | D95: First Quantum Minerals | E95: Zambia | G95: Mining | H95: B | I95: M4 | J95: isaac.kabula@fqml.com | K95: English | L95: http://www.linkedin.com/in/isaac-kabula-23b3b31ab | M95: first-quantum.com | N95: +1 416-361-6400 | O95: 20000 | P95: mining & metals | Q95: Downtime cost per hour on mill and conveyor drives - lead with lead time and availability | R95: HQ abroad (Canada) - verify local buying authority | S95: Not contacted
A96: Bright | B96: Kamawu | C96: Reliability Engineer, Electrical | D96: First Quantum Minerals | E96: Zambia | G96: Mining | H96: B | I96: M4 | J96: bright.kamawu@fqml.com | K96: English | L96: http://www.linkedin.com/in/brightkamawu | M96: first-quantum.com | N96: +1 416-361-6400 | O96: 20000 | P96: mining & metals | Q96: Downtime cost per hour on mill and conveyor drives - lead with lead time and availability | R96: HQ abroad (Canada) - verify local buying authority | S96: Not contacted
A97: Vinod | B97: Purohit | C97: Maintenance Manager | D97: Konkola Copper Mines plc | E97: Zambia | F97: Chingola | G97: Mining | H97: B | I97: M4 | J97: vinod.purohit@kcm.co.zm | K97: English | L97: http://www.linkedin.com/in/vinod-kumar-purohit-328a546b | M97: kcm.co.zm | N97: +260 21 2350604 | O97: 14000 | P97: mining & metals | Q97: Downtime cost per hour on mill and conveyor drives - lead with lead time and availability | S97: Not contacted
A98: Laison | B98: Malindi | C98: Plant Manager | D98: Konkola Copper Mines plc | E98: Zambia | G98: Mining | H98: B | I98: M4 | J98: laison.malindi@kcm.co.zm | K98: English | L98: http://www.linkedin.com/in/laison-malindi-528a0947 | M98: kcm.co.zm | N98: +260 21 2350604 | O98: 14000 | P98: mining & metals | Q98: Downtime cost per hour on mill and conveyor drives - lead with lead time and availability | S98: Not contacted
A99: Yoram | B99: Kapai | C99: Plant Manager | D99: Konkola Copper Mines plc | E99: Zambia | G99: Mining | H99: B | I99: M4 | J99: yoram.kapai@kcm.co.zm | K99: English | L99: http://www.linkedin.com/in/yoram-kapai-75760522 | M99: kcm.co.zm | N99: +260 21 2350604 | O99: 14000 | P99: mining & metals | Q99: Downtime cost per hour on mill and conveyor drives - lead with lead time and availability | S99: Not contacted
A100: Franklin | B100: Ngandu | C100: Plant Manager | D100: Konkola Copper Mines plc | E100: Zambia | G100: Mining | H100: B | I100: M4 | J100: franklin.ngandu@kcm.co.zm | K100: English | L100: http://www.linkedin.com/in/franklin-bwalya-ngandu-4a0a0678 | M100: kcm.co.zm | N100: +260 21 2350604 | O100: 14000 | P100: mining & metals | Q100: Downtime cost per hour on mill and conveyor drives - lead with lead time and availability | S100: Not contacted
...

Sheet Read me
A1: Gearbox Leads - Batch 1
A3: What this is
A4: 200 contacts in Botswana, Zambia and Angola who buy or resell industrial gearboxes.
A5: Every one has an Apollo-verified work email. No guessed addresses, no info@ catch-alls.
A6: Sourced from Apollo.io on 28 July 2026, across 134 companies.
A8: The Mails tab
A9: The 200 are grouped into 10 clusters of similar companies. Each cluster has its own short email,
A10: because a copper mine, an equipment dealer and a flour mill do not buy for the same reason.
A11: The Mail column on the Leads tab says which email each contact gets. Filter on it and send one
A12: cluster at a time.
A13: Before you send: replace every [BRACKET] with your own details - company name, product range,
A14: lead time in days, your name and phone. I do not know those, so I left them blank on purpose
... A51: Batch 4 - Namibia, DRC Copperbelt, Mozambique, Zimbabwe on the same industrial logic
