Workbook

Sheet Summary
A1: Gearbox Leads - Batch 1
A2: Botswana | Zambia | Angola - every contact has a verified email and a ready-to-send message
A4: By country
A5: Country | B5: Contacts
A6: Botswana | B6: =COUNTIF(Leads!$H$2:$H$201,A6)
A7: Zambia | B7: =COUNTIF(Leads!$H$2:$H$201,A7)
A8: Angola | B8: =COUNTIF(Leads!$H$2:$H$201,A8)
A9: Total | B9: =SUM(B6:B8)
A11: By segment
A12: Segment | B12: Contacts
A13: Distributor | B13: =COUNTIF(Leads!$J$2:$J$201,A13)
A14: Mining | B14: =COUNTIF(Leads!$J$2:$J$201,A14)
A15: Mining/Construction | B15: =COUNTIF(Leads!$J$2:$J$201,A15)
A16: Agro/Cement | B16: =COUNTIF(Leads!$J$2:$J$201,A16)
A17: Agro/Food | B17: =COUNTIF(Leads!$J$2:$J$201,A17)
A18: Energy/Oil&Gas | B18: =COUNTIF(Leads!$J$2:$J$201,A18)
A19: Energy/Logistics | B19: =COUNTIF(Leads!$J$2:$J$201,A19)
A20: Total | B20: =SUM(B13:B19)
A22: By priority tier - work A first
A23: Tier | B23: What it is | C23: Contacts
A24: A | B24: Distributors and dealers - resell, stock, buy repeatedly | C24: =COUNTIF(Leads!$K$2:$K$201,A24)
A25: B | B25: Mining - highest spend, downtime costs them per hour | C25: =COUNTIF(Leads!$K$2:$K$201,A25)
A26: C | B26: Other end users - agro, cement, energy, logistics | C26: =COUNTIF(Leads!$K$2:$K$201,A26)
A27: Total | C27: =SUM(C24:C26)
A29: Send language
A30: Language | B30: Contacts
A31: English | B31: =COUNTIF(Leads!$M$2:$M$201,A31)
A32: Portuguese | B32: =COUNTIF(Leads!$M$2:$M$201,A32)
A33: Angola is Portuguese. Those emails are already written in Portuguese.
A35: Outreach progress - fills in as you update the Status column
A36: Status | B36: Contacts
A37: Not contacted | B37: =COUNTIF(Leads!$U$2:$U$201,A37)
A38: Emailed | B38: =COUNTIF(Leads!$U$2:$U$201,A38)
A39: Follow-up sent | B39: =COUNTIF(Leads!$U$2:$U$201,A39)
A40: Replied | B40: =COUNTIF(Leads!$U$2:$U$201,A40)
A41: Meeting booked | B41: =COUNTIF(Leads!$U$2:$U$201,A41)
A42: Quoted | B42: =COUNTIF(Leads!$U$2:$U$201,A42)
A43: Not interested | B43: =COUNTIF(Leads!$U$2:$U$201,A43)
A44: Bounced | B44: =COUNTIF(Leads!$U$2:$U$201,A44)
A45: Reply rate | B45: =IFERROR(COUNTIF(Leads!$U$2:$U$201,"Replied")/MAX(1,COUNTIF(Leads!$U$2:$U$201,"Emailed")+COUNTIF(Leads!$U$2:$U$201,"Follow-up sent")+COUNTIF(Leads!$U$2:$U$201,"Replied")),0)
A47: Companies with their own email | B47: =COUNTA(Mails!$A$6:$A$141)

Sheet Mails
A1: One email per company
A2: 136 companies, 200 contacts. Each email names that company's own equipment.
A3: The whole email sits in ONE cell in the green column C - click it, copy, paste into your mail client. Ready as written; add your signature. The Leads tab has a copy addressed to each individual person.
A5: Code | B5: Company | C5: EMAIL - copy this cell | D5: Subject | E5: Send to | F5: Country | G5: Lang | H5: No. | I5: All contacts at this company
A6: C001 | B6: 260 Brands | C6: Hi Rahul, Plants like 260 Brands buy drive spares before the season, not during it - the mixer, conveyor and packing line drives on the plant cost far more to fix mid-run than to hold on the shelf. We supply helical, bevel-helical, planetary and shaft-mounted gearboxes - 10 to 14 days into Zambia for stocked sizes, with rebuild-on-exchange. If you tell me roughly when your next shutdown falls, I'll quote the units worth having in stock before it. | D6: Gearbox spares before your next shutdown - 260 Brands | E6: Rahul Singh <rahul.s@260brands.com> | F6: Zambia | G6: English | H6: =COUNTIF(Leads!$L$2:$L$201,A6) | I6: Rahul Singh (Production Manager)
A7: C002 | B7: ACTION AUTO ZAMBIA | C7: Hi Michael, ACTION AUTO ZAMBIA keeps its customers running, and the drivetrain and PTO gearboxes on the vehicles you support are what sit idle when a gearbox is on backorder. We supply industrial and mobile gearboxes - helical, bevel-helical, planetary, travel and swing drives - at trade pricing, 10 to 14 days into Zambia for stocked sizes. Most distributors we work with hold a small consignment of the units they move most, so a breakdown becomes a same-week fix instead of a six-week import. Can I send our range and dealer pricing? | D7: Gearbox supply for ACTION AUTO ZAMBIA | E7: Michael Bentley <m.bentley@actionautozambia.com> | F7: Zambia | G7: English | H7: =COUNTIF(Leads!$L$2:$L$201,A7) | I7: Michael Bentley (Managing Director)
A8: C003 | B8: AECI Mining | C8: Hi Seabi, At AECI Mining, the augers, mixers and conveyor drives on your emulsion plants are the units that stop production when a gearbox goes. The usual answer from suppliers is twelve weeks. We hold helical, bevel-helical and planetary gearboxes, and supply drop-in replacements for SEW-Eurodrive, Flender, Bonfiglioli and David Brown - 10 to 14 days into Botswana for stocked sizes, 4 to 6 weeks made to order, with rebuild-on-exchange. Send me the units on your critical spares list and I'll come back with price and lead time, so you have a second source on file before you need one. | D8: Gearbox lead times for AECI Mining | E8: Seabi Sekhobe <seabi.sekhobe@aeciworld.com> | F8: Botswana | G8: English | H8: =COUNTIF(Leads!$L$2:$L$201,A8) | I8: Seabi Sekhobe (Maintenance Manager)
A9: C004 | B9: Access Energy Solutions Pty Ltd | C9: Hi Sajad, Access Energy Solutions Pty Ltd keeps its customers running, and the gearboxes on the plant and energy equipment you supply are what sit idle when a gearbox is on backorder. We supply industrial and mobile gearboxes - helical, bevel-helical, planetary, travel and swing drives - at trade pricing, 10 to 14 days into Zambia for stocked sizes. Most distributors we work with hold a small consignment of the units they move most, so a breakdown becomes a same-week fix instead of a six-week import. Can I send our range and dealer pricing? | D9: Gearbox supply for Access Energy Solutions Pty Ltd | E9: Sajad Ahmed <sajad@accessenergys.com> | F9: Zambia | G9: English | H9: =COUNTIF(Leads!$L$2:$L$201,A9) | I9: Sajad Ahmed (MD)
A10: C005 | B10: Advanta Seeds | C10: Hi Innocent, Plants like Advanta Seeds buy drive spares before the season, not during it - the seed processing, grading and conveyor drives on the plant cost far more to fix mid-run than to hold on the shelf. We supply helical, bevel-helical, planetary and shaft-mounted gearboxes - 10 to 14 days into Zambia for stocked sizes, with rebuild-on-exchange. If you tell me roughly when your next shutdown falls, I'll quote the units worth having in stock before it. | D10: Gearbox spares before your next shutdown - Advanta Seeds | E10: Innocent Mwaanga <innocent.mwaanga@advantaseeds.com> | F10: Zambia | G10: English | H10: =COUNTIF(Leads!$L$2:$L$201,A10) | I10: Innocent Mwaanga (Production Manager)
A11: C006 | B11: Africa Global Logistics | C11: Hi Mwila, At Africa Global Logistics, the materials handling, crane and conveyor drives at the terminals fail the same way everywhere: the machine is available, the gearbox is not. We supply industrial, shaft-mounted and mobile gearboxes plus travel and swing drives - 10 to 14 days into Zambia for stocked sizes, with rebuild-on-exchange. Send me the drives that give you the most trouble and I'll come back with price and lead time. If we are not better than your current source, nothing lost. | D11: Drive and gearbox spares for Africa Global Logistics | E11: Mwila Chisanga <mwila.chisanga@aglgroup.com> | F11: Zambia | G11: English | H11: =COUNTIF(Leads!$L$2:$L$201,A11) | I11: Mwila Chisanga (Operations Manager IFFS)
A12: C007 | B12: African Mining Services | C12: Hi Tlamelo, At African Mining Services, the drivetrains and final drives across your contract fleet are the units that stop production when a gearbox goes. The usual answer from suppliers is twelve weeks. We hold helical, bevel-helical and planetary gearboxes, and supply drop-in replacements for SEW-Eurodrive, Flender, Bonfiglioli and David Brown - 10 to 14 days into Botswana for stocked sizes, 4 to 6 weeks made to order, with rebuild-on-exchange. Send me the units on your critical spares list and I'll come back with price and lead time, so you have a second source on file before you need one. | D12: Gearbox lead times for African Mining Services | E12: Tlamelo Rapata <trapata@amsgh.com> | F12: Botswana | G12: English | H12: =COUNTIF(Leads!$L$2:$L$201,A12) | I12: Tlamelo Rapata (Maintenance Manager)
A13: C008 | B13: Applied Metrology Services (Pty) Ltd. | C13: Hi Favor, Applied Metrology Services (Pty) Ltd. keeps its customers running, and the gearboxes on the process equipment you calibrate and service are what sit idle when a gearbox is on backorder. We supply industrial and mobile gearboxes - helical, bevel-helical, planetary, travel and swing drives - at trade pricing, 10 to 14 days into Botswana for stocked sizes. Most distributors we work with hold a small consignment of the units they move most, so a breakdown becomes a same-week fix instead of a six-week import. Can I send our range and dealer pricing? | D13: Gearbox supply for Applied Metrology Services (Pty) Ltd. | E13: Favor Marebole <favor@appliedmetrology.co.za> | F13: Botswana | G13: English | H13: =COUNTIF(Leads!$L$2:$L$201,A13) | I13: Favor Marebole (Managing Director)
A14: C009 | B14: Austin Powder | C14: Hi Brian, Plants like Austin Powder buy drive spares before the season, not during it - the mixers, augers and conveyor drives on your plant cost far more to fix mid-run than to hold on the shelf. We supply helical, bevel-helical, planetary and shaft-mounted gearboxes - 10 to 14 days into Zambia for stocked sizes, with rebuild-on-exchange. If you tell me roughly when your next shutdown falls, I'll quote the units worth having in stock before it. | D14: Gearbox spares before your next shutdown - Austin Powder | E14: Brian Mutale <brian.mutale@austinpowder.com> | F14: Zambia | G14: English | H14: =COUNTIF(Leads!$L$2:$L$201,A14) | I14: Brian Mutale (Plant Manager)
A15: C010 | B15: Azule Energy | C15: Olá Tatiana, Grande parte da despesa em redutores concentra-se num único fornecedor com prazos longos. Funciona até a unidade estar em rutura - e na Azule Energy isso significa os accionamentos dos guinchos, gruas e sistemas de amarração nas FPSO. Fornecemos redutores helicoidais, cónicos e planetários, e substituições compatíveis com SEW-Eurodrive, Flender, Bonfiglioli e David Brown - 10 a 14 dias até Angola para as medidas em stock, 4 a 6 semanas por encomenda, com recondicionamento por troca. Não é preciso mudar de fornecedor: basta consultarem-nos como segunda fonte. O que precisam da nossa parte para o registo de fornecedor? | D15: Segunda fonte para redutores - Azule Energy | E15: Tatiana Malheiro <tatiana.malheiro@azule-energy.com> | F15: Angola | G15: Portuguese | H15: =COUNTIF(Leads!$L$2:$L$201,A15) | I15: Tatiana Malheiro (Procurement Operations Manager), Xavier Riou (Engineering Manager), Davide Guttoriello (Contracts and Procurement Manager (Eni Secondee)), Nivaldo Vicente (Rigs & LLI’s Procurement), Cipriano Kakeu (Subsea Inspection, Maintenance & Repair and Vessel Manager)
A16: C011 | B16: BEFCO - Indústria | C16: Olá Malek, Fábricas como a BEFCO - Indústria compram peças de transmissão antes da campanha, não durante - os accionamentos dos misturadores, transportadores e linhas de produção custam muito mais a reparar em produção do que a ter em stock. Fornecemos redutores helicoidais, cónicos, planetários e de eixo oco - 10 a 14 dias até Angola para as medidas em stock, com recondicionamento por troca. Se me indicar a data da próxima paragem, orçamento as unidades que deveriam estar em stock antes disso. | D16: Redutores antes da próxima paragem - BEFCO - Indústria | E16: Malek Nazha <mnazha@befco-industria.com> | F16: Angola | G16: Portuguese | H16: =COUNTIF(Leads!$L$2:$L$201,A16) | I16: Malek Nazha (Plant Manager)
A17: C012 | B17: BIA GROUP | C17: Hi Dirk, BIA GROUP keeps its customers running, and the final drives, travel and swing drives on the machines you support are what sit idle when a gearbox is on backorder. We supply industrial and mobile gearboxes - helical, bevel-helical, planetary, travel and swing drives - at trade pricing, 10 to 14 days into Zambia for stocked sizes. Most distributors we work with hold a small consignment of the units they move most, so a breakdown becomes a same-week fix instead of a six-week import. Can I send our range and dealer pricing? | D17: Gearbox supply for BIA GROUP | E17: Dirk Wet <dirk.dewet@biagroup.com> | F17: Zambia | G17: English | H17: =COUNTIF(Leads!$L$2:$L$201,A17) | I17: Dirk Wet (Project Operation Manager), Johannes Subowo (Workshop Manager)
... A141: C136 | B141: ZISMO Engineering (Pty) Ltd. | C141: Hi Justice, ZISMO Engineering (Pty) Ltd. keeps its customers running, and the gearboxes that pair with the motors and drives you already rebuild are what sit idle when a gearbox is on backorder. We supply industrial and mobile gearboxes - helical, bevel-helical, planetary, travel and swing drives - at trade pricing, 10 to 14 days into Botswana for stocked sizes. Most distributors we work with hold a small consignment of the units they move most, so a breakdown becomes a same-week fix instead of a six-week import. Can I send our range and dealer pricing? | D141: Gearbox supply for ZISMO Engineering (Pty) Ltd. | E141: Justice Moilwa <jmoilwa@zismoengineering.com> | F141: Botswana | G141: English | H141: =COUNTIF(Leads!$L$2:$L$201,A141) | I141: Justice Moilwa (Managing Director)

Sheet Leads
A1: First name | B1: Last name | C1: Company | D1: EMAIL - copy this cell | E1: Subject | F1: Email address | G1: Title | H1: Country | I1: City | J1: Segment | K1: Tier | L1: Co. code | M1: Language | N1: LinkedIn | O1: Company domain | P1: Company phone | Q1: Employees | R1: Industry | S1: Suggested angle | T1: Check | U1: Status | V1: Date sent | W1: Replied | X1: Notes
A2: Ivo | B2: Araujo | C2: CENTROCAR - Centro de Equipamentos Mecânicos S.A. | D2: Olá Ivo, A CENTROCAR - Centro de Equipamentos Mecânicos S.A. mantém os clientes a trabalhar, e os comandos finais, de translação e de rotação das máquinas que assistem são o que fica parado quando um redutor está em falta. Fornecemos redutores industriais e móveis - helicoidais, cónicos, planetários, comandos de translação e rotação - a preços de revenda, 10 a 14 dias até Angola para as medidas em stock. A maioria dos distribuidores com quem trabalhamos mantém um pequeno stock das unidades que mais substituem, para resolver uma avaria na mesma semana em vez de esperar seis. Posso enviar a nossa gama e preços de revenda? | E2: Fornecimento de redutores para a CENTROCAR - Centro de Equipamentos Mecânicos S.A. | F2: ivo.araujo@centrocar.com | G2: General Manager Angola | H2: Angola | I2: Luanda | J2: Distributor | K2: A | L2: C026 | M2: Portuguese | N2: http://www.linkedin.com/in/ivo-araujo-9470b849 | O2: centrocar.com | P2: +351 22 002 9150 | Q2: 150 | R2: machinery | S2: Stocking terms and margin - lead with the commercial offer to the MD/GM, not the spec sheet | T2: HQ abroad (Portugal) - verify local buying authority | U2: Not contacted
A3: Luca | B3: Sassella | C3: E.A.T.S Metering Systems | D3: Olá Luca, A E.A.T.S Metering Systems mantém os clientes a trabalhar, e os redutores que acompanham os sistemas que fornecem são o que fica parado quando um redutor está em falta. Fornecemos redutores industriais e móveis - helicoidais, cónicos, planetários, comandos de translação e rotação - a preços de revenda, 10 a 14 dias até Angola para as medidas em stock. A maioria dos distribuidores com quem trabalhamos mantém um pequeno stock das unidades que mais substituem, para resolver uma avaria na mesma semana em vez de esperar seis. Posso enviar a nossa gama e preços de revenda? | E3: Fornecimento de redutores para a E.A.T.S Metering Systems | F3: luca.sassella@eats.ao | G3: Managing Director | H3: Angola | J3: Distributor | K3: A | L3: C044 | M3: Portuguese | N3: http://www.linkedin.com/in/luca-sassella-6b69765 | O3: eats.ao | P3: +244 931 878 469 | Q3: 9 | R3: oil & energy | S3: Stocking terms and margin - lead with the commercial offer to the MD/GM, not the spec sheet | U3: Not contacted
A4: Eduardo | B4: Fernandez | C4: ENCOM Lda. | D4: Olá Eduardo, A ENCOM Lda. mantém os clientes a trabalhar, e os redutores que os vossos clientes industriais vos pedem são o que fica parado quando um redutor está em falta. Fornecemos redutores industriais e móveis - helicoidais, cónicos, planetários, comandos de translação e rotação - a preços de revenda, 10 a 14 dias até Angola para as medidas em stock. A maioria dos distribuidores com quem trabalhamos mantém um pequeno stock das unidades que mais substituem, para resolver uma avaria na mesma semana em vez de esperar seis. Posso enviar a nossa gama e preços de revenda? | E4: Fornecimento de redutores para a ENCOM Lda. | F4: eduardo.fernandez@encom.it.ao | G4: Managing Director | H4: Angola | I4: Luanda | J4: Distributor | K4: A | L4: C045 | M4: Portuguese | N4: http://www.linkedin.com/in/edufernandez | O4: encom.it.ao | P4: +1 713-429-5084 | Q4: 24 | R4: oil & energy | S4: Stocking terms and margin - lead with the commercial offer to the MD/GM, not the spec sheet | U4: Not contacted
A5: Jose | B5: Santos | C5: ENERLINE, SA | D5: Olá Jose, A ENERLINE, SA mantém os clientes a trabalhar, e os redutores dos equipamentos que instalam e mantêm são o que fica parado quando um redutor está em falta. Fornecemos redutores industriais e móveis - helicoidais, cónicos, planetários, comandos de translação e rotação - a preços de revenda, 10 a 14 dias até Angola para as medidas em stock. A maioria dos distribuidores com quem trabalhamos mantém um pequeno stock das unidades que mais substituem, para resolver uma avaria na mesma semana em vez de esperar seis. Posso enviar a nossa gama e preços de revenda? | E5: Fornecimento de redutores para a ENERLINE, SA | F5: josesantos@enerline.ao | G5: General Manager | H5: Angola | I5: Luanda | J5: Distributor | K5: A | L5: C046 | M5: Portuguese | N5: http://www.linkedin.com/in/jose-santos-9193b9253 | O5: enerline.ao | Q5: 250 | R5: oil & energy | S5: Stocking terms and margin - lead with the commercial offer to the MD/GM, not the spec sheet | U5: Not contacted
A6: Jose | B6: Garrido | C6: Elecnor Group | D6: Olá Jose, A Elecnor Group mantém os clientes a trabalhar, e os accionamentos dos equipamentos de obra e das instalações que constroem são o que fica parado quando um redutor está em falta. Fornecemos redutores industriais e móveis - helicoidais, cónicos, planetários, comandos de translação e rotação - a preços de revenda, 10 a 14 dias até Angola para as medidas em stock. A maioria dos distribuidores com quem trabalhamos mantém um pequeno stock das unidades que mais substituem, para resolver uma avaria na mesma semana em vez de esperar seis. Posso enviar a nossa gama e preços de revenda? | E6: Fornecimento de redutores para a Elecnor Group | F6: jlgarrido@elecnor.com | G6: Director Geral Adjunto de Sucursal Angola | H6: Angola | I6: Luanda | J6: Distributor | K6: A | L6: C048 | M6: Portuguese | N6: http://www.linkedin.com/in/jose-luis-garrido-34110623 | O6: grupoelecnor.com | Q6: 29000 | R6: construction | S6: Stocking terms and margin - lead with the commercial offer to the MD/GM, not the spec sheet | T6: HQ abroad (Spain) - verify local buying authority | U6: Not contacted
A7: Januario | B7: Cuela | C7: GEA Group | D7: Olá Januario, A GEA Group mantém os clientes a trabalhar, e os redutores dos equipamentos de processo que instalam e assistem são o que fica parado quando um redutor está em falta. Fornecemos redutores industriais e móveis - helicoidais, cónicos, planetários, comandos de translação e rotação - a preços de revenda, 10 a 14 dias até Angola para as medidas em stock. A maioria dos distribuidores com quem trabalhamos mantém um pequeno stock das unidades que mais substituem, para resolver uma avaria na mesma semana em vez de esperar seis. Posso enviar a nossa gama e preços de revenda? | E7: Fornecimento de redutores para a GEA Group | F7: januario.cuela@gea.com | G7: Branch Manager Angola | H7: Angola | J7: Distributor | K7: A | L7: C055 | M7: Portuguese | N7: http://www.linkedin.com/in/januario-cuela-985a1538 | O7: gea.com | P7: +49 211 91360 | Q7: 20000 | R7: machinery | S7: Stocking terms and margin - lead with the commercial offer to the MD/GM, not the spec sheet | T7: HQ abroad (Germany) - verify local buying authority | U7: Not contacted
A8: Rayan | B8: Farhat | C8: Industryhub | D8: Olá Rayan, A Industryhub mantém os clientes a trabalhar, e os redutores que os vossos clientes industriais vos pedem são o que fica parado quando um redutor está em falta. Fornecemos redutores industriais e móveis - helicoidais, cónicos, planetários, comandos de translação e rotação - a preços de revenda, 10 a 14 dias até Angola para as medidas em stock. A maioria dos distribuidores com quem trabalhamos mantém um pequeno stock das unidades que mais substituem, para resolver uma avaria na mesma semana em vez de esperar seis. Posso enviar a nossa gama e preços de revenda? | E8: Fornecimento de redutores para a Industryhub | F8: rayan.farhat@industryhubangola.com | G8: Managing Director and Founder | H8: Angola | I8: Luanda | J8: Distributor | K8: A | L8: C063 | M8: Portuguese | N8: http://www.linkedin.com/in/rayan-farhat | O8: industryhubangola.com | Q8: 11 | R8: automotive | S8: Stocking terms and margin - lead with the commercial offer to the MD/GM, not the spec sheet | U8: Not contacted
A9: Nasim | B9: Kayali | C9: Mega Mecanix | D9: Olá Nasim, A Mega Mecanix mantém os clientes a trabalhar, e os redutores dos equipamentos industriais que fornecem são o que fica parado quando um redutor está em falta. Fornecemos redutores industriais e móveis - helicoidais, cónicos, planetários, comandos de translação e rotação - a preços de revenda, 10 a 14 dias até Angola para as medidas em stock. A maioria dos distribuidores com quem trabalhamos mantém um pequeno stock das unidades que mais substituem, para resolver uma avaria na mesma semana em vez de esperar seis. Posso enviar a nossa gama e preços de revenda? | E9: Fornecimento de redutores para a Mega Mecanix | F9: n.kayali@mecanixsal.com | G9: General Manager | H9: Angola | J9: Distributor | K9: A | L9: C074 | M9: Portuguese | N9: http://www.linkedin.com/in/nasim-kayali-0bbb2937 | O9: mecanixsal.com | P9: +961 5 950 866 | Q9: 19 | R9: machinery | S9: Stocking terms and margin - lead with the commercial offer to the MD/GM, not the spec sheet | U9: Not contacted
A10: Paulo | B10: Rodrigues | C10: Movicortes Angola | D10: Olá Paulo, A Movicortes Angola mantém os clientes a trabalhar, e os redutores das máquinas e equipamentos que comercializam são o que fica parado quando um redutor está em falta. Fornecemos redutores industriais e móveis - helicoidais, cónicos, planetários, comandos de translação e rotação - a preços de revenda, 10 a 14 dias até Angola para as medidas em stock. A maioria dos distribuidores com quem trabalhamos mantém um pequeno stock das unidades que mais substituem, para resolver uma avaria na mesma semana em vez de esperar seis. Posso enviar a nossa gama e preços de revenda? | E10: Fornecimento de redutores para a Movicortes Angola | F10: paulo.rodrigues@movicortes.pt | G10: General Manager | H10: Angola | I10: Luanda | J10: Distributor | K10: A | L10: C080 | M10: Portuguese | N10: http://www.linkedin.com/in/paulo-rodrigues-a35823164 | O10: movicortesangola.com | Q10: 7 | R10: machinery | S10: Stocking terms and margin - lead with the commercial offer to the MD/GM, not the spec sheet | U10: Not contacted
A11: Peter | B11: Mashangu | C11: Nampak | D11: Olá Peter, A Nampak mantém os clientes a trabalhar, e os accionamentos das prensas, transportadores e linhas de embalagem são o que fica parado quando um redutor está em falta. Fornecemos redutores industriais e móveis - helicoidais, cónicos, planetários, comandos de translação e rotação - a preços de revenda, 10 a 14 dias até Angola para as medidas em stock. A maioria dos distribuidores com quem trabalhamos mantém um pequeno stock das unidades que mais substituem, para resolver uma avaria na mesma semana em vez de esperar seis. Posso enviar a nossa gama e preços de revenda? | E11: Fornecimento de redutores para a Nampak | F11: peter.mashangu@nampak.com | G11: Managing Director | H11: Angola | I11: Luanda | J11: Distributor | K11: A | L11: C081 | M11: Portuguese | N11: http://www.linkedin.com/in/peter-mashangu-394611159 | O11: nampak.com | P11: +27 11 719 6300 | Q11: 2500 | R11: packaging & containers | S11: Stocking terms and margin - lead with the commercial offer to the MD/GM, not the spec sheet | T11: HQ abroad (South Africa) - verify local buying authority | U11: Not contacted
A12: Kitana | B12: Barbosa | C12: Nors Group | D12: Olá Kitana, A Nors Group mantém os clientes a trabalhar, e os comandos finais e caixas das máquinas e camiões que assistem no pós-venda são o que fica parado quando um redutor está em falta. Fornecemos redutores industriais e móveis - helicoidais, cónicos, planetários, comandos de translação e rotação - a preços de revenda, 10 a 14 dias até Angola para as medidas em stock. A maioria dos distribuidores com quem trabalhamos mantém um pequeno stock das unidades que mais substituem, para resolver uma avaria na mesma semana em vez de esperar seis. Posso enviar a nossa gama e preços de revenda? | E12: Fornecimento de redutores para a Nors Group | F12: kbarbosa@nors.com | G12: After Sales Director | H12: Angola | I12: Luanda | J12: Distributor | K12: A | L12: C083 | M12: Portuguese | N12: http://www.linkedin.com/in/kitana-barbosa-b3b58486 | O12: nors.com | P12: +351 22 615 0320 | Q12: 3200 | R12: automotive | S12: Stocking terms and margin - lead with the commercial offer to the MD/GM, not the spec sheet | T12: HQ abroad (Portugal) - verify local buying authority | U12: Not contacted
A13: Jean | B13: Rodrigues | C13: OG3S Mecanica Lda | D13: Olá Jean, A OG3S Mecanica Lda mantém os clientes a trabalhar, e os redutores dos equipamentos industriais que assistem são o que fica parado quando um redutor está em falta. Fornecemos redutores industriais e móveis - helicoidais, cónicos, planetários, comandos de translação e rotação - a preços de revenda, 10 a 14 dias até Angola para as medidas em stock. A maioria dos distribuidores com quem trabalhamos mantém um pequeno stock das unidades que mais substituem, para resolver uma avaria na mesma semana em vez de esperar seis. Posso enviar a nossa gama e preços de revenda? | E13: Fornecimento de redutores para a OG3S Mecanica Lda | F13: jean-philippe.rodrigues@og3s-mecanica.com | G13: Executive Managing Director | H13: Angola | J13: Distributor | K13: A | L13: C085 | M13: Portuguese | N13: http://www.linkedin.com/in/jean-philippe-rodrigues-a727b82b | O13: og3s-mecanica.com | Q13: 35 | R13: oil & energy | S13: Stocking terms and margin - lead with the commercial offer to the MD/GM, not the spec sheet | U13: Not contacted
A14: Luis | B14: Almeida | C14: SPIE Global Services Energy | D14: Olá Luis, A SPIE Global Services Energy mantém os clientes a trabalhar, e os redutores dos equipamentos rotativos que mantêm em operação são o que fica parado quando um redutor está em falta. Fornecemos redutores industriais e móveis - helicoidais, cónicos, planetários, comandos de translação e rotação - a preços de revenda, 10 a 14 dias até Angola para as medidas em stock. A maioria dos distribuidores com quem trabalhamos mantém um pequeno stock das unidades que mais substituem, para resolver uma avaria na mesma semana em vez de esperar seis. Posso enviar a nossa gama e preços de revenda? | E14: Fornecimento de redutores para a SPIE Global Services Energy | F14: l.almeida@spie.com | G14: Managing Director Angola & Mozambique | H14: Angola | I14: Luanda | J14: Distributor | K14: A | L14: C105 | M14: Portuguese | N14: http://www.linkedin.com/in/luis-ferreira-de-almeida-34495338 | O14: spie.com | P14: +33 1 34 41 81 81 | Q14: 5000 | R14: oil & energy | S14: Stocking terms and margin - lead with the commercial offer to the MD/GM, not the spec sheet | T14: HQ abroad (France) - verify local buying authority | U14: Not contacted
A15: Nicolas | B15: Monville | C15: TFE GROUP INC | D15: Olá Nicolas, A TFE GROUP INC mantém os clientes a trabalhar, e os redutores que os vossos clientes industriais vos pedem são o que fica parado quando um redutor está em falta. Fornecemos redutores industriais e móveis - helicoidais, cónicos, planetários, comandos de translação e rotação - a preços de revenda, 10 a 14 dias até Angola para as medidas em stock. A maioria dos distribuidores com quem trabalhamos mantém um pequeno stock das unidades que mais substituem, para resolver uma avaria na mesma semana em vez de esperar seis. Posso enviar a nossa gama e preços de revenda? | E15: Fornecimento de redutores para a TFE GROUP INC | F15: nicolas.monville@grouptfe.com | G15: Managing Director | H15: Angola | J15: Distributor | K15: A | L15: C119 | M15: Portuguese | N15: http://www.linkedin.com/in/nicolas-monville-411a6358 | O15: grouptfe.com | P15: +33 4 66 70 64 10 | Q15: 45 | R15: oil & energy | S15: Stocking terms and margin - lead with the commercial offer to the MD/GM, not the spec sheet | T15: HQ abroad (France) - verify local buying authority | U15: Not contacted
A16: Mathieu | B16: Wallach | C16: Welltec | D16: Olá Mathieu, A Welltec mantém os clientes a trabalhar, e os redutores e accionamentos dos guinchos e equipamentos de intervenção são o que fica parado quando um redutor está em falta. Fornecemos redutores industriais e móveis - helicoidais, cónicos, planetários, comandos de translação e rotação - a preços de revenda, 10 a 14 dias até Angola para as medidas em stock. A maioria dos distribuidores com quem trabalhamos mantém um pequeno stock das unidades que mais substituem, para resolver uma avaria na mesma semana em vez de esperar seis. Posso enviar a nossa gama e preços de revenda? | E16: Fornecimento de redutores para a Welltec | F16: mwallach@welltec.com | G16: Sales Director and General Manager, Southern Africa | H16: Angola | J16: Distributor | K16: A | L16: C132 | M16: Portuguese | N16: http://www.linkedin.com/in/mathieu-wallach-a9203a59 | O16: welltec.com | P16: +45 48 14 35 14 | Q16: 740 | R16: oil & energy | S16: Stocking terms and margin - lead with the commercial offer to the MD/GM, not the spec sheet | T16: HQ abroad (Denmark) - verify local buying authority | U16: Not contacted
A17: Favor | B17: Marebole | C17: Applied Metrology Services (Pty) Ltd. | D17: Hi Favor, Applied Metrology Services (Pty) Ltd. keeps its customers running, and the gearboxes on the process equipment you calibrate and service are what sit idle when a gearbox is on backorder. We supply industrial and mobile gearboxes - helical, bevel-helical, planetary, travel and swing drives - at trade pricing, 10 to 14 days into Botswana for stocked sizes. Most distributors we work with hold a small consignment of the units they move most, so a breakdown becomes a same-week fix instead of a six-week import. Can I send our range and dealer pricing? | E17: Gearbox supply for Applied Metrology Services (Pty) Ltd. | F17: favor@appliedmetrology.co.za | G17: Managing Director | H17: Botswana | J17: Distributor | K17: A | L17: C008 | M17: English | N17: http://www.linkedin.com/in/favor-marebole-a060559 | O17: appliedmetrology.co.za | P17: +27 11 568 0386 | Q17: 12 | R17: machinery | S17: Stocking terms and margin - lead with the commercial offer to the MD/GM, not the spec sheet | T17: HQ abroad (South Africa) - verify local buying authority | U17: Not contacted
A18: Bofedile | B18: Moeti | C18: Bofedile Tech Services (Pty) Ltd | D18: Hi Bofedile, Bofedile Tech Services (Pty) Ltd keeps its customers running, and the gearboxes on the mining and industrial equipment you supply are what sit idle when a gearbox is on backorder. We supply industrial and mobile gearboxes - helical, bevel-helical, planetary, travel and swing drives - at trade pricing, 10 to 14 days into Botswana for stocked sizes. Most distributors we work with hold a small consignment of the units they move most, so a breakdown becomes a same-week fix instead of a six-week import. Can I send our range and dealer pricing? | E18: Gearbox supply for Bofedile Tech Services (Pty) Ltd | F18: bmoeti@bts-bw.com | G18: Managing Director | H18: Botswana | I18: Gaborone | J18: Distributor | K18: A | L18: C022 | M18: English | N18: http://www.linkedin.com/in/bofedile-moeti-6b1b0447 | O18: bts-bw.com | Q18: 6 | R18: industrial automation | S18: Stocking terms and margin - lead with the commercial offer to the MD/GM, not the spec sheet | U18: Not contacted
A19: Wessel | B19: Wessels | C19: Coastal Hire | D19: Hi Wessel, Coastal Hire keeps its customers running, and the gearboxes on the plant in your hire fleet are what sit idle when a gearbox is on backorder. We supply industrial and mobile gearboxes - helical, bevel-helical, planetary, travel and swing drives - at trade pricing, 10 to 14 days into Botswana for stocked sizes. Most distributors we work with hold a small consignment of the units they move most, so a breakdown becomes a same-week fix instead of a six-week import. Can I send our range and dealer pricing? | E19: Gearbox supply for Coastal Hire | F19: wessel@coastalhire.co.za | G19: Managing Director | H19: Botswana | J19: Distributor | K19: A | L19: C033 | M19: English | N19: http://www.linkedin.com/in/wessel-wessels-086569146 | O19: coastalhire.co.za | P19: +27 10 158 0525 | Q19: 260 | R19: construction / equipment hire | S19: Stocking terms and margin - lead with the commercial offer to the MD/GM, not the spec sheet | T19: HQ abroad (South Africa) - verify local buying authority | U19: Not contacted
A20: Tichaona | B20: Ndhlovu | C20: Delswiz Manufacturing (Pty) Limited | D20: Hi Tichaona, Delswiz Manufacturing (Pty) Limited keeps its customers running, and the gearboxes for the conveyor systems and idlers you fabricate are what sit idle when a gearbox is on backorder. We supply industrial and mobile gearboxes - helical, bevel-helical, planetary, travel and swing drives - at trade pricing, 10 to 14 days into Botswana for stocked sizes. Most distributors we work with hold a small consignment of the units they move most, so a breakdown becomes a same-week fix instead of a six-week import. Can I send our range and dealer pricing? | E20: Gearbox supply for Delswiz Manufacturing (Pty) Limited | F20: tndhlovu@delswizgroup.com | G20: Managing Director | H20: Botswana | I20: Gaborone | J20: Distributor | K20: A | L20: C042 | M20: English | N20: http://www.linkedin.com/in/tichaona-ndhlovu-93212b141 | O20: delswizgroup.com | P20: +971 55 157 9261 | Q20: 26 | R20: mining & metals | S20: Stocking terms and margin - lead with the commercial offer to the MD/GM, not the spec sheet | U20: Not contacted
A21: Clayton | B21: Davis | C21: HANSA-FLEX AG | D21: Hi Clayton, HANSA-FLEX AG keeps its customers running, and the gearboxes that sit alongside the hydraulics you already supply are what sit idle when a gearbox is on backorder. We supply industrial and mobile gearboxes - helical, bevel-helical, planetary, travel and swing drives - at trade pricing, 10 to 14 days into Botswana for stocked sizes. Most distributors we work with hold a small consignment of the units they move most, so a breakdown becomes a same-week fix instead of a six-week import. Can I send our range and dealer pricing? | E21: Gearbox supply for HANSA-FLEX AG | F21: clayton.davis@hansa-flex.com | G21: General Manager | H21: Botswana | J21: Distributor | K21: A | L21: C058 | M21: English | N21: http://www.linkedin.com/in/clayton-davis-a18a377b | O21: hansa-flex.de | P21: +49 42 1489070 | Q21: 5200 | R21: machinery / hydraulics | S21: Stocking terms and margin - lead with the commercial offer to the MD/GM, not the spec sheet | T21: HQ abroad (Germany) - verify local buying authority | U21: Not contacted
A22: Zayd | B22: Bhoyroo | C22: Impex Group | D22: Hi Zayd, Impex Group keeps its customers running, and the industrial and automotive gearboxes your counter customers ask for are what sit idle when a gearbox is on backorder. We supply industrial and mobile gearboxes - helical, bevel-helical, planetary, travel and swing drives - at trade pricing, 10 to 14 days into Botswana for stocked sizes. Most distributors we work with hold a small consignment of the units they move most, so a breakdown becomes a same-week fix instead of a six-week import. Can I send our range and dealer pricing? | E22: Gearbox supply for Impex Group | F22: zayd@impex.co.bw | G22: Assistant General Manager | H22: Botswana | J22: Distributor | K22: A | L22: C062 | M22: English | N22: http://www.linkedin.com/in/zayd-bhoyroo-41419b161 | O22: impex.co.bw | Q22: 26 | R22: automotive / wholesale | S22: Stocking terms and margin - lead with the commercial offer to the MD/GM, not the spec sheet | U22: Not contacted
A23: Sonny | B23: Morekisi | C23: Komatsu Africa Holdings (Pty) Ltd | D23: Hi Sonny, Komatsu Africa Holdings (Pty) Ltd keeps its customers running, and your customers' excavator final drives, travel and swing drives are what sit idle when a gearbox is on backorder. We supply industrial and mobile gearboxes - helical, bevel-helical, planetary, travel and swing drives - at trade pricing, 10 to 14 days into Botswana for stocked sizes. Most distributors we work with hold a small consignment of the units they move most, so a breakdown becomes a same-week fix instead of a six-week import. Can I send our range and dealer pricing? | E23: Gearbox supply for Komatsu Africa Holdings (Pty) Ltd | F23: sonnym@komatsu.co.za | G23: Branch Manager | H23: Botswana | J23: Distributor | K23: A | L23: C066 | M23: English | N23: http://www.linkedin.com/in/sonny-morekisi-9b921043 | O23: komatsu.co.za | Q23: 360 | R23: machinery | S23: Stocking terms and margin - lead with the commercial offer to the MD/GM, not the spec sheet | T23: HQ abroad (South Africa) - verify local buying authority | U23: Not contacted
A24: Donovan | B24: Lendrum | C24: Rotating Solutions Botswana | D24: Hi Donovan, Rotating Solutions Botswana keeps its customers running, and the gearboxes that sit alongside the bearings and pumps you already distribute are what sit idle when a gearbox is on backorder. We supply industrial and mobile gearboxes - helical, bevel-helical, planetary, travel and swing drives - at trade pricing, 10 to 14 days into Botswana for stocked sizes. Most distributors we work with hold a small consignment of the units they move most, so a breakdown becomes a same-week fix instead of a six-week import. Can I send our range and dealer pricing? | E24: Gearbox supply for Rotating Solutions Botswana | F24: donovan@rotatingsolutions.co.bw | G24: Sales Director | H24: Botswana | I24: Gaborone | J24: Distributor | K24: A | L24: C100 | M24: English | N24: http://www.linkedin.com/in/donovan-lendrum-906a6352 | O24: rotatingsolutions.co.bw | Q24: 2 | R24: industrial supply / bearings and lubricants | S24: Stocking terms and margin - lead with the commercial offer to the MD/GM, not the spec sheet | U24: Not contacted
A25: Tshegofatso | B25: Mosweu | C25: SPTC | D25: Hi Tshegofatso, Most gearbox spend sits with a single supplier on long lead times. That works until the unit is on backorder - and at SPTC that means the gearboxes that pair with the electrical equipment you supply. We supply helical, bevel-helical and planetary gearboxes and drop-in replacements for SEW-Eurodrive, Flender, Bonfiglioli and David Brown - 10 to 14 days into Botswana for stocked sizes, 4 to 6 weeks made to order, with rebuild-on-exchange. No switching required. Quote us against your current source and see where we land. What do you need from us for vendor registration? | E25: Second source for gearbox spares - SPTC | F25: tshegofatso@sptc.com.sa | G25: Assistant Manager Procurement | H25: Botswana | J25: Distributor | K25: A | L25: C106 | M25: English | N25: http://www.linkedin.com/in/tshegofatso-mosweu-783017a1 | O25: sptc.com.sa | P25: +966 13 814 4624 | Q25: 320 | R25: electrical/electronic manufacturing | S25: Stocking terms and margin - lead with the commercial offer to the MD/GM, not the spec sheet | T25: HQ abroad (Saudi Arabia) - verify local buying authority | U25: Not contacted
A26: Justice | B26: Moilwa | C26: ZISMO Engineering (Pty) Ltd. | D26: Hi Justice, ZISMO Engineering (Pty) Ltd. keeps its customers running, and the gearboxes that pair with the motors and drives you already rebuild are what sit idle when a gearbox is on backorder. We supply industrial and mobile gearboxes - helical, bevel-helical, planetary, travel and swing drives - at trade pricing, 10 to 14 days into Botswana for stocked sizes. Most distributors we work with hold a small consignment of the units they move most, so a breakdown becomes a same-week fix instead of a six-week import. Can I send our range and dealer pricing? | E26: Gearbox supply for ZISMO Engineering (Pty) Ltd. | F26: jmoilwa@zismoengineering.com | G26: Managing Director | H26: Botswana | I26: Gaborone | J26: Distributor | K26: A | L26: C136 | M26: English | N26: http://www.linkedin.com/in/justice-moilwa-859595ba | O26: zismoengineeing.com | P26: +267 393 2711 | Q26: 58 | R26: electrical/electronic manufacturing | S26: Stocking terms and margin - lead with the commercial offer to the MD/GM, not the spec sheet | U26: Not contacted
A27: Michael | B27: Bentley | C27: ACTION AUTO ZAMBIA | D27: Hi Michael, ACTION AUTO ZAMBIA keeps its customers running, and the drivetrain and PTO gearboxes on the vehicles you support are what sit idle when a gearbox is on backorder. We supply industrial and mobile gearboxes - helical, bevel-helical, planetary, travel and swing drives - at trade pricing, 10 to 14 days into Zambia for stocked sizes. Most distributors we work with hold a small consignment of the units they move most, so a breakdown becomes a same-week fix instead of a six-week import. Can I send our range and dealer pricing? | E27: Gearbox supply for ACTION AUTO ZAMBIA | F27: m.bentley@actionautozambia.com | G27: Managing Director | H27: Zambia | J27: Distributor | K27: A | L27: C002 | M27: English | N27: http://www.linkedin.com/in/michael-bentley-69240073 | O27: actionautozambia.com | Q27: 54 | R27: automotive | S27: Stocking terms and margin - lead with the commercial offer to the MD/GM, not the spec sheet | U27: Not contacted
A28: Sajad | B28: Ahmed | C28: Access Energy Solutions Pty Ltd | D28: Hi Sajad, Access Energy Solutions Pty Ltd keeps its customers running, and the gearboxes on the plant and energy equipment you supply are what sit idle when a gearbox is on backorder. We supply industrial and mobile gearboxes - helical, bevel-helical, planetary, travel and swing drives - at trade pricing, 10 to 14 days into Zambia for stocked sizes. Most distributors we work with hold a small consignment of the units they move most, so a breakdown becomes a same-week fix instead of a six-week import. Can I send our range and dealer pricing? | E28: Gearbox supply for Access Energy Solutions Pty Ltd | F28: sajad@accessenergys.com | G28: MD | H28: Zambia | J28: Distributor | K28: A | L28: C004 | M28: English | N28: http://www.linkedin.com/in/sajad-ahmed-2ba5b5112 | O28: accessenergys.com | Q28: 4 | R28: environmental services | S28: Stocking terms and margin - lead with the commercial offer to the MD/GM, not the spec sheet | U28: Not contacted
A29: Dirk | B29: Wet | C29: BIA GROUP | D29: Hi Dirk, BIA GROUP keeps its customers running, and the final drives, travel and swing drives on the machines you support are what sit idle when a gearbox is on backorder. We supply industrial and mobile gearboxes - helical, bevel-helical, planetary, travel and swing drives - at trade pricing, 10 to 14 days into Zambia for stocked sizes. Most distributors we work with hold a small consignment of the units they move most, so a breakdown becomes a same-week fix instead of a six-week import. Can I send our range and dealer pricing? | E29: Gearbox supply for BIA GROUP | F29: dirk.dewet@biagroup.com | G29: Project Operation Manager | H29: Zambia | I29: Lusaka | J29: Distributor | K29: A | L29: C012 | M29: English | N29: http://www.linkedin.com/in/dirk-de-wet-8969b189 | O29: biagroup.com | P29: +32 2 689 28 11 | Q29: 1300 | R29: machinery | S29: Stocking terms and margin - lead with the commercial offer to the MD/GM, not the spec sheet | T29: HQ abroad (Mauritius) - verify local buying authority | U29: Not contacted
A30: Cobus | B30: Potgieter | C30: BL&D Plant Hire & Sales | D30: Hi Cobus, BL&D Plant Hire & Sales keeps its customers running, and the gearboxes on the plant in your hire and sales fleet are what sit idle when a gearbox is on backorder. We supply industrial and mobile gearboxes - helical, bevel-helical, planetary, travel and swing drives - at trade pricing, 10 to 14 days into Zambia for stocked sizes. Most distributors we work with hold a small consignment of the units they move most, so a breakdown becomes a same-week fix instead of a six-week import. Can I send our range and dealer pricing? | E30: Gearbox supply for BL&D Plant Hire & Sales | F30: cobus@bldequipment.com | G30: Branch Manager | H30: Zambia | J30: Distributor | K30: A | L30: C013 | M30: English | N30: http://www.linkedin.com/in/cobus-potgieter-68204494 | O30: bldequipment.com | Q30: 76 | R30: machinery | S30: Stocking terms and margin - lead with the commercial offer to the MD/GM, not the spec sheet | U30: Not contacted
A31: Samson | B31: Chingozho | C31: Bell Equipment Mining & Construction | D31: Hi Samson, Bell Equipment Mining & Construction keeps its customers running, and the drivetrains and hubs on the ADTs you support are what sit idle when a gearbox is on backorder. We supply industrial and mobile gearboxes - helical, bevel-helical, planetary, travel and swing drives - at trade pricing, 10 to 14 days into Zambia for stocked sizes. Most distributors we work with hold a small consignment of the units they move most, so a breakdown becomes a same-week fix instead of a six-week import. Can I send our range and dealer pricing? | E31: Gearbox supply for Bell Equipment Mining & Construction | F31: samson.chingozho@bellequipment.com | G31: Managing Director | H31: Zambia | J31: Distributor | K31: A | L31: C020 | M31: English | N31: http://www.linkedin.com/in/samson-chingozho-b584a212 | O31: bellequipment.com | P31: +27 35 907 9111 | Q31: 3500 | R31: machinery | S31: Stocking terms and margin - lead with the commercial offer to the MD/GM, not the spec sheet | T31: HQ abroad (South Africa) - verify local buying authority | U31: Not contacted
A32: Bevin | B32: Samwata | C32: Blumaq, S.A. | D32: Hi Bevin, Blumaq, S.A. keeps its customers running, and the final drives and travel drives your customers order most are what sit idle when a gearbox is on backorder. We supply industrial and mobile gearboxes - helical, bevel-helical, planetary, travel and swing drives - at trade pricing, 10 to 14 days into Zambia for stocked sizes. Most distributors we work with hold a small consignment of the units they move most, so a breakdown becomes a same-week fix instead of a six-week import. Can I send our range and dealer pricing? | E32: Gearbox supply for Blumaq, S.A. | F32: bevin.samwata@blumaq.com | G32: Branch Manager | H32: Zambia | I32: Kitwe | J32: Distributor | K32: A | L32: C021 | M32: English | N32: http://www.linkedin.com/in/bevin-samwata-76765a64 | O32: blumaq.com | P32: +34 964 69 70 30 | Q32: 250 | R32: machinery | S32: Stocking terms and margin - lead with the commercial offer to the MD/GM, not the spec sheet | T32: HQ abroad (Spain) - verify local buying authority | U32: Not contacted
A33: Henry | B33: Kapesa | C33: Bordertec Limited | D33: Hi Henry, Bordertec Limited keeps its customers running, and the gearboxes your industrial customers ask you to source are what sit idle when a gearbox is on backorder. We supply industrial and mobile gearboxes - helical, bevel-helical, planetary, travel and swing drives - at trade pricing, 10 to 14 days into Zambia for stocked sizes. Most distributors we work with hold a small consignment of the units they move most, so a breakdown becomes a same-week fix instead of a six-week import. Can I send our range and dealer pricing? | E33: Gearbox supply for Bordertec Limited | F33: henry@bordertecltd.com | G33: Managing Director | H33: Zambia | J33: Distributor | K33: A | L33: C023 | M33: English | N33: http://www.linkedin.com/in/henry-kapesa-044b16aa | O33: bordertec.co.zm | Q33: 5 | R33: management consulting | S33: Stocking terms and margin - lead with the commercial offer to the MD/GM, not the spec sheet | U33: Not contacted
A34: Jinu | B34: Raj | C34: DGC AFRICA | D34: Hi Jinu, DGC AFRICA keeps its customers running, and the gearboxes on the industrial plant you inspect and maintain are what sit idle when a gearbox is on backorder. We supply industrial and mobile gearboxes - helical, bevel-helical, planetary, travel and swing drives - at trade pricing, 10 to 14 days into Zambia for stocked sizes. Most distributors we work with hold a small consignment of the units they move most, so a breakdown becomes a same-week fix instead of a six-week import. Can I send our range and dealer pricing? | E34: Gearbox supply for DGC AFRICA | F34: jinu@dgc-africa.com | G34: General Manager | H34: Zambia | J34: Distributor | K34: A | L34: C037 | M34: English | N34: http://www.linkedin.com/in/jinu-raj-b51a2b15a | O34: dgc-africa.com | P34: +27 16 421 3720 | Q34: 200 | R34: mining & metals | S34: Stocking terms and margin - lead with the commercial offer to the MD/GM, not the spec sheet | T34: HQ abroad (South Africa) - verify local buying authority | U34: Not contacted
A35: Gregory | B35: Gavazzi | C35: Doppio Mining Equipment | D35: Hi Gregory, Doppio Mining Equipment keeps its customers running, and the gearboxes your mining equipment customers ask for are what sit idle when a gearbox is on backorder. We supply industrial and mobile gearboxes - helical, bevel-helical, planetary, travel and swing drives - at trade pricing, 10 to 14 days into Zambia for stocked sizes. Most distributors we work with hold a small consignment of the units they move most, so a breakdown becomes a same-week fix instead of a six-week import. Can I send our range and dealer pricing? | E35: Gearbox supply for Doppio Mining Equipment | F35: greg@doppioequipment.com | G35: Managing Director | H35: Zambia | J35: Distributor | K35: A | L35: C043 | M35: English | N35: http://www.linkedin.com/in/gregory-gavazzi-97ba9713a | O35: doppioequipment.com | Q35: 4 | R35: mining & metals | S35: Stocking terms and margin - lead with the commercial offer to the MD/GM, not the spec sheet | U35: Not contacted
A36: Chongo | B36: Mumba | C36: Hebei Aojin Machinery Co.,Ltd. | D36: Hi Chongo, Hebei Aojin Machinery Co.,Ltd. keeps its customers running, and the gearboxes on the machinery you bring into the market are what sit idle when a gearbox is on backorder. We supply industrial and mobile gearboxes - helical, bevel-helical, planetary, travel and swing drives - at trade pricing, 10 to 14 days into Zambia for stocked sizes. Most distributors we work with hold a small consignment of the units they move most, so a breakdown becomes a same-week fix instead of a six-week import. Can I send our range and dealer pricing? | E36: Gearbox supply for Hebei Aojin Machinery Co.,Ltd. | F36: chongom@aoj-pump.com | G36: Technical Sales Manager | H36: Zambia | J36: Distributor | K36: A | L36: C059 | M36: English | N36: http://www.linkedin.com/in/chongo-mumba-13295520 | O36: aoj-pump.com | P36: +86 311 8880 2472 | Q36: 150 | R36: machinery | S36: Stocking terms and margin - lead with the commercial offer to the MD/GM, not the spec sheet | T36: HQ abroad (China) - verify local buying authority | U36: Not contacted
A37: Arne | B37: Thorkildsen | C37: Hitachi Construction Machinery | D37: Hi Arne, Hitachi Construction Machinery keeps its customers running, and the travel and swing drives on the excavators you support are what sit idle when a gearbox is on backorder. We supply industrial and mobile gearboxes - helical, bevel-helical, planetary, travel and swing drives - at trade pricing, 10 to 14 days into Zambia for stocked sizes. Most distributors we work with hold a small consignment of the units they move most, so a breakdown becomes a same-week fix instead of a six-week import. Can I send our range and dealer pricing? | E37: Gearbox supply for Hitachi Construction Machinery | F37: arne.thorkildsen@hcmaf.com | G37: Branch Operations Manager | H37: Zambia | J37: Distributor | K37: A | L37: C060 | M37: English | N37: http://www.linkedin.com/in/arne-thorkildsen-336b2b82 | O37: hitachicm.com | P37: +81 358-26-8100 | Q37: 26000 | R37: machinery | S37: Stocking terms and margin - lead with the commercial offer to the MD/GM, not the spec sheet | T37: HQ abroad (Japan) - verify local buying authority | U37: Not contacted
A38: Henri | B38: Wassink | C38: Liebherr Group | D38: Hi Henri, Liebherr Group keeps its customers running, and the final and travel drives on the mining machines you support are what sit idle when a gearbox is on backorder. We supply industrial and mobile gearboxes - helical, bevel-helical, planetary, travel and swing drives - at trade pricing, 10 to 14 days into Zambia for stocked sizes. Most distributors we work with hold a small consignment of the units they move most, so a breakdown becomes a same-week fix instead of a six-week import. Can I send our range and dealer pricing? | E38: Gearbox supply for Liebherr Group | F38: hendrik.wassink@liebherr.com | G38: Managing Director - Administration | H38: Zambia | J38: Distributor | K38: A | L38: C070 | M38: English | N38: http://www.linkedin.com/in/henri-wassink-60322140 | O38: liebherr.com | P38: +49 735 1410 | Q38: 54000 | R38: machinery | S38: Stocking terms and margin - lead with the commercial offer to the MD/GM, not the spec sheet | T38: HQ abroad (Germany) - verify local buying authority | U38: Not contacted
A39: Yoginder | B39: Singh | C39: R A Consulting Services (RACS) | D39: Hi Yoginder, R A Consulting Services (RACS) keeps its customers running, and the gearboxes on the plant that passes through your workshop are what sit idle when a gearbox is on backorder. We supply industrial and mobile gearboxes - helical, bevel-helical, planetary, travel and swing drives - at trade pricing, 10 to 14 days into Zambia for stocked sizes. Most distributors we work with hold a small consignment of the units they move most, so a breakdown becomes a same-week fix instead of a six-week import. Can I send our range and dealer pricing? | E39: Gearbox supply for R A Consulting Services (RACS) | F39: yoginder@racsafrica.com | G39: Workshop Manager | H39: Zambia | J39: Distributor | K39: A | L39: C098 | M39: English | N39: http://www.linkedin.com/in/yoginder-singh-944003180 | O39: racsafrica.com | P39: +267 393 9773 | Q39: 87 | R39: information technology & services | S39: Stocking terms and margin - lead with the commercial offer to the MD/GM, not the spec sheet | U39: Not contacted
A40: Simon | B40: Kazunda | C40: SAFE KAHYA Limited | D40: Hi Simon, SAFE KAHYA Limited keeps its customers running, and the gearboxes your industrial customers ask you to source are what sit idle when a gearbox is on backorder. We supply industrial and mobile gearboxes - helical, bevel-helical, planetary, travel and swing drives - at trade pricing, 10 to 14 days into Zambia for stocked sizes. Most distributors we work with hold a small consignment of the units they move most, so a breakdown becomes a same-week fix instead of a six-week import. Can I send our range and dealer pricing? | E40: Gearbox supply for SAFE KAHYA Limited | F40: simon.kazunda@safekahya.com | G40: Managing Director | H40: Zambia | J40: Distributor | K40: A | L40: C103 | M40: English | N40: http://www.linkedin.com/in/simon-kazunda-46655b21 | O40: safekahya.com | Q40: 1 | R40: electrical/electronic manufacturing | S40: Stocking terms and margin - lead with the commercial offer to the MD/GM, not the spec sheet | U40: Not contacted
A41: Ashok | B41: Oza | C41: Saro Agro Industrial Ltd | D41: Hi Ashok, Saro Agro Industrial Ltd keeps its customers running, and the gearboxes on the implements, irrigation and processing equipment you sell are what sit idle when a gearbox is on backorder. We supply industrial and mobile gearboxes - helical, bevel-helical, planetary, travel and swing drives - at trade pricing, 10 to 14 days into Zambia for stocked sizes. Most distributors we work with hold a small consignment of the units they move most, so a breakdown becomes a same-week fix instead of a six-week import. Can I send our range and dealer pricing? | E41: Gearbox supply for Saro Agro Industrial Ltd | F41: ashok@saroagri.co.zm | G41: Managing Director | H41: Zambia | J41: Distributor | K41: A | L41: C109 | M41: English | N41: http://www.linkedin.com/in/ashok-oza-286ab513 | O41: sarozambia.com | P41: +1 260-241-4779 | Q41: 300 | R41: consumer goods | S41: Stocking terms and margin - lead with the commercial offer to the MD/GM, not the spec sheet | U41: Not contacted
A42: Tim | B42: Mumba | C42: Scamont and Karlsons Mining Solutions (SKMS) | D42: Hi Tim, Scamont and Karlsons Mining Solutions (SKMS) keeps its customers running, and the gearboxes on the mining equipment you supply and support are what sit idle when a gearbox is on backorder. We supply industrial and mobile gearboxes - helical, bevel-helical, planetary, travel and swing drives - at trade pricing, 10 to 14 days into Zambia for stocked sizes. Most distributors we work with hold a small consignment of the units they move most, so a breakdown becomes a same-week fix instead of a six-week import. Can I send our range and dealer pricing? | E42: Gearbox supply for Scamont and Karlsons Mining Solutions (SKMS) | F42: timmy.mumba@skmsltd.com | G42: General Manager Sales & Technical | H42: Zambia | J42: Distributor | K42: A | L42: C110 | M42: English | N42: http://www.linkedin.com/in/tim-mumba-49963488 | O42: skmsltd.com | Q42: 16 | R42: mining & metals | S42: Stocking terms and margin - lead with the commercial offer to the MD/GM, not the spec sheet | U42: Not contacted
A43: Justin | B43: Ricquebourg | C43: Selected Supplies | D43: Hi Justin, Selected Supplies keeps its customers running, and the gearboxes your industrial and mining customers ask for are what sit idle when a gearbox is on backorder. We supply industrial and mobile gearboxes - helical, bevel-helical, planetary, travel and swing drives - at trade pricing, 10 to 14 days into Zambia for stocked sizes. Most distributors we work with hold a small consignment of the units they move most, so a breakdown becomes a same-week fix instead of a six-week import. Can I send our range and dealer pricing? | E43: Gearbox supply for Selected Supplies | F43: justin.r@sszam.com | G43: Group Managing Director | H43: Zambia | J43: Distributor | K43: A | L43: C111 | M43: English | N43: http://www.linkedin.com/in/justin-de-ricquebourg-172539106 | O43: selectedsupplies.com | P43: +258 87 011 0660 | Q43: 92 | R43: retail | S43: Stocking terms and margin - lead with the commercial offer to the MD/GM, not the spec sheet | T43: HQ abroad (Mozambique) - verify local buying authority | U43: Not contacted
A44: Sean | B44: Bester | C44: Selected Supplies | D44: Hi Sean, Selected Supplies keeps its customers running, and the gearboxes your industrial and mining customers ask for are what sit idle when a gearbox is on backorder. We supply industrial and mobile gearboxes - helical, bevel-helical, planetary, travel and swing drives - at trade pricing, 10 to 14 days into Zambia for stocked sizes. Most distributors we work with hold a small consignment of the units they move most, so a breakdown becomes a same-week fix instead of a six-week import. Can I send our range and dealer pricing? | E44: Gearbox supply for Selected Supplies | F44: sean.bester@selectedsupplies.com | G44: Regional Commercial and Operations Manager | H44: Zambia | J44: Distributor | K44: A | L44: C111 | M44: English | N44: http://www.linkedin.com/in/sean-bester-14570911a | O44: selectedsupplies.com | P44: +258 87 011 0660 | Q44: 92 | R44: retail | S44: Stocking terms and margin - lead with the commercial offer to the MD/GM, not the spec sheet | T44: HQ abroad (Mozambique) - verify local buying authority | U44: Not contacted
A45: Robert | B45: Chisenga | C45: Sulzer | D45: Hi Robert, Sulzer keeps its customers running, and the gearboxes driving the pumps and rotating equipment you service are what sit idle when a gearbox is on backorder. We supply industrial and mobile gearboxes - helical, bevel-helical, planetary, travel and swing drives - at trade pricing, 10 to 14 days into Zambia for stocked sizes. Most distributors we work with hold a small consignment of the units they move most, so a breakdown becomes a same-week fix instead of a six-week import. Can I send our range and dealer pricing? | E45: Gearbox supply for Sulzer | F45: robert.chisenga@sulzer.com | G45: Managing Director | H45: Zambia | I45: Chingola | J45: Distributor | K45: A | L45: C116 | M45: English | N45: http://www.linkedin.com/in/robert-chisenga-960b0887 | O45: sulzer.com | P45: +41 52 262 30 00 | Q45: 14000 | R45: machinery | S45: Stocking terms and margin - lead with the commercial offer to the MD/GM, not the spec sheet | T45: HQ abroad (Switzerland) - verify local buying authority | U45: Not contacted
A46: Madalitso | B46: Banda | C46: Unirate Investments Limited | D46: Hi Madalitso, Unirate Investments Limited keeps its customers running, and the gearboxes your industrial customers ask you to source are what sit idle when a gearbox is on backorder. We supply industrial and mobile gearboxes - helical, bevel-helical, planetary, travel and swing drives - at trade pricing, 10 to 14 days into Zambia for stocked sizes. Most distributors we work with hold a small consignment of the units they move most, so a breakdown becomes a same-week fix instead of a six-week import. Can I send our range and dealer pricing? | E46: Gearbox supply for Unirate Investments Limited | F46: madalitso@unirate.co.zm | G46: Managing Director | H46: Zambia | J46: Distributor | K46: A | L46: C125 | M46: English | N46: http://www.linkedin.com/in/madalitso-banda-bab64215 | O46: unirate.co.zm | Q46: 21 | R46: logistics & supply chain | S46: Stocking terms and margin - lead with the commercial offer to the MD/GM, not the spec sheet | U46: Not contacted
A47: Mlayana | B47: Jasmin | C47: Younique Engineering Limited | D47: Hi Mlayana, Younique Engineering Limited keeps its customers running, and the gearboxes your industrial clients ask you to source are what sit idle when a gearbox is on backorder. We supply industrial and mobile gearboxes - helical, bevel-helical, planetary, travel and swing drives - at trade pricing, 10 to 14 days into Zambia for stocked sizes. Most distributors we work with hold a small consignment of the units they move most, so a breakdown becomes a same-week fix instead of a six-week import. Can I send our range and dealer pricing? | E47: Gearbox supply for Younique Engineering Limited | F47: mlayana@younique-engineering.com | G47: Co-Founder & Managing Director | H47: Zambia | I47: Lusaka | J47: Distributor | K47: A | L47: C133 | M47: English | N47: http://www.linkedin.com/in/mlayanachisi | O47: younique-engineering.com | Q47: 3 | R47: machinery | S47: Stocking terms and margin - lead with the commercial offer to the MD/GM, not the spec sheet | U47: Not contacted
A48: Badr | B48: Zein | C48: Dar | D48: Olá Badr, Na Dar, os redutores e accionamentos que especificam nos projectos industriais são o que pára a produção quando um redutor falha. A resposta habitual dos fornecedores é doze semanas. Temos em stock redutores helicoidais, cónicos e planetários, e substituições compatíveis com SEW-Eurodrive, Flender, Bonfiglioli e David Brown - 10 a 14 dias até Angola para as medidas em stock, 4 a 6 semanas por encomenda, com recondicionamento por troca. Envie-me as unidades da vossa lista de peças críticas e respondo com preço e prazo, para terem uma segunda fonte registada antes de precisarem. | E48: Prazos de entrega de redutores para a Dar | F48: badr.zein@dar.com | G48: Mechanical Engineer | H48: Angola | I48: Luanda | J48: Mining/Construction | K48: B | L48: C040 | M48: Portuguese | N48: http://www.linkedin.com/in/badr-zein-78a891109 | O48: dar.com | P48: +961 1 790 002 | Q48: 14000 | R48: design / civil engineering | S48: Downtime on plant and fleet drives - lead with lead time and availability | T48: HQ abroad (Lebanon) - verify local buying authority | U48: Not contacted
A49: Georges | B49: Stelly | C49: Dar | D49: Olá Georges, Na Dar, os redutores e accionamentos que especificam nos projectos industriais são o que pára a produção quando um redutor falha. A resposta habitual dos fornecedores é doze semanas. Temos em stock redutores helicoidais, cónicos e planetários, e substituições compatíveis com SEW-Eurodrive, Flender, Bonfiglioli e David Brown - 10 a 14 dias até Angola para as medidas em stock, 4 a 6 semanas por encomenda, com recondicionamento por troca. Envie-me as unidades da vossa lista de peças críticas e respondo com preço e prazo, para terem uma segunda fonte registada antes de precisarem. | E49: Prazos de entrega de redutores para a Dar | F49: georges.stelly@dar.com | G49: Mechanical Engineer | H49: Angola | I49: Luanda | J49: Mining/Construction | K49: B | L49: C040 | M49: Portuguese | N49: http://www.linkedin.com/in/georges-stelly-980898196 | O49: dar.com | P49: +961 1 790 002 | Q49: 14000 | R49: design / civil engineering | S49: Downtime on plant and fleet drives - lead with lead time and availability | T49: HQ abroad (Lebanon) - verify local buying authority | U49: Not contacted
A50: Vitor | B50: Mendes | C50: ESA - Engineering Services Angola | D50: Olá Vitor, Na ESA - Engineering Services Angola, os accionamentos dos equipamentos industriais que assistem em obra são o que pára a produção quando um redutor falha. A resposta habitual dos fornecedores é doze semanas. Temos em stock redutores helicoidais, cónicos e planetários, e substituições compatíveis com SEW-Eurodrive, Flender, Bonfiglioli e David Brown - 10 a 14 dias até Angola para as medidas em stock, 4 a 6 semanas por encomenda, com recondicionamento por troca. Envie-me as unidades da vossa lista de peças críticas e respondo com preço e prazo, para terem uma segunda fonte registada antes de precisarem. | E50: Prazos de entrega de redutores para a ESA - Engineering Services Angola | F50: vitor.mendes@esa-angola.com | G50: Mechanical Engineer | H50: Angola | J50: Mining/Construction | K50: B | L50: C047 | M50: Portuguese | N50: http://www.linkedin.com/in/vitor-mendes-586921b9 | Q50: 61 | R50: construction | S50: Downtime on plant and fleet drives - lead with lead time and availability | U50: Not contacted
A51: Rosmely | B51: Diaz | C51: Elecnor Group | D51: Olá Rosmely, Na Elecnor Group, os accionamentos dos equipamentos de obra e das instalações que constroem são o que pára a produção quando um redutor falha. A resposta habitual dos fornecedores é doze semanas. Temos em stock redutores helicoidais, cónicos e planetários, e substituições compatíveis com SEW-Eurodrive, Flender, Bonfiglioli e David Brown - 10 a 14 dias até Angola para as medidas em stock, 4 a 6 semanas por encomenda, com recondicionamento por troca. Envie-me as unidades da vossa lista de peças críticas e respondo com preço e prazo, para terem uma segunda fonte registada antes de precisarem. | E51: Prazos de entrega de redutores para a Elecnor Group | F51: rosmely.diaz@elecnor.com | G51: Mechanical Engineer | H51: Angola | J51: Mining/Construction | K51: B | L51: C048 | M51: Portuguese | N51: http://www.linkedin.com/in/rosmely-diaz-b26a15171 | O51: grupoelecnor.com | Q51: 29000 | R51: construction | S51: Downtime on plant and fleet drives - lead with lead time and availability | T51: HQ abroad (Spain) - verify local buying authority | U51: Not contacted
A52: Ernesto | B52: Manuel | C52: Endiama | D52: Olá Ernesto, Grande parte da despesa em redutores concentra-se num único fornecedor com prazos longos. Funciona até a unidade estar em rutura - e na Endiama isso significa os accionamentos de britagem, lavagem e transporte nas operações mineiras. Fornecemos redutores helicoidais, cónicos e planetários, e substituições compatíveis com SEW-Eurodrive, Flender, Bonfiglioli e David Brown - 10 a 14 dias até Angola para as medidas em stock, 4 a 6 semanas por encomenda, com recondicionamento por troca. Não é preciso mudar de fornecedor: basta consultarem-nos como segunda fonte. O que precisam da nossa parte para o registo de fornecedor? | E52: Segunda fonte para redutores - Endiama | F52: ernesto.manuel@endiama.co.ao | G52: Senior Procurement Manager | H52: Angola | I52: Luanda | J52: Mining/Construction | K52: B | L52: C049 | M52: Portuguese | N52: http://www.linkedin.com/in/ernesto-manuel-9287b186 | O52: endiama.co.ao | P52: +244 222 334 585 | Q52: 310 | R52: mining & metals | S52: Downtime on plant and fleet drives - lead with lead time and availability | U52: Not contacted
A53: Theuns | B53: Oosthuizen | C53: Equipment & Controls Africa | D53: Olá Theuns, Na Equipment & Controls Africa, os redutores dos equipamentos industriais que assistem são o que pára a produção quando um redutor falha. A resposta habitual dos fornecedores é doze semanas. Temos em stock redutores helicoidais, cónicos e planetários, e substituições compatíveis com SEW-Eurodrive, Flender, Bonfiglioli e David Brown - 10 a 14 dias até Angola para as medidas em stock, 4 a 6 semanas por encomenda, com recondicionamento por troca. Envie-me as unidades da vossa lista de peças críticas e respondo com preço e prazo, para terem uma segunda fonte registada antes de precisarem. | E53: Prazos de entrega de redutores para a Equipment & Controls Africa | F53: theuns.oosthuizen@ec-africa.com | G53: Workshop Manager | H53: Angola | I53: Soyo | J53: Mining/Construction | K53: B | L53: C050 | M53: Portuguese | N53: http://www.linkedin.com/in/theuns-oosthuizen-1292091a7 | O53: ec-africa.com | P53: +1 412-489-3000 | Q53: 71 | R53: oil & energy | S53: Downtime on plant and fleet drives - lead with lead time and availability | T53: HQ abroad (United States) - verify local buying authority | U53: Not contacted
A54: Aguinaldo | B54: Antunes | C54: Grupo Omatapalo | D54: Olá Aguinaldo, Na Grupo Omatapalo, os accionamentos das centrais de betão, britadores e transportadores de obra são o que pára a produção quando um redutor falha. A resposta habitual dos fornecedores é doze semanas. Temos em stock redutores helicoidais, cónicos e planetários, e substituições compatíveis com SEW-Eurodrive, Flender, Bonfiglioli e David Brown - 10 a 14 dias até Angola para as medidas em stock, 4 a 6 semanas por encomenda, com recondicionamento por troca. Envie-me as unidades da vossa lista de peças críticas e respondo com preço e prazo, para terem uma segunda fonte registada antes de precisarem. | E54: Prazos de entrega de redutores para a Grupo Omatapalo | F54: aguinaldoantunes@omatapalo.com | G54: Mechanical Engineer | H54: Angola | I54: Luanda | J54: Mining/Construction | K54: B | L54: C057 | M54: Portuguese | N54: http://www.linkedin.com/in/agui-antunes | O54: omatapalo.com | Q54: 12000 | R54: construction | S54: Downtime on plant and fleet drives - lead with lead time and availability | T54: HQ abroad (Austria) - verify local buying authority | U54: Not contacted
A55: Pradeep | B55: Kukna | C55: Marlin Natural Stones | D55: Olá Pradeep, Na Marlin Natural Stones, os accionamentos das serras, britadores e transportadores da pedreira são o que pára a produção quando um redutor falha. A resposta habitual dos fornecedores é doze semanas. Temos em stock redutores helicoidais, cónicos e planetários, e substituições compatíveis com SEW-Eurodrive, Flender, Bonfiglioli e David Brown - 10 a 14 dias até Angola para as medidas em stock, 4 a 6 semanas por encomenda, com recondicionamento por troca. Envie-me as unidades da vossa lista de peças críticas e respondo com preço e prazo, para terem uma segunda fonte registada antes de precisarem. | E55: Prazos de entrega de redutores para a Marlin Natural Stones | F55: pradeep.kukna@marlin.co.ao | G55: Workshop Manager | H55: Angola | I55: Lubango | J55: Mining/Construction | K55: B | L55: C073 | M55: Portuguese | N55: http://www.linkedin.com/in/pradeep-kukna-210997173 | O55: marlin.co.ao | Q55: 22 | R55: mechanical or industrial engineering | S55: Downtime on plant and fleet drives - lead with lead time and availability | U55: Not contacted
A56: Aurelio | B56: Numa | C56: Metalosul | D56: Olá Aurelio, Na Metalosul, os accionamentos das máquinas de transformação e das linhas de produção são o que pára a produção quando um redutor falha. A resposta habitual dos fornecedores é doze semanas. Temos em stock redutores helicoidais, cónicos e planetários, e substituições compatíveis com SEW-Eurodrive, Flender, Bonfiglioli e David Brown - 10 a 14 dias até Angola para as medidas em stock, 4 a 6 semanas por encomenda, com recondicionamento por troca. Envie-me as unidades da vossa lista de peças críticas e respondo com preço e prazo, para terem uma segunda fonte registada antes de precisarem. | E56: Prazos de entrega de redutores para a Metalosul | F56: aurelio.numa@metalosul.com | G56: Mechanical Engineer | H56: Angola | I56: Luanda | J56: Mining/Construction | K56: B | L56: C075 | M56: Portuguese | N56: http://www.linkedin.com/in/aur%c3%a9lio-livongue-numa-b620922bb | O56: metalosul.com | P56: +244 931 599 625 | Q56: 170 | R56: mining & metals | S56: Downtime on plant and fleet drives - lead with lead time and availability | U56: Not contacted
A57: William | B57: Sebastian | C57: Odebrecht Engenharia & Construção | D57: Olá William, Na Odebrecht Engenharia & Construção, os accionamentos das centrais de betão, gruas e equipamento de obra são o que pára a produção quando um redutor falha. A resposta habitual dos fornecedores é doze semanas. Temos em stock redutores helicoidais, cónicos e planetários, e substituições compatíveis com SEW-Eurodrive, Flender, Bonfiglioli e David Brown - 10 a 14 dias até Angola para as medidas em stock, 4 a 6 semanas por encomenda, com recondicionamento por troca. Envie-me as unidades da vossa lista de peças críticas e respondo com preço e prazo, para terem uma segunda fonte registada antes de precisarem. | E57: Prazos de entrega de redutores para a Odebrecht Engenharia & Construção | F57: williams@odebrecht.com | G57: Mechanical Engineer | H57: Angola | I57: Cabinda | J57: Mining/Construction | K57: B | L57: C086 | M57: Portuguese | N57: http://www.linkedin.com/in/william-sebastian-3002852a8 | Q57: 6800 | R57: civil engineering | S57: Downtime on plant and fleet drives - lead with lead time and availability | T57: HQ abroad (Brazil) - verify local buying authority | U57: Not contacted
A58: Antonio | B58: Zacarias | C58: PROMETIM | D58: Olá Antonio, Na PROMETIM, os redutores que passam pela vossa oficina de manutenção industrial são o que pára a produção quando um redutor falha. A resposta habitual dos fornecedores é doze semanas. Temos em stock redutores helicoidais, cónicos e planetários, e substituições compatíveis com SEW-Eurodrive, Flender, Bonfiglioli e David Brown - 10 a 14 dias até Angola para as medidas em stock, 4 a 6 semanas por encomenda, com recondicionamento por troca. Envie-me as unidades da vossa lista de peças críticas e respondo com preço e prazo, para terem uma segunda fonte registada antes de precisarem. | E58: Prazos de entrega de redutores para a PROMETIM | F58: antonio.zacarias@prometim.net | G58: Workshop Manager | H58: Angola | I58: Cacuaco | J58: Mining/Construction | K58: B | L58: C089 | M58: Portuguese | N58: http://www.linkedin.com/in/ant%c3%b3nio-zacarias-b2131656 | O58: prometim.net | P58: +244 923 637 414 | Q58: 350 | R58: oil & energy | S58: Downtime on plant and fleet drives - lead with lead time and availability | U58: Not contacted
A59: Dario | B59: Dantas | C59: Sociedade Mineira de Catoca | D59: Olá Dario, Na Sociedade Mineira de Catoca, os accionamentos dos britadores, lavadores e transportadores da lavaria são o que pára a produção quando um redutor falha. A resposta habitual dos fornecedores é doze semanas. Temos em stock redutores helicoidais, cónicos e planetários, e substituições compatíveis com SEW-Eurodrive, Flender, Bonfiglioli e David Brown - 10 a 14 dias até Angola para as medidas em stock, 4 a 6 semanas por encomenda, com recondicionamento por troca. Envie-me as unidades da vossa lista de peças críticas e respondo com preço e prazo, para terem uma segunda fonte registada antes de precisarem. | E59: Prazos de entrega de redutores para a Sociedade Mineira de Catoca | F59: dario.dantas@catoca.com | G59: Mechanical Engineer | H59: Angola | I59: Luanda | J59: Mining/Construction | K59: B | L59: C115 | M59: Portuguese | N59: http://www.linkedin.com/in/dario-dantas-4755b1237 | O59: catoca.com | P59: +1 226-624-7001 | Q59: 3000 | R59: mining & metals | S59: Downtime on plant and fleet drives - lead with lead time and availability | U59: Not contacted
A60: James | B60: Biggar | C60: TechnipFMC | D60: Olá James, Na TechnipFMC, os accionamentos dos guinchos, gruas e equipamento de fabricação são o que pára a produção quando um redutor falha. A resposta habitual dos fornecedores é doze semanas. Temos em stock redutores helicoidais, cónicos e planetários, e substituições compatíveis com SEW-Eurodrive, Flender, Bonfiglioli e David Brown - 10 a 14 dias até Angola para as medidas em stock, 4 a 6 semanas por encomenda, com recondicionamento por troca. Envie-me as unidades da vossa lista de peças críticas e respondo com preço e prazo, para terem uma segunda fonte registada antes de precisarem. | E60: Prazos de entrega de redutores para a TechnipFMC | F60: james.biggar@technipfmc.com | G60: Workshop Manager | H60: Angola | J60: Mining/Construction | K60: B | L60: C120 | M60: Portuguese | N60: http://www.linkedin.com/in/james-biggar-0491a251 | O60: technipfmc.com | P60: +44 28 1591 4000 | Q60: 21000 | R60: oil & energy | S60: Downtime on plant and fleet drives - lead with lead time and availability | T60: HQ abroad (United Kingdom) - verify local buying authority | U60: Not contacted
A61: Eugenia | B61: Domingos | C61: TechnipFMC | D61: Olá Eugenia, Na TechnipFMC, os accionamentos dos guinchos, gruas e equipamento de fabricação são o que pára a produção quando um redutor falha. A resposta habitual dos fornecedores é doze semanas. Temos em stock redutores helicoidais, cónicos e planetários, e substituições compatíveis com SEW-Eurodrive, Flender, Bonfiglioli e David Brown - 10 a 14 dias até Angola para as medidas em stock, 4 a 6 semanas por encomenda, com recondicionamento por troca. Envie-me as unidades da vossa lista de peças críticas e respondo com preço e prazo, para terem uma segunda fonte registada antes de precisarem. | E61: Prazos de entrega de redutores para a TechnipFMC | F61: eugenia.domingos@technipfmc.com | G61: Mechanical Engineer | H61: Angola | I61: Luanda | J61: Mining/Construction | K61: B | L61: C120 | M61: Portuguese | N61: http://www.linkedin.com/in/eddomingos | O61: technipfmc.com | P61: +44 28 1591 4000 | Q61: 21000 | R61: oil & energy | S61: Downtime on plant and fleet drives - lead with lead time and availability | T61: HQ abroad (United Kingdom) - verify local buying authority | U61: Not contacted
A62: Seabi | B62: Sekhobe | C62: AECI Mining | D62: Hi Seabi, At AECI Mining, the augers, mixers and conveyor drives on your emulsion plants are the units that stop production when a gearbox goes. The usual answer from suppliers is twelve weeks. We hold helical, bevel-helical and planetary gearboxes, and supply drop-in replacements for SEW-Eurodrive, Flender, Bonfiglioli and David Brown - 10 to 14 days into Botswana for stocked sizes, 4 to 6 weeks made to order, with rebuild-on-exchange. Send me the units on your critical spares list and I'll come back with price and lead time, so you have a second source on file before you need one. | E62: Gearbox lead times for AECI Mining | F62: seabi.sekhobe@aeciworld.com | G62: Maintenance Manager | H62: Botswana | J62: Mining | K62: B | L62: C003 | M62: English | N62: http://www.linkedin.com/in/seabi-sekhobe-68671840 | O62: aecimining.com | P62: +27 11 806 8700 | Q62: 2500 | R62: mining & metals | S62: Downtime cost per hour on mill and conveyor drives - lead with lead time and availability | T62: HQ abroad (South Africa) - verify local buying authority | U62: Not contacted
A63: Tlamelo | B63: Rapata | C63: African Mining Services | D63: Hi Tlamelo, At African Mining Services, the drivetrains and final drives across your contract fleet are the units that stop production when a gearbox goes. The usual answer from suppliers is twelve weeks. We hold helical, bevel-helical and planetary gearboxes, and supply drop-in replacements for SEW-Eurodrive, Flender, Bonfiglioli and David Brown - 10 to 14 days into Botswana for stocked sizes, 4 to 6 weeks made to order, with rebuild-on-exchange. Send me the units on your critical spares list and I'll come back with price and lead time, so you have a second source on file before you need one. | E63: Gearbox lead times for African Mining Services | F63: trapata@amsgh.com | G63: Maintenance Manager | H63: Botswana | I63: Gaborone | J63: Mining | K63: B | L63: C007 | M63: English | N63: http://www.linkedin.com/in/tlamelo-rapata-7a33a596 | O63: amsgh.com | P63: +233 30 261 1333 | Q63: 670 | R63: mining & metals | S63: Downtime cost per hour on mill and conveyor drives - lead with lead time and availability | T63: HQ abroad (Ghana) - verify local buying authority | U63: Not contacted
A64: Andries | B64: Garnett | C64: BME, a Member of the Omnia Group | D64: Hi Andries, At BME, a Member of the Omnia Group, the augers, mixers and pump drives on your emulsion and bulk explosives plants are the units that stop production when a gearbox goes. The usual answer from suppliers is twelve weeks. We hold helical, bevel-helical and planetary gearboxes, and supply drop-in replacements for SEW-Eurodrive, Flender, Bonfiglioli and David Brown - 10 to 14 days into Botswana for stocked sizes, 4 to 6 weeks made to order, with rebuild-on-exchange. Send me the units on your critical spares list and I'll come back with price and lead time, so you have a second source on file before you need one. | E64: Gearbox lead times for BME, a Member of the Omnia Group | F64: andries.garnett@bme.co.za | G64: Workshop Manager | H64: Botswana | J64: Mining | K64: B | L64: C014 | M64: English | N64: http://www.linkedin.com/in/andries-garnett-056a401a0 | O64: bme.co.za | Q64: 2000 | R64: mining & metals | S64: Downtime cost per hour on mill and conveyor drives - lead with lead time and availability | T64: HQ abroad (South Africa) - verify local buying authority | U64: Not contacted
A65: Sidney | B65: Kubuitsile | C65: Barminco | D65: Hi Sidney, At Barminco, the drivetrains on your underground loaders and trucks are the units that stop production when a gearbox goes. The usual answer from suppliers is twelve weeks. We hold helical, bevel-helical and planetary gearboxes, and supply drop-in replacements for SEW-Eurodrive, Flender, Bonfiglioli and David Brown - 10 to 14 days into Botswana for stocked sizes, 4 to 6 weeks made to order, with rebuild-on-exchange. Send me the units on your critical spares list and I'll come back with price and lead time, so you have a second source on file before you need one. | E65: Gearbox lead times for Barminco | F65: sidney.kubuitsile@barminco.com.au | G65: Site Reliability Engineer | H65: Botswana | J65: Mining | K65: B | L65: C018 | M65: English | N65: http://www.linkedin.com/in/sidney777 | O65: barminco.com.au | P65: +61 8 9416 1000 | Q65: 4300 | R65: mining & metals | S65: Downtime cost per hour on mill and conveyor drives - lead with lead time and availability | T65: HQ abroad (Australia) - verify local buying authority | U65: Not contacted
A66: Modise | B66: Moora | C66: Botswana Ash | D66: Hi Modise, At Botswana Ash, the dredger, conveyor and crystalliser drives at Sua Pan are the units that stop production when a gearbox goes. The usual answer from suppliers is twelve weeks. We hold helical, bevel-helical and planetary gearboxes, and supply drop-in replacements for SEW-Eurodrive, Flender, Bonfiglioli and David Brown - 10 to 14 days into Botswana for stocked sizes, 4 to 6 weeks made to order, with rebuild-on-exchange. Send me the units on your critical spares list and I'll come back with price and lead time, so you have a second source on file before you need one. | E66: Gearbox lead times for Botswana Ash | F66: mm1@botash.bw | G66: Maintenance Manager | H66: Botswana | I66: Francistown | J66: Mining | K66: B | L66: C024 | M66: English | N66: http://www.linkedin.com/in/modise-moora-7700b421 | O66: botash.bw | P66: +267 621 3210 | Q66: 190 | R66: chemicals | S66: Downtime cost per hour on mill and conveyor drives - lead with lead time and availability | U66: Not contacted
A67: Obakeng | B67: Matonyane | C67: Debswana Diamond Company | D67: Hi Obakeng, At Debswana Diamond Company, the crusher, scrubber and DMS plant drives, and the plant conveyors at Jwaneng and Orapa are the units that stop production when a gearbox goes. The usual answer from suppliers is twelve weeks. We hold helical, bevel-helical and planetary gearboxes, and supply drop-in replacements for SEW-Eurodrive, Flender, Bonfiglioli and David Brown - 10 to 14 days into Botswana for stocked sizes, 4 to 6 weeks made to order, with rebuild-on-exchange. Send me the units on your critical spares list and I'll come back with price and lead time, so you have a second source on file before you need one. | E67: Gearbox lead times for Debswana Diamond Company | F67: omatonyane@debswana.bw | G67: Mechanical Engineer | H67: Botswana | J67: Mining | K67: B | L67: C041 | M67: English | N67: http://www.linkedin.com/in/obakeng-matonyane-64081883 | O67: debswana.com | P67: +267 361 4200 | Q67: 6200 | R67: mining & metals | S67: Downtime cost per hour on mill and conveyor drives - lead with lead time and availability | U67: Not contacted
A68: Tebogo | B68: Tshane | C68: Debswana Diamond Company | D68: Hi Tebogo, At Debswana Diamond Company, the crusher, scrubber and DMS plant drives, and the plant conveyors at Jwaneng and Orapa are the units that stop production when a gearbox goes. The usual answer from suppliers is twelve weeks. We hold helical, bevel-helical and planetary gearboxes, and supply drop-in replacements for SEW-Eurodrive, Flender, Bonfiglioli and David Brown - 10 to 14 days into Botswana for stocked sizes, 4 to 6 weeks made to order, with rebuild-on-exchange. Send me the units on your critical spares list and I'll come back with price and lead time, so you have a second source on file before you need one. | E68: Gearbox lead times for Debswana Diamond Company | F68: ttshane@debswana.bw | G68: Plant Manager | H68: Botswana | J68: Mining | K68: B | L68: C041 | M68: English | N68: http://www.linkedin.com/in/tebogo-tshane-p-eng-b7284020 | O68: debswana.com | P68: +267 361 4200 | Q68: 6200 | R68: mining & metals | S68: Downtime cost per hour on mill and conveyor drives - lead with lead time and availability | U68: Not contacted
A69: Adam | B69: Masebola | C69: Debswana Diamond Company | D69: Hi Adam, At Debswana Diamond Company, the crusher, scrubber and DMS plant drives, and the plant conveyors at Jwaneng and Orapa are the units that stop production when a gearbox goes. The usual answer from suppliers is twelve weeks. We hold helical, bevel-helical and planetary gearboxes, and supply drop-in replacements for SEW-Eurodrive, Flender, Bonfiglioli and David Brown - 10 to 14 days into Botswana for stocked sizes, 4 to 6 weeks made to order, with rebuild-on-exchange. Send me the units on your critical spares list and I'll come back with price and lead time, so you have a second source on file before you need one. | E69: Gearbox lead times for Debswana Diamond Company | F69: amasebola@debswana.bw | G69: Plant Manager | H69: Botswana | I69: Gaborone | J69: Mining | K69: B | L69: C041 | M69: English | N69: http://www.linkedin.com/in/adam-masebola-b546b8121 | O69: debswana.com | P69: +267 361 4200 | Q69: 6200 | R69: mining & metals | S69: Downtime cost per hour on mill and conveyor drives - lead with lead time and availability | U69: Not contacted
A70: Phemelo | B70: Tshenolo | C70: Debswana Diamond Company | D70: Hi Phemelo, At Debswana Diamond Company, the crusher, scrubber and DMS plant drives, and the plant conveyors at Jwaneng and Orapa are the units that stop production when a gearbox goes. The usual answer from suppliers is twelve weeks. We hold helical, bevel-helical and planetary gearboxes, and supply drop-in replacements for SEW-Eurodrive, Flender, Bonfiglioli and David Brown - 10 to 14 days into Botswana for stocked sizes, 4 to 6 weeks made to order, with rebuild-on-exchange. Send me the units on your critical spares list and I'll come back with price and lead time, so you have a second source on file before you need one. | E70: Gearbox lead times for Debswana Diamond Company | F70: ptshenolo@debswana.bw | G70: Project Mechanical Engineer | H70: Botswana | J70: Mining | K70: B | L70: C041 | M70: English | N70: http://www.linkedin.com/in/phemelo-tshenolo-84881666 | O70: debswana.com | P70: +267 361 4200 | Q70: 6200 | R70: mining & metals | S70: Downtime cost per hour on mill and conveyor drives - lead with lead time and availability | U70: Not contacted
A71: Badiri | B71: Keitumetse | C71: Debswana Diamond Company | D71: Hi Badiri, Most gearbox spend sits with a single supplier on long lead times. That works until the unit is on backorder - and at Debswana Diamond Company that means the crusher, scrubber and DMS plant drives, and the plant conveyors at Jwaneng and Orapa. We supply helical, bevel-helical and planetary gearboxes and drop-in replacements for SEW-Eurodrive, Flender, Bonfiglioli and David Brown - 10 to 14 days into Botswana for stocked sizes, 4 to 6 weeks made to order, with rebuild-on-exchange. No switching required. Quote us against your current source and see where we land. What do you need from us for vendor registration? | E71: Second source for gearbox spares - Debswana Diamond Company | F71: bkeitumetse@debswana.bw | G71: Project Procurement Manager | H71: Botswana | J71: Mining | K71: B | L71: C041 | M71: English | N71: http://www.linkedin.com/in/badirikeitumetse | O71: debswana.com | P71: +267 361 4200 | Q71: 6200 | R71: mining & metals | S71: Downtime cost per hour on mill and conveyor drives - lead with lead time and availability | U71: Not contacted
A72: Kago | B72: Morale | C72: Debswana Diamond Company | D72: Hi Kago, At Debswana Diamond Company, the crusher, scrubber and DMS plant drives, and the plant conveyors at Jwaneng and Orapa are the units that stop production when a gearbox goes. The usual answer from suppliers is twelve weeks. We hold helical, bevel-helical and planetary gearboxes, and supply drop-in replacements for SEW-Eurodrive, Flender, Bonfiglioli and David Brown - 10 to 14 days into Botswana for stocked sizes, 4 to 6 weeks made to order, with rebuild-on-exchange. Send me the units on your critical spares list and I'll come back with price and lead time, so you have a second source on file before you need one. | E72: Gearbox lead times for Debswana Diamond Company | F72: kmorale@debswana.bw | G72: Engineering Manager Electrical | H72: Botswana | J72: Mining | K72: B | L72: C041 | M72: English | N72: http://www.linkedin.com/in/kago-morale-pr-eng-pmp-70383a110 | O72: debswana.com | P72: +267 361 4200 | Q72: 6200 | R72: mining & metals | S72: Downtime cost per hour on mill and conveyor drives - lead with lead time and availability | U72: Not contacted
A73: Gwere | B73: Albert | C73: Debswana Diamond Company | D73: Hi Gwere, At Debswana Diamond Company, the crusher, scrubber and DMS plant drives, and the plant conveyors at Jwaneng and Orapa are the units that stop production when a gearbox goes. The usual answer from suppliers is twelve weeks. We hold helical, bevel-helical and planetary gearboxes, and supply drop-in replacements for SEW-Eurodrive, Flender, Bonfiglioli and David Brown - 10 to 14 days into Botswana for stocked sizes, 4 to 6 weeks made to order, with rebuild-on-exchange. Send me the units on your critical spares list and I'll come back with price and lead time, so you have a second source on file before you need one. | E73: Gearbox lead times for Debswana Diamond Company | F73: agwere@debswana.bw | G73: Senior Engineering Manager | H73: Botswana | J73: Mining | K73: B | L73: C041 | M73: English | N73: http://www.linkedin.com/in/gwere-albert-7473968a | O73: debswana.com | P73: +267 361 4200 | Q73: 6200 | R73: mining & metals | S73: Downtime cost per hour on mill and conveyor drives - lead with lead time and availability | U73: Not contacted
A74: Keene | B74: Nkoane | C74: Debswana Diamond Company | D74: Hi Keene, At Debswana Diamond Company, the crusher, scrubber and DMS plant drives, and the plant conveyors at Jwaneng and Orapa are the units that stop production when a gearbox goes. The usual answer from suppliers is twelve weeks. We hold helical, bevel-helical and planetary gearboxes, and supply drop-in replacements for SEW-Eurodrive, Flender, Bonfiglioli and David Brown - 10 to 14 days into Botswana for stocked sizes, 4 to 6 weeks made to order, with rebuild-on-exchange. Send me the units on your critical spares list and I'll come back with price and lead time, so you have a second source on file before you need one. | E74: Gearbox lead times for Debswana Diamond Company | F74: knkoane@debswana.bw | G74: Senior Engineering Manager at Debswana Diamond Company | H74: Botswana | J74: Mining | K74: B | L74: C041 | M74: English | N74: http://www.linkedin.com/in/keene-nkoane-a4ba2893 | O74: debswana.com | P74: +267 361 4200 | Q74: 6200 | R74: mining & metals | S74: Downtime cost per hour on mill and conveyor drives - lead with lead time and availability | U74: Not contacted
A75: Omphile | B75: Mafunye | C75: Debswana Diamond Company | D75: Hi Omphile, At Debswana Diamond Company, the crusher, scrubber and DMS plant drives, and the plant conveyors at Jwaneng and Orapa are the units that stop production when a gearbox goes. The usual answer from suppliers is twelve weeks. We hold helical, bevel-helical and planetary gearboxes, and supply drop-in replacements for SEW-Eurodrive, Flender, Bonfiglioli and David Brown - 10 to 14 days into Botswana for stocked sizes, 4 to 6 weeks made to order, with rebuild-on-exchange. Send me the units on your critical spares list and I'll come back with price and lead time, so you have a second source on file before you need one. | E75: Gearbox lead times for Debswana Diamond Company | F75: omafunye@debswana.bw | G75: Principal Engineer-Mechanical | H75: Botswana | I75: Gaborone | J75: Mining | K75: B | L75: C041 | M75: English | N75: http://www.linkedin.com/in/omphile-mafunye-58364238 | O75: debswana.com | P75: +267 361 4200 | Q75: 6200 | R75: mining & metals | S75: Downtime cost per hour on mill and conveyor drives - lead with lead time and availability | U75: Not contacted
A76: Kevin | B76: Tladiyamoroba | C76: Debswana Diamond Company | D76: Hi Kevin, At Debswana Diamond Company, the crusher, scrubber and DMS plant drives, and the plant conveyors at Jwaneng and Orapa are the units that stop production when a gearbox goes. The usual answer from suppliers is twelve weeks. We hold helical, bevel-helical and planetary gearboxes, and supply drop-in replacements for SEW-Eurodrive, Flender, Bonfiglioli and David Brown - 10 to 14 days into Botswana for stocked sizes, 4 to 6 weeks made to order, with rebuild-on-exchange. Send me the units on your critical spares list and I'll come back with price and lead time, so you have a second source on file before you need one. | E76: Gearbox lead times for Debswana Diamond Company | F76: ktladiyamoroba@debswana.bw | G76: Mining Manager - Technical Services | H76: Botswana | J76: Mining | K76: B | L76: C041 | M76: English | N76: http://www.linkedin.com/in/kevin-tladiyamoroba | O76: debswana.com | P76: +267 361 4200 | Q76: 6200 | R76: mining & metals | S76: Downtime cost per hour on mill and conveyor drives - lead with lead time and availability | U76: Not contacted
A77: Edwin | B77: Sesinyi | C77: Minergy Ltd | D77: Hi Edwin, At Minergy Ltd, the crushing and screening plant drives at Masama are the units that stop production when a gearbox goes. The usual answer from suppliers is twelve weeks. We hold helical, bevel-helical and planetary gearboxes, and supply drop-in replacements for SEW-Eurodrive, Flender, Bonfiglioli and David Brown - 10 to 14 days into Botswana for stocked sizes, 4 to 6 weeks made to order, with rebuild-on-exchange. Send me the units on your critical spares list and I'll come back with price and lead time, so you have a second source on file before you need one. | E77: Gearbox lead times for Minergy Ltd | F77: edwin@minergycoal.com | G77: Mechanical Engineer | H77: Botswana | J77: Mining | K77: B | L77: C076 | M77: English | N77: http://www.linkedin.com/in/edwin-sesinyi-92187736 | O77: minergycoal.com | P77: +267 397 2891 | Q77: 19 | R77: mining & metals | S77: Downtime cost per hour on mill and conveyor drives - lead with lead time and availability | U77: Not contacted
A78: Mothusi | B78: Makwape | C78: Morupule Coal Mine | D78: Hi Mothusi, At Morupule Coal Mine, the coal conveyor, crusher and screen drives on the plant are the units that stop production when a gearbox goes. The usual answer from suppliers is twelve weeks. We hold helical, bevel-helical and planetary gearboxes, and supply drop-in replacements for SEW-Eurodrive, Flender, Bonfiglioli and David Brown - 10 to 14 days into Botswana for stocked sizes, 4 to 6 weeks made to order, with rebuild-on-exchange. Send me the units on your critical spares list and I'll come back with price and lead time, so you have a second source on file before you need one. | E78: Gearbox lead times for Morupule Coal Mine | F78: mmakwape@mcm.co.bw | G78: Mine Reliability Engineer | H78: Botswana | J78: Mining | K78: B | L78: C078 | M78: English | N78: http://www.linkedin.com/in/mothusi-makwape-bb323447 | O78: mcm.co.bw | P78: +267 492 0251 | Q78: 900 | R78: mining & metals | S78: Downtime cost per hour on mill and conveyor drives - lead with lead time and availability | U78: Not contacted
A79: Oaitse | B79: Medupe | C79: Morupule Coal Mine | D79: Hi Oaitse, At Morupule Coal Mine, the coal conveyor, crusher and screen drives on the plant are the units that stop production when a gearbox goes. The usual answer from suppliers is twelve weeks. We hold helical, bevel-helical and planetary gearboxes, and supply drop-in replacements for SEW-Eurodrive, Flender, Bonfiglioli and David Brown - 10 to 14 days into Botswana for stocked sizes, 4 to 6 weeks made to order, with rebuild-on-exchange. Send me the units on your critical spares list and I'll come back with price and lead time, so you have a second source on file before you need one. | E79: Gearbox lead times for Morupule Coal Mine | F79: omedupe@mcm.co.bw | G79: Plant Manager | H79: Botswana | J79: Mining | K79: B | L79: C078 | M79: English | N79: http://www.linkedin.com/in/oaitse-medupe-b140098a | O79: mcm.co.bw | P79: +267 492 0251 | Q79: 900 | R79: mining & metals | S79: Downtime cost per hour on mill and conveyor drives - lead with lead time and availability | U79: Not contacted
A80: Kabo | B80: Malebang | C80: Morupule Coal Mine | D80: Hi Kabo, At Morupule Coal Mine, the coal conveyor, crusher and screen drives on the plant are the units that stop production when a gearbox goes. The usual answer from suppliers is twelve weeks. We hold helical, bevel-helical and planetary gearboxes, and supply drop-in replacements for SEW-Eurodrive, Flender, Bonfiglioli and David Brown - 10 to 14 days into Botswana for stocked sizes, 4 to 6 weeks made to order, with rebuild-on-exchange. Send me the units on your critical spares list and I'll come back with price and lead time, so you have a second source on file before you need one. | E80: Gearbox lead times for Morupule Coal Mine | F80: kmalebang@mcm.co.bw | G80: Technical Services Manager | H80: Botswana | J80: Mining | K80: B | L80: C078 | M80: English | N80: http://www.linkedin.com/in/kabo-malebang-79513645 | O80: mcm.co.bw | P80: +267 492 0251 | Q80: 900 | R80: mining & metals | S80: Downtime cost per hour on mill and conveyor drives - lead with lead time and availability | U80: Not contacted
A81: Onnete | B81: Raditsi | C81: Sandfire | D81: Hi Onnete, At Sandfire, the mill and conveyor drives on the Motheo circuit are the units that stop production when a gearbox goes. The usual answer from suppliers is twelve weeks. We hold helical, bevel-helical and planetary gearboxes, and supply drop-in replacements for SEW-Eurodrive, Flender, Bonfiglioli and David Brown - 10 to 14 days into Botswana for stocked sizes, 4 to 6 weeks made to order, with rebuild-on-exchange. Send me the units on your critical spares list and I'll come back with price and lead time, so you have a second source on file before you need one. | E81: Gearbox lead times for Sandfire | F81: onnete.raditsi@sandfire.com.au | G81: Reliability Engineer | H81: Botswana | I81: Maun | J81: Mining | K81: B | L81: C108 | M81: English | N81: http://www.linkedin.com/in/onnete-raditsi-270a7ba3 | O81: sandfire.com.au | P81: +61 8 6430 3800 | Q81: 1300 | R81: mining & metals | S81: Downtime cost per hour on mill and conveyor drives - lead with lead time and availability | T81: HQ abroad (Australia) - verify local buying authority | U81: Not contacted
A82: Teto | B82: Ntswaneng | C82: Sandfire | D82: Hi Teto, At Sandfire, the mill and conveyor drives on the Motheo circuit are the units that stop production when a gearbox goes. The usual answer from suppliers is twelve weeks. We hold helical, bevel-helical and planetary gearboxes, and supply drop-in replacements for SEW-Eurodrive, Flender, Bonfiglioli and David Brown - 10 to 14 days into Botswana for stocked sizes, 4 to 6 weeks made to order, with rebuild-on-exchange. Send me the units on your critical spares list and I'll come back with price and lead time, so you have a second source on file before you need one. | E82: Gearbox lead times for Sandfire | F82: teto.ntswaneng@sandfire.com.au | G82: Reliability Engineer | H82: Botswana | I82: Ghanzi | J82: Mining | K82: B | L82: C108 | M82: English | N82: http://www.linkedin.com/in/teto-ntswaneng-403391b1 | O82: sandfire.com.au | P82: +61 8 6430 3800 | Q82: 1300 | R82: mining & metals | S82: Downtime cost per hour on mill and conveyor drives - lead with lead time and availability | T82: HQ abroad (Australia) - verify local buying authority | U82: Not contacted
A83: Airborne | B83: Clark | C83: UMS Group (United Mining Services) | D83: Hi Airborne, At UMS Group (United Mining Services), the winders, hoists and shaft equipment you install and maintain are the units that stop production when a gearbox goes. The usual answer from suppliers is twelve weeks. We hold helical, bevel-helical and planetary gearboxes, and supply drop-in replacements for SEW-Eurodrive, Flender, Bonfiglioli and David Brown - 10 to 14 days into Botswana for stocked sizes, 4 to 6 weeks made to order, with rebuild-on-exchange. Send me the units on your critical spares list and I'll come back with price and lead time, so you have a second source on file before you need one. | E83: Gearbox lead times for UMS Group (United Mining Services) | F83: airbornec@umsint.com | G83: Mechanical Engineer | H83: Botswana | I83: Gaborone | J83: Mining | K83: B | L83: C123 | M83: English | N83: http://www.linkedin.com/in/airborne-clark-505158223 | O83: umsint.com | P83: +27 11 445 4300 | Q83: 450 | R83: mining & metals | S83: Downtime cost per hour on mill and conveyor drives - lead with lead time and availability | T83: HQ abroad (South Africa) - verify local buying authority | U83: Not contacted
A84: Chimuka | B84: Christopher | C84: Barrick Mining Corporation | D84: Hi Chimuka, At Barrick Mining Corporation, the mill and overland conveyor drives at Lumwana are the units that stop production when a gearbox goes. The usual answer from suppliers is twelve weeks. We hold helical, bevel-helical and planetary gearboxes, and supply drop-in replacements for SEW-Eurodrive, Flender, Bonfiglioli and David Brown - 10 to 14 days into Zambia for stocked sizes, 4 to 6 weeks made to order, with rebuild-on-exchange. Send me the units on your critical spares list and I'll come back with price and lead time, so you have a second source on file before you need one. | E84: Gearbox lead times for Barrick Mining Corporation | F84: cchimuka@barrick.com | G84: Assistant Maintenance Manager | H84: Zambia | I84: Solwezi | J84: Mining | K84: B | L84: C019 | M84: English | N84: http://www.linkedin.com/in/christopher-chimuka-8661ba63 | O84: barrick.com | P84: +1 416-861-9911 | Q84: 6500 | R84: mining & metals | S84: Downtime cost per hour on mill and conveyor drives - lead with lead time and availability | T84: HQ abroad (Canada) - verify local buying authority | U84: Not contacted
A85: Anton | B85: Khoroshev | C85: First Quantum Minerals | D85: Hi Anton, At First Quantum Minerals, the SAG and ball mill drives, overland conveyors and crusher drives at Kansanshi and Sentinel are the units that stop production when a gearbox goes. The usual answer from suppliers is twelve weeks. We hold helical, bevel-helical and planetary gearboxes, and supply drop-in replacements for SEW-Eurodrive, Flender, Bonfiglioli and David Brown - 10 to 14 days into Zambia for stocked sizes, 4 to 6 weeks made to order, with rebuild-on-exchange. Send me the units on your critical spares list and I'll come back with price and lead time, so you have a second source on file before you need one. | E85: Gearbox lead times for First Quantum Minerals | F85: anton.khoroshev@fqml.com | G85: Plant Maintenance Manager | H85: Zambia | I85: Solwezi | J85: Mining | K85: B | L85: C054 | M85: English | N85: http://www.linkedin.com/in/anton-khoroshev-460264b6 | O85: first-quantum.com | P85: +1 416-361-6400 | Q85: 20000 | R85: mining & metals | S85: Downtime cost per hour on mill and conveyor drives - lead with lead time and availability | T85: HQ abroad (Canada) - verify local buying authority | U85: Not contacted
A86: Theuns | B86: Hamman | C86: First Quantum Minerals | D86: Hi Theuns, At First Quantum Minerals, the SAG and ball mill drives, overland conveyors and crusher drives at Kansanshi and Sentinel are the units that stop production when a gearbox goes. The usual answer from suppliers is twelve weeks. We hold helical, bevel-helical and planetary gearboxes, and supply drop-in replacements for SEW-Eurodrive, Flender, Bonfiglioli and David Brown - 10 to 14 days into Zambia for stocked sizes, 4 to 6 weeks made to order, with rebuild-on-exchange. Send me the units on your critical spares list and I'll come back with price and lead time, so you have a second source on file before you need one. | E86: Gearbox lead times for First Quantum Minerals | F86: theuns.hamman@fqml.com | G86: Engineering Manager Process Plant | H86: Zambia | I86: Solwezi | J86: Mining | K86: B | L86: C054 | M86: English | N86: http://www.linkedin.com/in/theuns-hamman-45781484 | O86: first-quantum.com | P86: +1 416-361-6400 | Q86: 20000 | R86: mining & metals | S86: Downtime cost per hour on mill and conveyor drives - lead with lead time and availability | T86: HQ abroad (Canada) - verify local buying authority | U86: Not contacted
A87: Sylvester | B87: Mulanshoka | C87: First Quantum Minerals | D87: Hi Sylvester, At First Quantum Minerals, the SAG and ball mill drives, overland conveyors and crusher drives at Kansanshi and Sentinel are the units that stop production when a gearbox goes. The usual answer from suppliers is twelve weeks. We hold helical, bevel-helical and planetary gearboxes, and supply drop-in replacements for SEW-Eurodrive, Flender, Bonfiglioli and David Brown - 10 to 14 days into Zambia for stocked sizes, 4 to 6 weeks made to order, with rebuild-on-exchange. Send me the units on your critical spares list and I'll come back with price and lead time, so you have a second source on file before you need one. | E87: Gearbox lead times for First Quantum Minerals | F87: sylvester.mulanshoka@fqml.com | G87: Senior Reliability Engineer | H87: Zambia | J87: Mining | K87: B | L87: C054 | M87: English | N87: http://www.linkedin.com/in/sylvester-mulanshoka-822229a6 | O87: first-quantum.com | P87: +1 416-361-6400 | Q87: 20000 | R87: mining & metals | S87: Downtime cost per hour on mill and conveyor drives - lead with lead time and availability | T87: HQ abroad (Canada) - verify local buying authority | U87: Not contacted
A88: Lutoba | B88: Kayamba | C88: First Quantum Minerals | D88: Hi Lutoba, At First Quantum Minerals, the SAG and ball mill drives, overland conveyors and crusher drives at Kansanshi and Sentinel are the units that stop production when a gearbox goes. The usual answer from suppliers is twelve weeks. We hold helical, bevel-helical and planetary gearboxes, and supply drop-in replacements for SEW-Eurodrive, Flender, Bonfiglioli and David Brown - 10 to 14 days into Zambia for stocked sizes, 4 to 6 weeks made to order, with rebuild-on-exchange. Send me the units on your critical spares list and I'll come back with price and lead time, so you have a second source on file before you need one. | E88: Gearbox lead times for First Quantum Minerals | F88: lutoba.kayamba@fqml.com | G88: Senior Reliability Engineer | H88: Zambia | I88: Solwezi | J88: Mining | K88: B | L88: C054 | M88: English | N88: http://www.linkedin.com/in/lutoba-kayamba-b04539128 | O88: first-quantum.com | P88: +1 416-361-6400 | Q88: 20000 | R88: mining & metals | S88: Downtime cost per hour on mill and conveyor drives - lead with lead time and availability | T88: HQ abroad (Canada) - verify local buying authority | U88: Not contacted
A89: Ernest | B89: Tembo | C89: First Quantum Minerals | D89: Hi Ernest, At First Quantum Minerals, the SAG and ball mill drives, overland conveyors and crusher drives at Kansanshi and Sentinel are the units that stop production when a gearbox goes. The usual answer from suppliers is twelve weeks. We hold helical, bevel-helical and planetary gearboxes, and supply drop-in replacements for SEW-Eurodrive, Flender, Bonfiglioli and David Brown - 10 to 14 days into Zambia for stocked sizes, 4 to 6 weeks made to order, with rebuild-on-exchange. Send me the units on your critical spares list and I'll come back with price and lead time, so you have a second source on file before you need one. | E89: Gearbox lead times for First Quantum Minerals | F89: ernest.tembo@fqml.com | G89: Senior Reliability Engineer | H89: Zambia | I89: Lusaka | J89: Mining | K89: B | L89: C054 | M89: English | N89: http://www.linkedin.com/in/ernest-tembo-9321ba1b3 | O89: first-quantum.com | P89: +1 416-361-6400 | Q89: 20000 | R89: mining & metals | S89: Downtime cost per hour on mill and conveyor drives - lead with lead time and availability | T89: HQ abroad (Canada) - verify local buying authority | U89: Not contacted
A90: Wesley | B90: Yowela | C90: First Quantum Minerals | D90: Hi Wesley, At First Quantum Minerals, the SAG and ball mill drives, overland conveyors and crusher drives at Kansanshi and Sentinel are the units that stop production when a gearbox goes. The usual answer from suppliers is twelve weeks. We hold helical, bevel-helical and planetary gearboxes, and supply drop-in replacements for SEW-Eurodrive, Flender, Bonfiglioli and David Brown - 10 to 14 days into Zambia for stocked sizes, 4 to 6 weeks made to order, with rebuild-on-exchange. Send me the units on your critical spares list and I'll come back with price and lead time, so you have a second source on file before you need one. | E90: Gearbox lead times for First Quantum Minerals | F90: wesley.yowela@fqml.com | G90: Reliability Engineer | H90: Zambia | I90: Lusaka | J90: Mining | K90: B | L90: C054 | M90: English | N90: http://www.linkedin.com/in/wesley-yowela-8b4072242 | O90: first-quantum.com | P90: +1 416-361-6400 | Q90: 20000 | R90: mining & metals | S90: Downtime cost per hour on mill and conveyor drives - lead with lead time and availability | T90: HQ abroad (Canada) - verify local buying authority | U90: Not contacted
A91: Mildred | B91: Kapika | C91: First Quantum Minerals | D91: Hi Mildred, At First Quantum Minerals, the SAG and ball mill drives, overland conveyors and crusher drives at Kansanshi and Sentinel are the units that stop production when a gearbox goes. The usual answer from suppliers is twelve weeks. We hold helical, bevel-helical and planetary gearboxes, and supply drop-in replacements for SEW-Eurodrive, Flender, Bonfiglioli and David Brown - 10 to 14 days into Zambia for stocked sizes, 4 to 6 weeks made to order, with rebuild-on-exchange. Send me the units on your critical spares list and I'll come back with price and lead time, so you have a second source on file before you need one. | E91: Gearbox lead times for First Quantum Minerals | F91: mildred.kapika@fqml.com | G91: Reliability Engineer | H91: Zambia | I91: Mufulira | J91: Mining | K91: B | L91: C054 | M91: English | N91: http://www.linkedin.com/in/mildred-kapika-8073a4216 | O91: first-quantum.com | P91: +1 416-361-6400 | Q91: 20000 | R91: mining & metals | S91: Downtime cost per hour on mill and conveyor drives - lead with lead time and availability | T91: HQ abroad (Canada) - verify local buying authority | U91: Not contacted
A92: Jane | B92: George | C92: First Quantum Minerals | D92: Hi Jane, At First Quantum Minerals, the SAG and ball mill drives, overland conveyors and crusher drives at Kansanshi and Sentinel are the units that stop production when a gearbox goes. The usual answer from suppliers is twelve weeks. We hold helical, bevel-helical and planetary gearboxes, and supply drop-in replacements for SEW-Eurodrive, Flender, Bonfiglioli and David Brown - 10 to 14 days into Zambia for stocked sizes, 4 to 6 weeks made to order, with rebuild-on-exchange. Send me the units on your critical spares list and I'll come back with price and lead time, so you have a second source on file before you need one. | E92: Gearbox lead times for First Quantum Minerals | F92: jane.george@fqml.com | G92: Reliability Engineer | H92: Zambia | J92: Mining | K92: B | L92: C054 | M92: English | N92: http://www.linkedin.com/in/jane-george-40b42315b | O92: first-quantum.com | P92: +1 416-361-6400 | Q92: 20000 | R92: mining & metals | S92: Downtime cost per hour on mill and conveyor drives - lead with lead time and availability | T92: HQ abroad (Canada) - verify local buying authority | U92: Not contacted
A93: Michael | B93: Mumamba | C93: First Quantum Minerals | D93: Hi Michael, At First Quantum Minerals, the SAG and ball mill drives, overland conveyors and crusher drives at Kansanshi and Sentinel are the units that stop production when a gearbox goes. The usual answer from suppliers is twelve weeks. We hold helical, bevel-helical and planetary gearboxes, and supply drop-in replacements for SEW-Eurodrive, Flender, Bonfiglioli and David Brown - 10 to 14 days into Zambia for stocked sizes, 4 to 6 weeks made to order, with rebuild-on-exchange. Send me the units on your critical spares list and I'll come back with price and lead time, so you have a second source on file before you need one. | E93: Gearbox lead times for First Quantum Minerals | F93: michael.mumamba@fqml.com | G93: Reliability Engineer | H93: Zambia | J93: Mining | K93: B | L93: C054 | M93: English | N93: http://www.linkedin.com/in/michael-mumamba-3562a6212 | O93: first-quantum.com | P93: +1 416-361-6400 | Q93: 20000 | R93: mining & metals | S93: Downtime cost per hour on mill and conveyor drives - lead with lead time and availability | T93: HQ abroad (Canada) - verify local buying authority | U93: Not contacted
A94: Dalitso | B94: Ngoma | C94: First Quantum Minerals | D94: Hi Dalitso, At First Quantum Minerals, the SAG and ball mill drives, overland conveyors and crusher drives at Kansanshi and Sentinel are the units that stop production when a gearbox goes. The usual answer from suppliers is twelve weeks. We hold helical, bevel-helical and planetary gearboxes, and supply drop-in replacements for SEW-Eurodrive, Flender, Bonfiglioli and David Brown - 10 to 14 days into Zambia for stocked sizes, 4 to 6 weeks made to order, with rebuild-on-exchange. Send me the units on your critical spares list and I'll come back with price and lead time, so you have a second source on file before you need one. | E94: Gearbox lead times for First Quantum Minerals | F94: dalitso.ngoma@fqml.com | G94: Reliability Engineer | H94: Zambia | J94: Mining | K94: B | L94: C054 | M94: English | N94: http://www.linkedin.com/in/dalitso-ngoma-37a43692 | O94: first-quantum.com | P94: +1 416-361-6400 | Q94: 20000 | R94: mining & metals | S94: Downtime cost per hour on mill and conveyor drives - lead with lead time and availability | T94: HQ abroad (Canada) - verify local buying authority | U94: Not contacted
A95: Isaac | B95: Kabula | C95: First Quantum Minerals | D95: Hi Isaac, At First Quantum Minerals, the SAG and ball mill drives, overland conveyors and crusher drives at Kansanshi and Sentinel are the units that stop production when a gearbox goes. The usual answer from suppliers is twelve weeks. We hold helical, bevel-helical and planetary gearboxes, and supply drop-in replacements for SEW-Eurodrive, Flender, Bonfiglioli and David Brown - 10 to 14 days into Zambia for stocked sizes, 4 to 6 weeks made to order, with rebuild-on-exchange. Send me the units on your critical spares list and I'll come back with price and lead time, so you have a second source on file before you need one. | E95: Gearbox lead times for First Quantum Minerals | F95: isaac.kabula@fqml.com | G95: Maintenance Reliability Engineer | H95: Zambia | J95: Mining | K95: B | L95: C054 | M95: English | N95: http://www.linkedin.com/in/isaac-kabula-23b3b31ab | O95: first-quantum.com | P95: +1 416-361-6400 | Q95: 20000 | R95: mining & metals | S95: Downtime cost per hour on mill and conveyor drives - lead with lead time and availability | T95: HQ abroad (Canada) - verify local buying authority | U95: Not contacted
A96: Bright | B96: Kamawu | C96: First Quantum Minerals | D96: Hi Bright, At First Quantum Minerals, the SAG and ball mill drives, overland conveyors and crusher drives at Kansanshi and Sentinel are the units that stop production when a gearbox goes. The usual answer from suppliers is twelve weeks. We hold helical, bevel-helical and planetary gearboxes, and supply drop-in replacements for SEW-Eurodrive, Flender, Bonfiglioli and David Brown - 10 to 14 days into Zambia for stocked sizes, 4 to 6 weeks made to order, with rebuild-on-exchange. Send me the units on your critical spares list and I'll come back with price and lead time, so you have a second source on file before you need one. | E96: Gearbox lead times for First Quantum Minerals | F96: bright.kamawu@fqml.com | G96: Reliability Engineer, Electrical | H96: Zambia | J96: Mining | K96: B | L96: C054 | M96: English | N96: http://www.linkedin.com/in/brightkamawu | O96: first-quantum.com | P96: +1 416-361-6400 | Q96: 20000 | R96: mining & metals | S96: Downtime cost per hour on mill and conveyor drives - lead with lead time and availability | T96: HQ abroad (Canada) - verify local buying authority | U96: Not contacted
A97: Vinod | B97: Purohit | C97: Konkola Copper Mines plc | D97: Hi Vinod, At Konkola Copper Mines plc, the concentrator mill drives, shaft winders and tailings leach plant drives at Konkola and Nchanga are the units that stop production when a gearbox goes. The usual answer from suppliers is twelve weeks. We hold helical, bevel-helical and planetary gearboxes, and supply drop-in replacements for SEW-Eurodrive, Flender, Bonfiglioli and David Brown - 10 to 14 days into Zambia for stocked sizes, 4 to 6 weeks made to order, with rebuild-on-exchange. Send me the units on your critical spares list and I'll come back with price and lead time, so you have a second source on file before you need one. | E97: Gearbox lead times for Konkola Copper Mines plc | F97: vinod.purohit@kcm.co.zm | G97: Maintenance Manager | H97: Zambia | I97: Chingola | J97: Mining | K97: B | L97: C067 | M97: English | N97: http://www.linkedin.com/in/vinod-kumar-purohit-328a546b | O97: kcm.co.zm | P97: +260 21 2350604 | Q97: 14000 | R97: mining & metals | S97: Downtime cost per hour on mill and conveyor drives - lead with lead time and availability | U97: Not contacted
A98: Laison | B98: Malindi | C98: Konkola Copper Mines plc | D98: Hi Laison, At Konkola Copper Mines plc, the concentrator mill drives, shaft winders and tailings leach plant drives at Konkola and Nchanga are the units that stop production when a gearbox goes. The usual answer from suppliers is twelve weeks. We hold helical, bevel-helical and planetary gearboxes, and supply drop-in replacements for SEW-Eurodrive, Flender, Bonfiglioli and David Brown - 10 to 14 days into Zambia for stocked sizes, 4 to 6 weeks made to order, with rebuild-on-exchange. Send me the units on your critical spares list and I'll come back with price and lead time, so you have a second source on file before you need one. | E98: Gearbox lead times for Konkola Copper Mines plc | F98: laison.malindi@kcm.co.zm | G98: Plant Manager | H98: Zambia | J98: Mining | K98: B | L98: C067 | M98: English | N98: http://www.linkedin.com/in/laison-malindi-528a0947 | O98: kcm.co.zm | P98: +260 21 2350604 | Q98: 14000 | R98: mining & metals | S98: Downtime cost per hour on mill and conveyor drives - lead with lead time and availability | U98: Not contacted
A99: Yoram | B99: Kapai | C99: Konkola Copper Mines plc | D99: Hi Yoram, At Konkola Copper Mines plc, the concentrator mill drives, shaft winders and tailings leach plant drives at Konkola and Nchanga are the units that stop production when a gearbox goes. The usual answer from suppliers is twelve weeks. We hold helical, bevel-helical and planetary gearboxes, and supply drop-in replacements for SEW-Eurodrive, Flender, Bonfiglioli and David Brown - 10 to 14 days into Zambia for stocked sizes, 4 to 6 weeks made to order, with rebuild-on-exchange. Send me the units on your critical spares list and I'll come back with price and lead time, so you have a second source on file before you need one. | E99: Gearbox lead times for Konkola Copper Mines plc | F99: yoram.kapai@kcm.co.zm | G99: Plant Manager | H99: Zambia | J99: Mining | K99: B | L99: C067 | M99: English | N99: http://www.linkedin.com/in/yoram-kapai-75760522 | O99: kcm.co.zm | P99: +260 21 2350604 | Q99: 14000 | R99: mining & metals | S99: Downtime cost per hour on mill and conveyor drives - lead with lead time and availability | U99: Not contacted
A100: Franklin | B100: Ngandu | C100: Konkola Copper Mines plc | D100: Hi Franklin, At Konkola Copper Mines plc, the concentrator mill drives, shaft winders and tailings leach plant drives at Konkola and Nchanga are the units that stop production when a gearbox goes. The usual answer from suppliers is twelve weeks. We hold helical, bevel-helical and planetary gearboxes, and supply drop-in replacements for SEW-Eurodrive, Flender, Bonfiglioli and David Brown - 10 to 14 days into Zambia for stocked sizes, 4 to 6 weeks made to order, with rebuild-on-exchange. Send me the units on your critical spares list and I'll come back with price and lead time, so you have a second source on file before you need one. | E100: Gearbox lead times for Konkola Copper Mines plc | F100: franklin.ngandu@kcm.co.zm | G100: Plant Manager | H100: Zambia | J100: Mining | K100: B | L100: C067 | M100: English | N100: http://www.linkedin.com/in/franklin-bwalya-ngandu-4a0a0678 | O100: kcm.co.zm | P100: +260 21 2350604 | Q100: 14000 | R100: mining & metals | S100: Downtime cost per hour on mill and conveyor drives - lead with lead time and availability | U100: Not contacted
...

Sheet Read me
A1: Gearbox Leads - Batch 1
A3: What this is
A4: 200 contacts in Botswana, Zambia and Angola who buy or resell industrial gearboxes.
A5: Every one has an Apollo-verified work email. Sourced 28 July 2026.
A7: The emails
A8: 136 companies, 136 different emails - one written for each company.
A9: Each email names that company's own equipment. First Quantum's mentions the Kansanshi and
A10: Sentinel mill and conveyor drives. Chilanga Cement's mentions the raw mill, kiln and clinker
A11: conveyors. Nors Group's mentions the final drives on the machines they service.
A13: On the Leads tab, column K holds the email for that person with their name already written in.
A14: It is ready to send: copy the cell, paste into your mail client, add your signature.
A15: The Mails tab shows the same emails once per company, if you prefer to read them that way.
... A48: Batch 4 - Namibia, DRC Copperbelt, Mozambique, Zimbabwe
